Workbook

Sheet Base versus Growth
A1: Base versus Growth
A2: Mend — Forecast and runway · Base
A4: Variable / dimension | B4: 2026-10 | C4: 2026-10 > Growth | D4: 2026-11 | E4: 2026-11 > Growth | F4: 2026-12 | G4: 2026-12 > Growth | H4: 2027-01 | I4: 2027-01 > Growth | J4: 2027-02 | K4: 2027-02 > Growth | L4: 2027-03 | M4: 2027-03 > Growth | N4: 2027-04 | O4: 2027-04 > Growth | P4: 2027-05 | Q4: 2027-05 > Growth | R4: 2027-06 | S4: 2027-06 > Growth | T4: 2027-07 | U4: 2027-07 > Growth | V4: 2027-08 | W4: 2027-08 > Growth | X4: 2027-09 | Y4: 2027-09 > Growth | Z4: 2027-10 | AA4: 2027-10 > Growth | AB4: 2027-11 | AC4: 2027-11 > Growth | AD4: 2027-12 | AE4: 2027-12 > Growth | AF4: 2028-01 | AG4: 2028-01 > Growth | AH4: 2028-02 | AI4: 2028-02 > Growth | AJ4: 2028-03 | AK4: 2028-03 > Growth
A5: Paying teams | B5: =IF('Model inputs'!U40="","",'Model inputs'!U40) -> 50 | C5: =IF('Model inputs'!U41="","",'Model inputs'!U41) -> 50 | D5: ='Base versus Growth'!B5*(1+'Model inputs'!U30) -> 50 | E5: ='Base versus Growth'!C5*(1+'Model inputs'!U31) -> 55 | F5: ='Base versus Growth'!D5*(1+'Model inputs'!U30) -> 50 | G5: ='Base versus Growth'!E5*(1+'Model inputs'!U31) -> 60.5 | H5: ='Base versus Growth'!F5*(1+'Model inputs'!U30) -> 50 | I5: ='Base versus Growth'!G5*(1+'Model inputs'!U31) -> 66.55 | J5: ='Base versus Growth'!H5*(1+'Model inputs'!U30) -> 50 | K5: ='Base versus Growth'!I5*(1+'Model inputs'!U31) -> 73.205 | L5: ='Base versus Growth'!J5*(1+'Model inputs'!U30) -> 50 | M5: ='Base versus Growth'!K5*(1+'Model inputs'!U31) -> 80.5255 | N5: ='Base versus Growth'!L5*(1+'Model inputs'!U30) -> 50 | O5: ='Base versus Growth'!M5*(1+'Model inputs'!U31) -> 88.57805 | P5: ='Base versus Growth'!N5*(1+'Model inputs'!U30) -> 50 | Q5: ='Base versus Growth'!O5*(1+'Model inputs'!U31) -> 97.435855 | R5: ='Base versus Growth'!P5*(1+'Model inputs'!U30) -> 50 | S5: ='Base versus Growth'!Q5*(1+'Model inputs'!U31) -> 107.17944 | T5: ='Base versus Growth'!R5*(1+'Model inputs'!U30) -> 50 | U5: ='Base versus Growth'!S5*(1+'Model inputs'!U31) -> 117.89738 | V5: ='Base versus Growth'!T5*(1+'Model inputs'!U30) -> 50 | W5: ='Base versus Growth'!U5*(1+'Model inputs'!U31) -> 129.68712 | X5: ='Base versus Growth'!V5*(1+'Model inputs'!U30) -> 50 | Y5: ='Base versus Growth'!W5*(1+'Model inputs'!U31) -> 142.65584 | Z5: ='Base versus Growth'!X5*(1+'Model inputs'!U30) -> 50 | AA5: ='Base versus Growth'!Y5*(1+'Model inputs'!U31) -> 156.92142 | AB5: ='Base versus Growth'!Z5*(1+'Model inputs'!U30) -> 50 | AC5: ='Base versus Growth'!AA5*(1+'Model inputs'!U31) -> 172.61356 | AD5: ='Base versus Growth'!AB5*(1+'Model inputs'!U30) -> 50 | AE5: ='Base versus Growth'!AC5*(1+'Model inputs'!U31) -> 189.87492 | AF5: ='Base versus Growth'!AD5*(1+'Model inputs'!U30) -> 50 | AG5: ='Base versus Growth'!AE5*(1+'Model inputs'!U31) -> 208.86241 | AH5: ='Base versus Growth'!AF5*(1+'Model inputs'!U30) -> 50 | AI5: ='Base versus Growth'!AG5*(1+'Model inputs'!U31) -> 229.74865 | AJ5: ='Base versus Growth'!AH5*(1+'Model inputs'!U30) -> 50 | AK5: ='Base versus Growth'!AI5*(1+'Model inputs'!U31) -> 252.72351
A6: Monthly revenue | B6: ='Base versus Growth'!B5*'Model inputs'!U35 -> 2450 | C6: ='Base versus Growth'!C5*'Model inputs'!U36 -> 2450 | D6: ='Base versus Growth'!D5*'Model inputs'!U35 -> 2450 | E6: ='Base versus Growth'!E5*'Model inputs'!U36 -> 2695 | F6: ='Base versus Growth'!F5*'Model inputs'!U35 -> 2450 | G6: ='Base versus Growth'!G5*'Model inputs'!U36 -> 2964.5 | H6: ='Base versus Growth'!H5*'Model inputs'!U35 -> 2450 | I6: ='Base versus Growth'!I5*'Model inputs'!U36 -> 3260.95 | J6: ='Base versus Growth'!J5*'Model inputs'!U35 -> 2450 | K6: ='Base versus Growth'!K5*'Model inputs'!U36 -> 3587.045 | L6: ='Base versus Growth'!L5*'Model inputs'!U35 -> 2450 | M6: ='Base versus Growth'!M5*'Model inputs'!U36 -> 3945.7495 | N6: ='Base versus Growth'!N5*'Model inputs'!U35 -> 2450 | O6: ='Base versus Growth'!O5*'Model inputs'!U36 -> 4340.3245 | P6: ='Base versus Growth'!P5*'Model inputs'!U35 -> 2450 | Q6: ='Base versus Growth'!Q5*'Model inputs'!U36 -> 4774.3569 | R6: ='Base versus Growth'!R5*'Model inputs'!U35 -> 2450 | S6: ='Base versus Growth'!S5*'Model inputs'!U36 -> 5251.7926 | T6: ='Base versus Growth'!T5*'Model inputs'!U35 -> 2450 | U6: ='Base versus Growth'!U5*'Model inputs'!U36 -> 5776.9718 | V6: ='Base versus Growth'!V5*'Model inputs'!U35 -> 2450 | W6: ='Base versus Growth'!W5*'Model inputs'!U36 -> 6354.669 | X6: ='Base versus Growth'!X5*'Model inputs'!U35 -> 2450 | Y6: ='Base versus Growth'!Y5*'Model inputs'!U36 -> 6990.1359 | Z6: ='Base versus Growth'!Z5*'Model inputs'!U35 -> 2450 | AA6: ='Base versus Growth'!AA5*'Model inputs'!U36 -> 7689.1495 | AB6: ='Base versus Growth'!AB5*'Model inputs'!U35 -> 2450 | AC6: ='Base versus Growth'!AC5*'Model inputs'!U36 -> 8458.0645 | AD6: ='Base versus Growth'!AD5*'Model inputs'!U35 -> 2450 | AE6: ='Base versus Growth'!AE5*'Model inputs'!U36 -> 9303.8709 | AF6: ='Base versus Growth'!AF5*'Model inputs'!U35 -> 2450 | AG6: ='Base versus Growth'!AG5*'Model inputs'!U36 -> 10234.258 | AH6: ='Base versus Growth'!AH5*'Model inputs'!U35 -> 2450 | AI6: ='Base versus Growth'!AI5*'Model inputs'!U36 -> 11257.684 | AJ6: ='Base versus Growth'!AJ5*'Model inputs'!U35 -> 2450 | AK6: ='Base versus Growth'!AK5*'Model inputs'!U36 -> 12383.452
A7: Gross margin | B7: =IFERROR('18-month forecast'!B11/'Base versus Growth'!B6,"") -> 0.30612245 | C7: =IFERROR('Model inputs'!C21/'Base versus Growth'!C6,"") -> 0.30612245 | D7: =IFERROR('18-month forecast'!C11/'Base versus Growth'!D6,"") -> 0.30612245 | E7: =IFERROR('Model inputs'!D21/'Base versus Growth'!E6,"") -> 0.3135436 | F7: =IFERROR('18-month forecast'!D11/'Base versus Growth'!F6,"") -> 0.30612245 | G7: =IFERROR('Model inputs'!E21/'Base versus Growth'!G6,"") -> 0.3202901 | H7: =IFERROR('18-month forecast'!E11/'Base versus Growth'!H6,"") -> 0.30612245 | I7: =IFERROR('Model inputs'!F21/'Base versus Growth'!I6,"") -> 0.32642328 | J7: =IFERROR('18-month forecast'!F11/'Base versus Growth'!J6,"") -> 0.30612245 | K7: =IFERROR('Model inputs'!G21/'Base versus Growth'!K6,"") -> 0.3319989 | L7: =IFERROR('18-month forecast'!G11/'Base versus Growth'!L6,"") -> 0.30612245 | M7: =IFERROR('Model inputs'!H21/'Base versus Growth'!M6,"") -> 0.33706765 | N7: =IFERROR('18-month forecast'!H11/'Base versus Growth'!N6,"") -> 0.30612245 | O7: =IFERROR('Model inputs'!I21/'Base versus Growth'!O6,"") -> 0.3416756 | P7: =IFERROR('18-month forecast'!I11/'Base versus Growth'!P6,"") -> 0.30612245 | Q7: =IFERROR('Model inputs'!J21/'Base versus Growth'!Q6,"") -> 0.34586464 | R7: =IFERROR('18-month forecast'!J11/'Base versus Growth'!R6,"") -> 0.30612245 | S7: =IFERROR('Model inputs'!K21/'Base versus Growth'!S6,"") -> 0.34967287 | T7: =IFERROR('18-month forecast'!K11/'Base versus Growth'!T6,"") -> 0.30612245 | U7: =IFERROR('Model inputs'!L21/'Base versus Growth'!U6,"") -> 0.35313489 | V7: =IFERROR('18-month forecast'!L11/'Base versus Growth'!V6,"") -> 0.30612245 | W7: =IFERROR('Model inputs'!M21/'Base versus Growth'!W6,"") -> 0.35628218 | X7: =IFERROR('18-month forecast'!M11/'Base versus Growth'!X6,"") -> 0.30612245 | Y7: =IFERROR('Model inputs'!N21/'Base versus Growth'!Y6,"") -> 0.35914336 | Z7: =IFERROR('18-month forecast'!N11/'Base versus Growth'!Z6,"") -> 0.30612245 | AA7: =IFERROR('Model inputs'!O21/'Base versus Growth'!AA6,"") -> 0.36174442 | AB7: =IFERROR('18-month forecast'!O11/'Base versus Growth'!AB6,"") -> 0.30612245 | AC7: =IFERROR('Model inputs'!P21/'Base versus Growth'!AC6,"") -> 0.36410903 | AD7: =IFERROR('18-month forecast'!P11/'Base versus Growth'!AD6,"") -> 0.30612245 | AE7: =IFERROR('Model inputs'!Q21/'Base versus Growth'!AE6,"") -> 0.36625867 | AF7: =IFERROR('18-month forecast'!Q11/'Base versus Growth'!AF6,"") -> 0.30612245 | AG7: =IFERROR('Model inputs'!R21/'Base versus Growth'!AG6,"") -> 0.36821289 | AH7: =IFERROR('18-month forecast'!R11/'Base versus Growth'!AH6,"") -> 0.30612245 | AI7: =IFERROR('Model inputs'!S21/'Base versus Growth'!AI6,"") -> 0.36998946 | AJ7: =IFERROR('18-month forecast'!S11/'Base versus Growth'!AJ6,"") -> 0.30612245 | AK7: =IFERROR('Model inputs'!T21/'Base versus Growth'!AK6,"") -> 0.37160452
A8: Net cash flow | B8: ='18-month forecast'!B11-'18-month forecast'!B13 -> 750 | C8: ='Model inputs'!C21-'Model inputs'!C19 -> 750 | D8: ='18-month forecast'!C11-'18-month forecast'!C13 -> 750 | E8: ='Model inputs'!D21-'Model inputs'!D19 -> 845 | F8: ='18-month forecast'!D11-'18-month forecast'!D13 -> 750 | G8: ='Model inputs'!E21-'Model inputs'!E19 -> 949.5 | H8: ='18-month forecast'!E11-'18-month forecast'!E13 -> 750 | I8: ='Model inputs'!F21-'Model inputs'!F19 -> 1064.45 | J8: ='18-month forecast'!F11-'18-month forecast'!F13 -> 750 | K8: ='Model inputs'!G21-'Model inputs'!G19 -> 1190.895 | L8: ='18-month forecast'!G11-'18-month forecast'!G13 -> 750 | M8: ='Model inputs'!H21-'Model inputs'!H19 -> 1329.9845 | N8: ='18-month forecast'!H11-'18-month forecast'!H13 -> -7250 | O8: ='Model inputs'!I21-'Model inputs'!I19 -> -6517.017 | P8: ='18-month forecast'!I11-'18-month forecast'!I13 -> -7250 | Q8: ='Model inputs'!J21-'Model inputs'!J19 -> -6348.7188 | R8: ='18-month forecast'!J11-'18-month forecast'!J13 -> -7250 | S8: ='Model inputs'!K21-'Model inputs'!K19 -> -6163.5906 | T8: ='18-month forecast'!K11-'18-month forecast'!K13 -> -7250 | U8: ='Model inputs'!L21-'Model inputs'!L19 -> -5959.9497 | V8: ='18-month forecast'!L11-'18-month forecast'!L13 -> -7250 | W8: ='Model inputs'!M21-'Model inputs'!M19 -> -5735.9447 | X8: ='18-month forecast'!M11-'18-month forecast'!M13 -> -7250 | Y8: ='Model inputs'!N21-'Model inputs'!N19 -> -5489.5391 | Z8: ='18-month forecast'!N11-'18-month forecast'!N13 -> -7250 | AA8: ='Model inputs'!O21-'Model inputs'!O19 -> -5218.493 | AB8: ='18-month forecast'!O11-'18-month forecast'!O13 -> -7250 | AC8: ='Model inputs'!P21-'Model inputs'!P19 -> -4920.3423 | AD8: ='18-month forecast'!P11-'18-month forecast'!P13 -> -7250 | AE8: ='Model inputs'!Q21-'Model inputs'!Q19 -> -4592.3766 | AF8: ='18-month forecast'!Q11-'18-month forecast'!Q13 -> -7250 | AG8: ='Model inputs'!R21-'Model inputs'!R19 -> -4231.6142 | AH8: ='18-month forecast'!R11-'18-month forecast'!R13 -> -7250 | AI8: ='Model inputs'!S21-'Model inputs'!S19 -> -3834.7757 | AJ8: ='18-month forecast'!S11-'18-month forecast'!S13 -> -7250 | AK8: ='Model inputs'!T21-'Model inputs'!T19 -> -3398.2532
A9: Closing cash | B9: =IF(IF(DATE(2026,10,1)=DATE(2026,10,1),IF('Model inputs'!U38="","",'Model inputs'!U38),IF('Model inputs'!B6="","",'Model inputs'!B6))="",0,IF(DATE(2026,10,1)=DATE(2026,10,1),IF('Model inputs'!U38="","",'Model inputs'!U38),IF('Model inputs'!B6="","",'Model inputs'!B6)))+'Base versus Growth'!B8 -> 10750 | C9: =IF(IF(DATE(2026,10,1)=DATE(2026,10,1),IF('Model inputs'!U39="","",'Model inputs'!U39),IF('Model inputs'!B7="","",'Model inputs'!B7))="",0,IF(DATE(2026,10,1)=DATE(2026,10,1),IF('Model inputs'!U39="","",'Model inputs'!U39),IF('Model inputs'!B7="","",'Model inputs'!B7)))+'Base versus Growth'!C8 -> 10750 | D9: =IF(IF(DATE(2026,11,1)=DATE(2026,10,1),IF('Model inputs'!U38="","",'Model inputs'!U38),IF('Base versus Growth'!B9="","",'Base versus Growth'!B9))="",0,IF(DATE(2026,11,1)=DATE(2026,10,1),IF('Model inputs'!U38="","",'Model inputs'!U38),IF('Base versus Growth'!B9="","",'Base versus Growth'!B9)))+'Base versus Growth'!D8 -> 11500 | E9: =IF(IF(DATE(2026,11,1)=DATE(2026,10,1),IF('Model inputs'!U39="","",'Model inputs'!U39),IF('Base versus Growth'!C9="","",'Base versus Growth'!C9))="",0,IF(DATE(2026,11,1)=DATE(2026,10,1),IF('Model inputs'!U39="","",'Model inputs'!U39),IF('Base versus Growth'!C9="","",'Base versus Growth'!C9)))+'Base versus Growth'!E8 -> 11595 | F9: =IF(IF(DATE(2026,12,1)=DATE(2026,10,1),IF('Model inputs'!U38="","",'Model inputs'!U38),IF('Base versus Growth'!D9="","",'Base versus Growth'!D9))="",0,IF(DATE(2026,12,1)=DATE(2026,10,1),IF('Model inputs'!U38="","",'Model inputs'!U38),IF('Base versus Growth'!D9="","",'Base versus Growth'!D9)))+'Base versus Growth'!F8 -> 12250 | G9: =IF(IF(DATE(2026,12,1)=DATE(2026,10,1),IF('Model inputs'!U39="","",'Model inputs'!U39),IF('Base versus Growth'!E9="","",'Base versus Growth'!E9))="",0,IF(DATE(2026,12,1)=DATE(2026,10,1),IF('Model inputs'!U39="","",'Model inputs'!U39),IF('Base versus Growth'!E9="","",'Base versus Growth'!E9)))+'Base versus Growth'!G8 -> 12544.5 | H9: =IF(IF(DATE(2027,1,1)=DATE(2026,10,1),IF('Model inputs'!U38="","",'Model inputs'!U38),IF('Base versus Growth'!F9="","",'Base versus Growth'!F9))="",0,IF(DATE(2027,1,1)=DATE(2026,10,1),IF('Model inputs'!U38="","",'Model inputs'!U38),IF('Base versus Growth'!F9="","",'Base versus Growth'!F9)))+'Base versus Growth'!H8 -> 13000 | I9: =IF(IF(DATE(2027,1,1)=DATE(2026,10,1),IF('Model inputs'!U39="","",'Model inputs'!U39),IF('Base versus Growth'!G9="","",'Base versus Growth'!G9))="",0,IF(DATE(2027,1,1)=DATE(2026,10,1),IF('Model inputs'!U39="","",'Model inputs'!U39),IF('Base versus Growth'!G9="","",'Base versus Growth'!G9)))+'Base versus Growth'!I8 -> 13608.95 | J9: =IF(IF(DATE(2027,2,1)=DATE(2026,10,1),IF('Model inputs'!U38="","",'Model inputs'!U38),IF('Base versus Growth'!H9="","",'Base versus Growth'!H9))="",0,IF(DATE(2027,2,1)=DATE(2026,10,1),IF('Model inputs'!U38="","",'Model inputs'!U38),IF('Base versus Growth'!H9="","",'Base versus Growth'!H9)))+'Base versus Growth'!J8 -> 13750 | K9: =IF(IF(DATE(2027,2,1)=DATE(2026,10,1),IF('Model inputs'!U39="","",'Model inputs'!U39),IF('Base versus Growth'!I9="","",'Base versus Growth'!I9))="",0,IF(DATE(2027,2,1)=DATE(2026,10,1),IF('Model inputs'!U39="","",'Model inputs'!U39),IF('Base versus Growth'!I9="","",'Base versus Growth'!I9)))+'Base versus Growth'!K8 -> 14799.845 | L9: =IF(IF(DATE(2027,3,1)=DATE(2026,10,1),IF('Model inputs'!U38="","",'Model inputs'!U38),IF('Base versus Growth'!J9="","",'Base versus Growth'!J9))="",0,IF(DATE(2027,3,1)=DATE(2026,10,1),IF('Model inputs'!U38="","",'Model inputs'!U38),IF('Base versus Growth'!J9="","",'Base versus Growth'!J9)))+'Base versus Growth'!L8 -> 14500 | M9: =IF(IF(DATE(2027,3,1)=DATE(2026,10,1),IF('Model inputs'!U39="","",'Model inputs'!U39),IF('Base versus Growth'!K9="","",'Base versus Growth'!K9))="",0,IF(DATE(2027,3,1)=DATE(2026,10,1),IF('Model inputs'!U39="","",'Model inputs'!U39),IF('Base versus Growth'!K9="","",'Base versus Growth'!K9)))+'Base versus Growth'!M8 -> 16129.83 | N9: =IF(IF(DATE(2027,4,1)=DATE(2026,10,1),IF('Model inputs'!U38="","",'Model inputs'!U38),IF('Base versus Growth'!L9="","",'Base versus Growth'!L9))="",0,IF(DATE(2027,4,1)=DATE(2026,10,1),IF('Model inputs'!U38="","",'Model inputs'!U38),IF('Base versus Growth'!L9="","",'Base versus Growth'!L9)))+'Base versus Growth'!N8 -> 7250 | O9: =IF(IF(DATE(2027,4,1)=DATE(2026,10,1),IF('Model inputs'!U39="","",'Model inputs'!U39),IF('Base versus Growth'!M9="","",'Base versus Growth'!M9))="",0,IF(DATE(2027,4,1)=DATE(2026,10,1),IF('Model inputs'!U39="","",'Model inputs'!U39),IF('Base versus Growth'!M9="","",'Base versus Growth'!M9)))+'Base versus Growth'!O8 -> 9612.8125 | P9: =IF(IF(DATE(2027,5,1)=DATE(2026,10,1),IF('Model inputs'!U38="","",'Model inputs'!U38),IF('Base versus Growth'!N9="","",'Base versus Growth'!N9))="",0,IF(DATE(2027,5,1)=DATE(2026,10,1),IF('Model inputs'!U38="","",'Model inputs'!U38),IF('Base versus Growth'!N9="","",'Base versus Growth'!N9)))+'Base versus Growth'!P8 -> 0 | Q9: =IF(IF(DATE(2027,5,1)=DATE(2026,10,1),IF('Model inputs'!U39="","",'Model inputs'!U39),IF('Base versus Growth'!O9="","",'Base versus Growth'!O9))="",0,IF(DATE(2027,5,1)=DATE(2026,10,1),IF('Model inputs'!U39="","",'Model inputs'!U39),IF('Base versus Growth'!O9="","",'Base versus Growth'!O9)))+'Base versus Growth'!Q8 -> 3264.0937 | R9: =IF(IF(DATE(2027,6,1)=DATE(2026,10,1),IF('Model inputs'!U38="","",'Model inputs'!U38),IF('Base versus Growth'!P9="","",'Base versus Growth'!P9))="",0,IF(DATE(2027,6,1)=DATE(2026,10,1),IF('Model inputs'!U38="","",'Model inputs'!U38),IF('Base versus Growth'!P9="","",'Base versus Growth'!P9)))+'Base versus Growth'!R8 -> -7250 | S9: =IF(IF(DATE(2027,6,1)=DATE(2026,10,1),IF('Model inputs'!U39="","",'Model inputs'!U39),IF('Base versus Growth'!Q9="","",'Base versus Growth'!Q9))="",0,IF(DATE(2027,6,1)=DATE(2026,10,1),IF('Model inputs'!U39="","",'Model inputs'!U39),IF('Base versus Growth'!Q9="","",'Base versus Growth'!Q9)))+'Base versus Growth'!S8 -> -2899.4969 | T9: =IF(IF(DATE(2027,7,1)=DATE(2026,10,1),IF('Model inputs'!U38="","",'Model inputs'!U38),IF('Base versus Growth'!R9="","",'Base versus Growth'!R9))="",0,IF(DATE(2027,7,1)=DATE(2026,10,1),IF('Model inputs'!U38="","",'Model inputs'!U38),IF('Base versus Growth'!R9="","",'Base versus Growth'!R9)))+'Base versus Growth'!T8 -> -14500 | U9: =IF(IF(DATE(2027,7,1)=DATE(2026,10,1),IF('Model inputs'!U39="","",'Model inputs'!U39),IF('Base versus Growth'!S9="","",'Base versus Growth'!S9))="",0,IF(DATE(2027,7,1)=DATE(2026,10,1),IF('Model inputs'!U39="","",'Model inputs'!U39),IF('Base versus Growth'!S9="","",'Base versus Growth'!S9)))+'Base versus Growth'!U8 -> -8859.4466 | V9: =IF(IF(DATE(2027,8,1)=DATE(2026,10,1),IF('Model inputs'!U38="","",'Model inputs'!U38),IF('Base versus Growth'!T9="","",'Base versus Growth'!T9))="",0,IF(DATE(2027,8,1)=DATE(2026,10,1),IF('Model inputs'!U38="","",'Model inputs'!U38),IF('Base versus Growth'!T9="","",'Base versus Growth'!T9)))+'Base versus Growth'!V8 -> -21750 | W9: =IF(IF(DATE(2027,8,1)=DATE(2026,10,1),IF('Model inputs'!U39="","",'Model inputs'!U39),IF('Base versus Growth'!U9="","",'Base versus Growth'!U9))="",0,IF(DATE(2027,8,1)=DATE(2026,10,1),IF('Model inputs'!U39="","",'Model inputs'!U39),IF('Base versus Growth'!U9="","",'Base versus Growth'!U9)))+'Base versus Growth'!W8 -> -14595.391 | X9: =IF(IF(DATE(2027,9,1)=DATE(2026,10,1),IF('Model inputs'!U38="","",'Model inputs'!U38),IF('Base versus Growth'!V9="","",'Base versus Growth'!V9))="",0,IF(DATE(2027,9,1)=DATE(2026,10,1),IF('Model inputs'!U38="","",'Model inputs'!U38),IF('Base versus Growth'!V9="","",'Base versus Growth'!V9)))+'Base versus Growth'!X8 -> -29000 | Y9: =IF(IF(DATE(2027,9,1)=DATE(2026,10,1),IF('Model inputs'!U39="","",'Model inputs'!U39),IF('Base versus Growth'!W9="","",'Base versus Growth'!W9))="",0,IF(DATE(2027,9,1)=DATE(2026,10,1),IF('Model inputs'!U39="","",'Model inputs'!U39),IF('Base versus Growth'!W9="","",'Base versus Growth'!W9)))+'Base versus Growth'!Y8 -> -20084.93 | Z9: =IF(IF(DATE(2027,10,1)=DATE(2026,10,1),IF('Model inputs'!U38="","",'Model inputs'!U38),IF('Base versus Growth'!X9="","",'Base versus Growth'!X9))="",0,IF(DATE(2027,10,1)=DATE(2026,10,1),IF('Model inputs'!U38="","",'Model inputs'!U38),IF('Base versus Growth'!X9="","",'Base versus Growth'!X9)))+'Base versus Growth'!Z8 -> -36250 | AA9: =IF(IF(DATE(2027,10,1)=DATE(2026,10,1),IF('Model inputs'!U39="","",'Model inputs'!U39),IF('Base versus Growth'!Y9="","",'Base versus Growth'!Y9))="",0,IF(DATE(2027,10,1)=DATE(2026,10,1),IF('Model inputs'!U39="","",'Model inputs'!U39),IF('Base versus Growth'!Y9="","",'Base versus Growth'!Y9)))+'Base versus Growth'!AA8 -> -25303.423 | AB9: =IF(IF(DATE(2027,11,1)=DATE(2026,10,1),IF('Model inputs'!U38="","",'Model inputs'!U38),IF('Base versus Growth'!Z9="","",'Base versus Growth'!Z9))="",0,IF(DATE(2027,11,1)=DATE(2026,10,1),IF('Model inputs'!U38="","",'Model inputs'!U38),IF('Base versus Growth'!Z9="","",'Base versus Growth'!Z9)))+'Base versus Growth'!AB8 -> -43500 | AC9: =IF(IF(DATE(2027,11,1)=DATE(2026,10,1),IF('Model inputs'!U39="","",'Model inputs'!U39),IF('Base versus Growth'!AA9="","",'Base versus Growth'!AA9))="",0,IF(DATE(2027,11,1)=DATE(2026,10,1),IF('Model inputs'!U39="","",'Model inputs'!U39),IF('Base versus Growth'!AA9="","",'Base versus Growth'!AA9)))+'Base versus Growth'!AC8 -> -30223.766 | AD9: =IF(IF(DATE(2027,12,1)=DATE(2026,10,1),IF('Model inputs'!U38="","",'Model inputs'!U38),IF('Base versus Growth'!AB9="","",'Base versus Growth'!AB9))="",0,IF(DATE(2027,12,1)=DATE(2026,10,1),IF('Model inputs'!U38="","",'Model inputs'!U38),IF('Base versus Growth'!AB9="","",'Base versus Growth'!AB9)))+'Base versus Growth'!AD8 -> -50750 | AE9: =IF(IF(DATE(2027,12,1)=DATE(2026,10,1),IF('Model inputs'!U39="","",'Model inputs'!U39),IF('Base versus Growth'!AC9="","",'Base versus Growth'!AC9))="",0,IF(DATE(2027,12,1)=DATE(2026,10,1),IF('Model inputs'!U39="","",'Model inputs'!U39),IF('Base versus Growth'!AC9="","",'Base versus Growth'!AC9)))+'Base versus Growth'!AE8 -> -34816.142 | AF9: =IF(IF(DATE(2028,1,1)=DATE(2026,10,1),IF('Model inputs'!U38="","",'Model inputs'!U38),IF('Base versus Growth'!AD9="","",'Base versus Growth'!AD9))="",0,IF(DATE(2028,1,1)=DATE(2026,10,1),IF('Model inputs'!U38="","",'Model inputs'!U38),IF('Base versus Growth'!AD9="","",'Base versus Growth'!AD9)))+'Base versus Growth'!AF8 -> -58000 | AG9: =IF(IF(DATE(2028,1,1)=DATE(2026,10,1),IF('Model inputs'!U39="","",'Model inputs'!U39),IF('Base versus Growth'!AE9="","",'Base versus Growth'!AE9))="",0,IF(DATE(2028,1,1)=DATE(2026,10,1),IF('Model inputs'!U39="","",'Model inputs'!U39),IF('Base versus Growth'!AE9="","",'Base versus Growth'!AE9)))+'Base versus Growth'!AG8 -> -39047.757 | AH9: =IF(IF(DATE(2028,2,1)=DATE(2026,10,1),IF('Model inputs'!U38="","",'Model inputs'!U38),IF('Base versus Growth'!AF9="","",'Base versus Growth'!AF9))="",0,IF(DATE(2028,2,1)=DATE(2026,10,1),IF('Model inputs'!U38="","",'Model inputs'!U38),IF('Base versus Growth'!AF9="","",'Base versus Growth'!AF9)))+'Base versus Growth'!AH8 -> -65250 | AI9: =IF(IF(DATE(2028,2,1)=DATE(2026,10,1),IF('Model inputs'!U39="","",'Model inputs'!U39),IF('Base versus Growth'!AG9="","",'Base versus Growth'!AG9))="",0,IF(DATE(2028,2,1)=DATE(2026,10,1),IF('Model inputs'!U39="","",'Model inputs'!U39),IF('Base versus Growth'!AG9="","",'Base versus Growth'!AG9)))+'Base versus Growth'!AI8 -> -42882.532 | AJ9: =IF(IF(DATE(2028,3,1)=DATE(2026,10,1),IF('Model inputs'!U38="","",'Model inputs'!U38),IF('Base versus Growth'!AH9="","",'Base versus Growth'!AH9))="",0,IF(DATE(2028,3,1)=DATE(2026,10,1),IF('Model inputs'!U38="","",'Model inputs'!U38),IF('Base versus Growth'!AH9="","",'Base versus Growth'!AH9)))+'Base versus Growth'!AJ8 -> -72500 | AK9: =IF(IF(DATE(2028,3,1)=DATE(2026,10,1),IF('Model inputs'!U39="","",'Model inputs'!U39),IF('Base versus Growth'!AI9="","",'Base versus Growth'!AI9))="",0,IF(DATE(2028,3,1)=DATE(2026,10,1),IF('Model inputs'!U39="","",'Model inputs'!U39),IF('Base versus Growth'!AI9="","",'Base versus Growth'!AI9)))+'Base versus Growth'!AK8 -> -46280.786

Sheet 18-month forecast
A1: 18-month forecast
A2: Mend — Forecast and runway · Base
A4: Variable / dimension | B4: 2026-10 | C4: 2026-11 | D4: 2026-12 | E4: 2027-01 | F4: 2027-02 | G4: 2027-03 | H4: 2027-04 | I4: 2027-05 | J4: 2027-06 | K4: 2027-07 | L4: 2027-08 | M4: 2027-09 | N4: 2027-10 | O4: 2027-11 | P4: 2027-12 | Q4: 2028-01 | R4: 2028-02 | S4: 2028-03
A5: Paying teams | B5: =IF('Model inputs'!U40="","",'Model inputs'!U40) -> 50 | C5: ='18-month forecast'!B5*(1+'Model inputs'!U30) -> 50 | D5: ='18-month forecast'!C5*(1+'Model inputs'!U30) -> 50 | E5: ='18-month forecast'!D5*(1+'Model inputs'!U30) -> 50 | F5: ='18-month forecast'!E5*(1+'Model inputs'!U30) -> 50 | G5: ='18-month forecast'!F5*(1+'Model inputs'!U30) -> 50 | H5: ='18-month forecast'!G5*(1+'Model inputs'!U30) -> 50 | I5: ='18-month forecast'!H5*(1+'Model inputs'!U30) -> 50 | J5: ='18-month forecast'!I5*(1+'Model inputs'!U30) -> 50 | K5: ='18-month forecast'!J5*(1+'Model inputs'!U30) -> 50 | L5: ='18-month forecast'!K5*(1+'Model inputs'!U30) -> 50 | M5: ='18-month forecast'!L5*(1+'Model inputs'!U30) -> 50 | N5: ='18-month forecast'!M5*(1+'Model inputs'!U30) -> 50 | O5: ='18-month forecast'!N5*(1+'Model inputs'!U30) -> 50 | P5: ='18-month forecast'!O5*(1+'Model inputs'!U30) -> 50 | Q5: ='18-month forecast'!P5*(1+'Model inputs'!U30) -> 50 | R5: ='18-month forecast'!Q5*(1+'Model inputs'!U30) -> 50 | S5: ='18-month forecast'!R5*(1+'Model inputs'!U30) -> 50
A6: Monthly revenue | B6: ='18-month forecast'!B5*'Model inputs'!U35 -> 2450 | C6: ='18-month forecast'!C5*'Model inputs'!U35 -> 2450 | D6: ='18-month forecast'!D5*'Model inputs'!U35 -> 2450 | E6: ='18-month forecast'!E5*'Model inputs'!U35 -> 2450 | F6: ='18-month forecast'!F5*'Model inputs'!U35 -> 2450 | G6: ='18-month forecast'!G5*'Model inputs'!U35 -> 2450 | H6: ='18-month forecast'!H5*'Model inputs'!U35 -> 2450 | I6: ='18-month forecast'!I5*'Model inputs'!U35 -> 2450 | J6: ='18-month forecast'!J5*'Model inputs'!U35 -> 2450 | K6: ='18-month forecast'!K5*'Model inputs'!U35 -> 2450 | L6: ='18-month forecast'!L5*'Model inputs'!U35 -> 2450 | M6: ='18-month forecast'!M5*'Model inputs'!U35 -> 2450 | N6: ='18-month forecast'!N5*'Model inputs'!U35 -> 2450 | O6: ='18-month forecast'!O5*'Model inputs'!U35 -> 2450 | P6: ='18-month forecast'!P5*'Model inputs'!U35 -> 2450 | Q6: ='18-month forecast'!Q5*'Model inputs'!U35 -> 2450 | R6: ='18-month forecast'!R5*'Model inputs'!U35 -> 2450 | S6: ='18-month forecast'!S5*'Model inputs'!U35 -> 2450
A7: Repair rounds delivered | B7: ='18-month forecast'!B5*'Model inputs'!U37 -> 1000 | C7: ='18-month forecast'!C5*'Model inputs'!U37 -> 1000 | D7: ='18-month forecast'!D5*'Model inputs'!U37 -> 1000 | E7: ='18-month forecast'!E5*'Model inputs'!U37 -> 1000 | F7: ='18-month forecast'!F5*'Model inputs'!U37 -> 1000 | G7: ='18-month forecast'!G5*'Model inputs'!U37 -> 1000 | H7: ='18-month forecast'!H5*'Model inputs'!U37 -> 1000 | I7: ='18-month forecast'!I5*'Model inputs'!U37 -> 1000 | J7: ='18-month forecast'!J5*'Model inputs'!U37 -> 1000 | K7: ='18-month forecast'!K5*'Model inputs'!U37 -> 1000 | L7: ='18-month forecast'!L5*'Model inputs'!U37 -> 1000 | M7: ='18-month forecast'!M5*'Model inputs'!U37 -> 1000 | N7: ='18-month forecast'!N5*'Model inputs'!U37 -> 1000 | O7: ='18-month forecast'!O5*'Model inputs'!U37 -> 1000 | P7: ='18-month forecast'!P5*'Model inputs'!U37 -> 1000 | Q7: ='18-month forecast'!Q5*'Model inputs'!U37 -> 1000 | R7: ='18-month forecast'!R5*'Model inputs'!U37 -> 1000 | S7: ='18-month forecast'!S5*'Model inputs'!U37 -> 1000
A8: Monthly model fees | B8: ='18-month forecast'!B7*'Model inputs'!U34 -> 1500 | C8: ='18-month forecast'!C7*'Model inputs'!U34 -> 1500 | D8: ='18-month forecast'!D7*'Model inputs'!U34 -> 1500 | E8: ='18-month forecast'!E7*'Model inputs'!U34 -> 1500 | F8: ='18-month forecast'!F7*'Model inputs'!U34 -> 1500 | G8: ='18-month forecast'!G7*'Model inputs'!U34 -> 1500 | H8: ='18-month forecast'!H7*'Model inputs'!U34 -> 1500 | I8: ='18-month forecast'!I7*'Model inputs'!U34 -> 1500 | J8: ='18-month forecast'!J7*'Model inputs'!U34 -> 1500 | K8: ='18-month forecast'!K7*'Model inputs'!U34 -> 1500 | L8: ='18-month forecast'!L7*'Model inputs'!U34 -> 1500 | M8: ='18-month forecast'!M7*'Model inputs'!U34 -> 1500 | N8: ='18-month forecast'!N7*'Model inputs'!U34 -> 1500 | O8: ='18-month forecast'!O7*'Model inputs'!U34 -> 1500 | P8: ='18-month forecast'!P7*'Model inputs'!U34 -> 1500 | Q8: ='18-month forecast'!Q7*'Model inputs'!U34 -> 1500 | R8: ='18-month forecast'!R7*'Model inputs'!U34 -> 1500 | S8: ='18-month forecast'!S7*'Model inputs'!U34 -> 1500
A9: Infrastructure expense | B9: =IF('Model inputs'!U8="","",'Model inputs'!U8) -> 200 | C9: =IF('Model inputs'!U8="","",'Model inputs'!U8) -> 200 | D9: =IF('Model inputs'!U8="","",'Model inputs'!U8) -> 200 | E9: =IF('Model inputs'!U8="","",'Model inputs'!U8) -> 200 | F9: =IF('Model inputs'!U8="","",'Model inputs'!U8) -> 200 | G9: =IF('Model inputs'!U8="","",'Model inputs'!U8) -> 200 | H9: =IF('Model inputs'!U8="","",'Model inputs'!U8) -> 200 | I9: =IF('Model inputs'!U8="","",'Model inputs'!U8) -> 200 | J9: =IF('Model inputs'!U8="","",'Model inputs'!U8) -> 200 | K9: =IF('Model inputs'!U8="","",'Model inputs'!U8) -> 200 | L9: =IF('Model inputs'!U8="","",'Model inputs'!U8) -> 200 | M9: =IF('Model inputs'!U8="","",'Model inputs'!U8) -> 200 | N9: =IF('Model inputs'!U8="","",'Model inputs'!U8) -> 200 | O9: =IF('Model inputs'!U8="","",'Model inputs'!U8) -> 200 | P9: =IF('Model inputs'!U8="","",'Model inputs'!U8) -> 200 | Q9: =IF('Model inputs'!U8="","",'Model inputs'!U8) -> 200 | R9: =IF('Model inputs'!U8="","",'Model inputs'!U8) -> 200 | S9: =IF('Model inputs'!U8="","",'Model inputs'!U8) -> 200
A10: Cost of revenue | B10: ='18-month forecast'!B8+'18-month forecast'!B9 -> 1700 | C10: ='18-month forecast'!C8+'18-month forecast'!C9 -> 1700 | D10: ='18-month forecast'!D8+'18-month forecast'!D9 -> 1700 | E10: ='18-month forecast'!E8+'18-month forecast'!E9 -> 1700 | F10: ='18-month forecast'!F8+'18-month forecast'!F9 -> 1700 | G10: ='18-month forecast'!G8+'18-month forecast'!G9 -> 1700 | H10: ='18-month forecast'!H8+'18-month forecast'!H9 -> 1700 | I10: ='18-month forecast'!I8+'18-month forecast'!I9 -> 1700 | ... S10: ='18-month forecast'!S8+'18-month forecast'!S9 -> 1700
A11: Gross profit | B11: ='18-month forecast'!B6-'18-month forecast'!B10 -> 750 | C11: ='18-month forecast'!C6-'18-month forecast'!C10 -> 750 | D11: ='18-month forecast'!D6-'18-month forecast'!D10 -> 750 | E11: ='18-month forecast'!E6-'18-month forecast'!E10 -> 750 | F11: ='18-month forecast'!F6-'18-month forecast'!F10 -> 750 | G11: ='18-month forecast'!G6-'18-month forecast'!G10 -> 750 | H11: ='18-month forecast'!H6-'18-month forecast'!H10 -> 750 | I11: ='18-month forecast'!I6-'18-month forecast'!I10 -> 750 | ... S11: ='18-month forecast'!S6-'18-month forecast'!S10 -> 750
A12: Gross margin | B12: =IFERROR('18-month forecast'!B11/'18-month forecast'!B6,"") -> 0.30612245 | C12: =IFERROR('18-month forecast'!C11/'18-month forecast'!C6,"") -> 0.30612245 | D12: =IFERROR('18-month forecast'!D11/'18-month forecast'!D6,"") -> 0.30612245 | E12: =IFERROR('18-month forecast'!E11/'18-month forecast'!E6,"") -> 0.30612245 | F12: =IFERROR('18-month forecast'!F11/'18-month forecast'!F6,"") -> 0.30612245 | G12: =IFERROR('18-month forecast'!G11/'18-month forecast'!G6,"") -> 0.30612245 | H12: =IFERROR('18-month forecast'!H11/'18-month forecast'!H6,"") -> 0.30612245 | I12: =IFERROR('18-month forecast'!I11/'18-month forecast'!I6,"") -> 0.30612245 | ... S12: =IFERROR('18-month forecast'!S11/'18-month forecast'!S6,"") -> 0.30612245
A13: Founder payroll | B13: =SUM('18-month forecast'!B14,'18-month forecast'!B15,'18-month forecast'!B16,'18-month forecast'!B17) -> 0 | C13: =SUM('18-month forecast'!C14,'18-month forecast'!C15,'18-month forecast'!C16,'18-month forecast'!C17) -> 0 | D13: =SUM('18-month forecast'!D14,'18-month forecast'!D15,'18-month forecast'!D16,'18-month forecast'!D17) -> 0 | E13: =SUM('18-month forecast'!E14,'18-month forecast'!E15,'18-month forecast'!E16,'18-month forecast'!E17) -> 0 | F13: =SUM('18-month forecast'!F14,'18-month forecast'!F15,'18-month forecast'!F16,'18-month forecast'!F17) -> 0 | G13: =SUM('18-month forecast'!G14,'18-month forecast'!G15,'18-month forecast'!G16,'18-month forecast'!G17) -> 0 | H13: =SUM('18-month forecast'!H14,'18-month forecast'!H15,'18-month forecast'!H16,'18-month forecast'!H17) -> 8000 | I13: =SUM('18-month forecast'!I14,'18-month forecast'!I15,'18-month forecast'!I16,'18-month forecast'!I17) -> 8000 | ... S13: =SUM('18-month forecast'!S14,'18-month forecast'!S15,'18-month forecast'!S16,'18-month forecast'!S17) -> 8000
A14: Placeholder founder 1 | B14: =IF(IF(IF(ISERROR(DATE(2026,10,1)>=DATE(YEAR('Model inputs'!U10),MONTH('Model inputs'!U10),1)),DATE(2026,10,1)>=DATE(YEAR('Model inputs'!U10),MONTH('Model inputs'!U10),1),IF(DATE(YEAR('Model inputs'!U10),MONTH('Model inputs'!U10),1)="","",DATE(2026,10,1)>=DATE(YEAR('Model inputs'!U10),MONTH('Model inputs'!U10),1)))="",FALSE,IF(ISERROR(DATE(2026,10,1)>=DATE(YEAR('Model inputs'!U10),MONTH('Model inputs'!U10),1)),DATE(2026,10,1)>=DATE(YEAR('Model inputs'!U10),MONTH('Model inputs'!U10),1),IF(DATE(YEAR('Model inputs'!U10),MONTH('Model inputs'!U10),1)="","",DATE(2026,10,1)>=DATE(YEAR('Model inputs'!U10),MONTH('Model inputs'!U10),1)))),IF('Model inputs'!U23="","",'Model inputs'!U23),0) -> 0 | C14: =IF(IF(IF(ISERROR(DATE(2026,11,1)>=DATE(YEAR('Model inputs'!U10),MONTH('Model inputs'!U10),1)),DATE(2026,11,1)>=DATE(YEAR('Model inputs'!U10),MONTH('Model inputs'!U10),1),IF(DATE(YEAR('Model inputs'!U10),MONTH('Model inputs'!U10),1)="","",DATE(2026,11,1)>=DATE(YEAR('Model inputs'!U10),MONTH('Model inputs'!U10),1)))="",FALSE,IF(ISERROR(DATE(2026,11,1)>=DATE(YEAR('Model inputs'!U10),MONTH('Model inputs'!U10),1)),DATE(2026,11,1)>=DATE(YEAR('Model inputs'!U10),MONTH('Model inputs'!U10),1),IF(DATE(YEAR('Model inputs'!U10),MONTH('Model inputs'!U10),1)="","",DATE(2026,11,1)>=DATE(YEAR('Model inputs'!U10),MONTH('Model inputs'!U10),1)))),IF('Model inputs'!U23="","",'Model inputs'!U23),0) -> 0 | D14: =IF(IF(IF(ISERROR(DATE(2026,12,1)>=DATE(YEAR('Model inputs'!U10),MONTH('Model inputs'!U10),1)),DATE(2026,12,1)>=DATE(YEAR('Model inputs'!U10),MONTH('Model inputs'!U10),1),IF(DATE(YEAR('Model inputs'!U10),MONTH('Model inputs'!U10),1)="","",DATE(2026,12,1)>=DATE(YEAR('Model inputs'!U10),MONTH('Model inputs'!U10),1)))="",FALSE,IF(ISERROR(DATE(2026,12,1)>=DATE(YEAR('Model inputs'!U10),MONTH('Model inputs'!U10),1)),DATE(2026,12,1)>=DATE(YEAR('Model inputs'!U10),MONTH('Model inputs'!U10),1),IF(DATE(YEAR('Model inputs'!U10),MONTH('Model inputs'!U10),1)="","",DATE(2026,12,1)>=DATE(YEAR('Model inputs'!U10),MONTH('Model inputs'!U10),1)))),IF('Model inputs'!U23="","",'Model inputs'!U23),0) -> 0 | E14: =IF(IF(IF(ISERROR(DATE(2027,1,1)>=DATE(YEAR('Model inputs'!U10),MONTH('Model inputs'!U10),1)),DATE(2027,1,1)>=DATE(YEAR('Model inputs'!U10),MONTH('Model inputs'!U10),1),IF(DATE(YEAR('Model inputs'!U10),MONTH('Model inputs'!U10),1)="","",DATE(2027,1,1)>=DATE(YEAR('Model inputs'!U10),MONTH('Model inputs'!U10),1)))="",FALSE,IF(ISERROR(DATE(2027,1,1)>=DATE(YEAR('Model inputs'!U10),MONTH('Model inputs'!U10),1)),DATE(2027,1,1)>=DATE(YEAR('Model inputs'!U10),MONTH('Model inputs'!U10),1),IF(DATE(YEAR('Model inputs'!U10),MONTH('Model inputs'!U10),1)="","",DATE(2027,1,1)>=DATE(YEAR('Model inputs'!U10),MONTH('Model inputs'!U10),1)))),IF('Model inputs'!U23="","",'Model inputs'!U23),0) -> 0 | F14: =IF(IF(IF(ISERROR(DATE(2027,2,1)>=DATE(YEAR('Model inputs'!U10),MONTH('Model inputs'!U10),1)),DATE(2027,2,1)>=DATE(YEAR('Model inputs'!U10),MONTH('Model inputs'!U10),1),IF(DATE(YEAR('Model inputs'!U10),MONTH('Model inputs'!U10),1)="","",DATE(2027,2,1)>=DATE(YEAR('Model inputs'!U10),MONTH('Model inputs'!U10),1)))="",FALSE,IF(ISERROR(DATE(2027,2,1)>=DATE(YEAR('Model inputs'!U10),MONTH('Model inputs'!U10),1)),DATE(2027,2,1)>=DATE(YEAR('Model inputs'!U10),MONTH('Model inputs'!U10),1),IF(DATE(YEAR('Model inputs'!U10),MONTH('Model inputs'!U10),1)="","",DATE(2027,2,1)>=DATE(YEAR('Model inputs'!U10),MONTH('Model inputs'!U10),1)))),IF('Model inputs'!U23="","",'Model inputs'!U23),0) -> 0 | G14: =IF(IF(IF(ISERROR(DATE(2027,3,1)>=DATE(YEAR('Model inputs'!U10),MONTH('Model inputs'!U10),1)),DATE(2027,3,1)>=DATE(YEAR('Model inputs'!U10),MONTH('Model inputs'!U10),1),IF(DATE(YEAR('Model inputs'!U10),MONTH('Model inputs'!U10),1)="","",DATE(2027,3,1)>=DATE(YEAR('Model inputs'!U10),MONTH('Model inputs'!U10),1)))="",FALSE,IF(ISERROR(DATE(2027,3,1)>=DATE(YEAR('Model inputs'!U10),MONTH('Model inputs'!U10),1)),DATE(2027,3,1)>=DATE(YEAR('Model inputs'!U10),MONTH('Model inputs'!U10),1),IF(DATE(YEAR('Model inputs'!U10),MONTH('Model inputs'!U10),1)="","",DATE(2027,3,1)>=DATE(YEAR('Model inputs'!U10),MONTH('Model inputs'!U10),1)))),IF('Model inputs'!U23="","",'Model inputs'!U23),0) -> 0 | H14: =IF(IF(IF(ISERROR(DATE(2027,4,1)>=DATE(YEAR('Model inputs'!U10),MONTH('Model inputs'!U10),1)),DATE(2027,4,1)>=DATE(YEAR('Model inputs'!U10),MONTH('Model inputs'!U10),1),IF(DATE(YEAR('Model inputs'!U10),MONTH('Model inputs'!U10),1)="","",DATE(2027,4,1)>=DATE(YEAR('Model inputs'!U10),MONTH('Model inputs'!U10),1)))="",FALSE,IF(ISERROR(DATE(2027,4,1)>=DATE(YEAR('Model inputs'!U10),MONTH('Model inputs'!U10),1)),DATE(2027,4,1)>=DATE(YEAR('Model inputs'!U10),MONTH('Model inputs'!U10),1),IF(DATE(YEAR('Model inputs'!U10),MONTH('Model inputs'!U10),1)="","",DATE(2027,4,1)>=DATE(YEAR('Model inputs'!U10),MONTH('Model inputs'!U10),1)))),IF('Model inputs'!U23="","",'Model inputs'!U23),0) -> 2000 | I14: =IF(IF(IF(ISERROR(DATE(2027,5,1)>=DATE(YEAR('Model inputs'!U10),MONTH('Model inputs'!U10),1)),DATE(2027,5,1)>=DATE(YEAR('Model inputs'!U10),MONTH('Model inputs'!U10),1),IF(DATE(YEAR('Model inputs'!U10),MONTH('Model inputs'!U10),1)="","",DATE(2027,5,1)>=DATE(YEAR('Model inputs'!U10),MONTH('Model inputs'!U10),1)))="",FALSE,IF(ISERROR(DATE(2027,5,1)>=DATE(YEAR('Model inputs'!U10),MONTH('Model inputs'!U10),1)),DATE(2027,5,1)>=DATE(YEAR('Model inputs'!U10),MONTH('Model inputs'!U10),1),IF(DATE(YEAR('Model inputs'!U10),MONTH('Model inputs'!U10),1)="","",DATE(2027,5,1)>=DATE(YEAR('Model inputs'!U10),MONTH('Model inputs'!U10),1)))),IF('Model inputs'!U23="","",'Model inputs'!U23),0) -> 2000 | J14: =IF(IF(IF(ISERROR(DATE(2027,6,1)>=DATE(YEAR('Model inputs'!U10),MONTH('Model inputs'!U10),1)),DATE(2027,6,1)>=DATE(YEAR('Model inputs'!U10),MONTH('Model inputs'!U10),1),IF(DATE(YEAR('Model inputs'!U10),MONTH('Model inputs'!U10),1)="","",DATE(2027,6,1)>=DATE(YEAR('Model inputs'!U10),MONTH('Model inputs'!U10),1)))="",FALSE,IF(ISERROR(DATE(2027,6,1)>=DATE(YEAR('Model inputs'!U10),MONTH('Model inputs'!U10),1)),DATE(2027,6,1)>=DATE(YEAR('Model inputs'!U10),MONTH('Model inputs'!U10),1),IF(DATE(YEAR('Model inputs'!U10),MONTH('Model inputs'!U10),1)="","",DATE(2027,6,1)>=DATE(YEAR('Model inputs'!U10),MONTH('Model inputs'!U10),1)))),IF('Model inputs'!U23="","",'Model inputs'!U23),0) -> 2000 | K14: =IF(IF(IF(ISERROR(DATE(2027,7,1)>=DATE(YEAR('Model inputs'!U10),MONTH('Model inputs'!U10),1)),DATE(2027,7,1)>=DATE(YEAR('Model inputs'!U10),MONTH('Model inputs'!U10),1),IF(DATE(YEAR('Model inputs'!U10),MONTH('Model inputs'!U10),1)="","",DATE(2027,7,1)>=DATE(YEAR('Model inputs'!U10),MONTH('Model inputs'!U10),1)))="",FALSE,IF(ISERROR(DATE(2027,7,1)>=DATE(YEAR('Model inputs'!U10),MONTH('Model inputs'!U10),1)),DATE(2027,7,1)>=DATE(YEAR('Model inputs'!U10),MONTH('Model inputs'!U10),1),IF(DATE(YEAR('Model inputs'!U10),MONTH('Model inputs'!U10),1)="","",DATE(2027,7,1)>=DATE(YEAR('Model inputs'!U10),MONTH('Model inputs'!U10),1)))),IF('Model inputs'!U23="","",'Model inputs'!U23),0) -> 2000 | L14: =IF(IF(IF(ISERROR(DATE(2027,8,1)>=DATE(YEAR('Model inputs'!U10),MONTH('Model inputs'!U10),1)),DATE(2027,8,1)>=DATE(YEAR('Model inputs'!U10),MONTH('Model inputs'!U10),1),IF(DATE(YEAR('Model inputs'!U10),MONTH('Model inputs'!U10),1)="","",DATE(2027,8,1)>=DATE(YEAR('Model inputs'!U10),MONTH('Model inputs'!U10),1)))="",FALSE,IF(ISERROR(DATE(2027,8,1)>=DATE(YEAR('Model inputs'!U10),MONTH('Model inputs'!U10),1)),DATE(2027,8,1)>=DATE(YEAR('Model inputs'!U10),MONTH('Model inputs'!U10),1),IF(DATE(YEAR('Model inputs'!U10),MONTH('Model inputs'!U10),1)="","",DATE(2027,8,1)>=DATE(YEAR('Model inputs'!U10),MONTH('Model inputs'!U10),1)))),IF('Model inputs'!U23="","",'Model inputs'!U23),0) -> 2000 | M14: =IF(IF(IF(ISERROR(DATE(2027,9,1)>=DATE(YEAR('Model inputs'!U10),MONTH('Model inputs'!U10),1)),DATE(2027,9,1)>=DATE(YEAR('Model inputs'!U10),MONTH('Model inputs'!U10),1),IF(DATE(YEAR('Model inputs'!U10),MONTH('Model inputs'!U10),1)="","",DATE(2027,9,1)>=DATE(YEAR('Model inputs'!U10),MONTH('Model inputs'!U10),1)))="",FALSE,IF(ISERROR(DATE(2027,9,1)>=DATE(YEAR('Model inputs'!U10),MONTH('Model inputs'!U10),1)),DATE(2027,9,1)>=DATE(YEAR('Model inputs'!U10),MONTH('Model inputs'!U10),1),IF(DATE(YEAR('Model inputs'!U10),MONTH('Model inputs'!U10),1)="","",DATE(2027,9,1)>=DATE(YEAR('Model inputs'!U10),MONTH('Model inputs'!U10),1)))),IF('Model inputs'!U23="","",'Model inputs'!U23),0) -> 2000 | N14: =IF(IF(IF(ISERROR(DATE(2027,10,1)>=DATE(YEAR('Model inputs'!U10),MONTH('Model inputs'!U10),1)),DATE(2027,10,1)>=DATE(YEAR('Model inputs'!U10),MONTH('Model inputs'!U10),1),IF(DATE(YEAR('Model inputs'!U10),MONTH('Model inputs'!U10),1)="","",DATE(2027,10,1)>=DATE(YEAR('Model inputs'!U10),MONTH('Model inputs'!U10),1)))="",FALSE,IF(ISERROR(DATE(2027,10,1)>=DATE(YEAR('Model inputs'!U10),MONTH('Model inputs'!U10),1)),DATE(2027,10,1)>=DATE(YEAR('Model inputs'!U10),MONTH('Model inputs'!U10),1),IF(DATE(YEAR('Model inputs'!U10),MONTH('Model inputs'!U10),1)="","",DATE(2027,10,1)>=DATE(YEAR('Model inputs'!U10),MONTH('Model inputs'!U10),1)))),IF('Model inputs'!U23="","",'Model inputs'!U23),0) -> 2000 | O14: =IF(IF(IF(ISERROR(DATE(2027,11,1)>=DATE(YEAR('Model inputs'!U10),MONTH('Model inputs'!U10),1)),DATE(2027,11,1)>=DATE(YEAR('Model inputs'!U10),MONTH('Model inputs'!U10),1),IF(DATE(YEAR('Model inputs'!U10),MONTH('Model inputs'!U10),1)="","",DATE(2027,11,1)>=DATE(YEAR('Model inputs'!U10),MONTH('Model inputs'!U10),1)))="",FALSE,IF(ISERROR(DATE(2027,11,1)>=DATE(YEAR('Model inputs'!U10),MONTH('Model inputs'!U10),1)),DATE(2027,11,1)>=DATE(YEAR('Model inputs'!U10),MONTH('Model inputs'!U10),1),IF(DATE(YEAR('Model inputs'!U10),MONTH('Model inputs'!U10),1)="","",DATE(2027,11,1)>=DATE(YEAR('Model inputs'!U10),MONTH('Model inputs'!U10),1)))),IF('Model inputs'!U23="","",'Model inputs'!U23),0) -> 2000 | P14: =IF(IF(IF(ISERROR(DATE(2027,12,1)>=DATE(YEAR('Model inputs'!U10),MONTH('Model inputs'!U10),1)),DATE(2027,12,1)>=DATE(YEAR('Model inputs'!U10),MONTH('Model inputs'!U10),1),IF(DATE(YEAR('Model inputs'!U10),MONTH('Model inputs'!U10),1)="","",DATE(2027,12,1)>=DATE(YEAR('Model inputs'!U10),MONTH('Model inputs'!U10),1)))="",FALSE,IF(ISERROR(DATE(2027,12,1)>=DATE(YEAR('Model inputs'!U10),MONTH('Model inputs'!U10),1)),DATE(2027,12,1)>=DATE(YEAR('Model inputs'!U10),MONTH('Model inputs'!U10),1),IF(DATE(YEAR('Model inputs'!U10),MONTH('Model inputs'!U10),1)="","",DATE(2027,12,1)>=DATE(YEAR('Model inputs'!U10),MONTH('Model inputs'!U10),1)))),IF('Model inputs'!U23="","",'Model inputs'!U23),0) -> 2000 | Q14: =IF(IF(IF(ISERROR(DATE(2028,1,1)>=DATE(YEAR('Model inputs'!U10),MONTH('Model inputs'!U10),1)),DATE(2028,1,1)>=DATE(YEAR('Model inputs'!U10),MONTH('Model inputs'!U10),1),IF(DATE(YEAR('Model inputs'!U10),MONTH('Model inputs'!U10),1)="","",DATE(2028,1,1)>=DATE(YEAR('Model inputs'!U10),MONTH('Model inputs'!U10),1)))="",FALSE,IF(ISERROR(DATE(2028,1,1)>=DATE(YEAR('Model inputs'!U10),MONTH('Model inputs'!U10),1)),DATE(2028,1,1)>=DATE(YEAR('Model inputs'!U10),MONTH('Model inputs'!U10),1),IF(DATE(YEAR('Model inputs'!U10),MONTH('Model inputs'!U10),1)="","",DATE(2028,1,1)>=DATE(YEAR('Model inputs'!U10),MONTH('Model inputs'!U10),1)))),IF('Model inputs'!U23="","",'Model inputs'!U23),0) -> 2000 | R14: =IF(IF(IF(ISERROR(DATE(2028,2,1)>=DATE(YEAR('Model inputs'!U10),MONTH('Model inputs'!U10),1)),DATE(2028,2,1)>=DATE(YEAR('Model inputs'!U10),MONTH('Model inputs'!U10),1),IF(DATE(YEAR('Model inputs'!U10),MONTH('Model inputs'!U10),1)="","",DATE(2028,2,1)>=DATE(YEAR('Model inputs'!U10),MONTH('Model inputs'!U10),1)))="",FALSE,IF(ISERROR(DATE(2028,2,1)>=DATE(YEAR('Model inputs'!U10),MONTH('Model inputs'!U10),1)),DATE(2028,2,1)>=DATE(YEAR('Model inputs'!U10),MONTH('Model inputs'!U10),1),IF(DATE(YEAR('Model inputs'!U10),MONTH('Model inputs'!U10),1)="","",DATE(2028,2,1)>=DATE(YEAR('Model inputs'!U10),MONTH('Model inputs'!U10),1)))),IF('Model inputs'!U23="","",'Model inputs'!U23),0) -> 2000 | S14: =IF(IF(IF(ISERROR(DATE(2028,3,1)>=DATE(YEAR('Model inputs'!U10),MONTH('Model inputs'!U10),1)),DATE(2028,3,1)>=DATE(YEAR('Model inputs'!U10),MONTH('Model inputs'!U10),1),IF(DATE(YEAR('Model inputs'!U10),MONTH('Model inputs'!U10),1)="","",DATE(2028,3,1)>=DATE(YEAR('Model inputs'!U10),MONTH('Model inputs'!U10),1)))="",FALSE,IF(ISERROR(DATE(2028,3,1)>=DATE(YEAR('Model inputs'!U10),MONTH('Model inputs'!U10),1)),DATE(2028,3,1)>=DATE(YEAR('Model inputs'!U10),MONTH('Model inputs'!U10),1),IF(DATE(YEAR('Model inputs'!U10),MONTH('Model inputs'!U10),1)="","",DATE(2028,3,1)>=DATE(YEAR('Model inputs'!U10),MONTH('Model inputs'!U10),1)))),IF('Model inputs'!U23="","",'Model inputs'!U23),0) -> 2000
A15: Placeholder founder 2 | B15: =IF(IF(IF(ISERROR(DATE(2026,10,1)>=DATE(YEAR('Model inputs'!U11),MONTH('Model inputs'!U11),1)),DATE(2026,10,1)>=DATE(YEAR('Model inputs'!U11),MONTH('Model inputs'!U11),1),IF(DATE(YEAR('Model inputs'!U11),MONTH('Model inputs'!U11),1)="","",DATE(2026,10,1)>=DATE(YEAR('Model inputs'!U11),MONTH('Model inputs'!U11),1)))="",FALSE,IF(ISERROR(DATE(2026,10,1)>=DATE(YEAR('Model inputs'!U11),MONTH('Model inputs'!U11),1)),DATE(2026,10,1)>=DATE(YEAR('Model inputs'!U11),MONTH('Model inputs'!U11),1),IF(DATE(YEAR('Model inputs'!U11),MONTH('Model inputs'!U11),1)="","",DATE(2026,10,1)>=DATE(YEAR('Model inputs'!U11),MONTH('Model inputs'!U11),1)))),IF('Model inputs'!U24="","",'Model inputs'!U24),0) -> 0 | C15: =IF(IF(IF(ISERROR(DATE(2026,11,1)>=DATE(YEAR('Model inputs'!U11),MONTH('Model inputs'!U11),1)),DATE(2026,11,1)>=DATE(YEAR('Model inputs'!U11),MONTH('Model inputs'!U11),1),IF(DATE(YEAR('Model inputs'!U11),MONTH('Model inputs'!U11),1)="","",DATE(2026,11,1)>=DATE(YEAR('Model inputs'!U11),MONTH('Model inputs'!U11),1)))="",FALSE,IF(ISERROR(DATE(2026,11,1)>=DATE(YEAR('Model inputs'!U11),MONTH('Model inputs'!U11),1)),DATE(2026,11,1)>=DATE(YEAR('Model inputs'!U11),MONTH('Model inputs'!U11),1),IF(DATE(YEAR('Model inputs'!U11),MONTH('Model inputs'!U11),1)="","",DATE(2026,11,1)>=DATE(YEAR('Model inputs'!U11),MONTH('Model inputs'!U11),1)))),IF('Model inputs'!U24="","",'Model inputs'!U24),0) -> 0 | D15: =IF(IF(IF(ISERROR(DATE(2026,12,1)>=DATE(YEAR('Model inputs'!U11),MONTH('Model inputs'!U11),1)),DATE(2026,12,1)>=DATE(YEAR('Model inputs'!U11),MONTH('Model inputs'!U11),1),IF(DATE(YEAR('Model inputs'!U11),MONTH('Model inputs'!U11),1)="","",DATE(2026,12,1)>=DATE(YEAR('Model inputs'!U11),MONTH('Model inputs'!U11),1)))="",FALSE,IF(ISERROR(DATE(2026,12,1)>=DATE(YEAR('Model inputs'!U11),MONTH('Model inputs'!U11),1)),DATE(2026,12,1)>=DATE(YEAR('Model inputs'!U11),MONTH('Model inputs'!U11),1),IF(DATE(YEAR('Model inputs'!U11),MONTH('Model inputs'!U11),1)="","",DATE(2026,12,1)>=DATE(YEAR('Model inputs'!U11),MONTH('Model inputs'!U11),1)))),IF('Model inputs'!U24="","",'Model inputs'!U24),0) -> 0 | E15: =IF(IF(IF(ISERROR(DATE(2027,1,1)>=DATE(YEAR('Model inputs'!U11),MONTH('Model inputs'!U11),1)),DATE(2027,1,1)>=DATE(YEAR('Model inputs'!U11),MONTH('Model inputs'!U11),1),IF(DATE(YEAR('Model inputs'!U11),MONTH('Model inputs'!U11),1)="","",DATE(2027,1,1)>=DATE(YEAR('Model inputs'!U11),MONTH('Model inputs'!U11),1)))="",FALSE,IF(ISERROR(DATE(2027,1,1)>=DATE(YEAR('Model inputs'!U11),MONTH('Model inputs'!U11),1)),DATE(2027,1,1)>=DATE(YEAR('Model inputs'!U11),MONTH('Model inputs'!U11),1),IF(DATE(YEAR('Model inputs'!U11),MONTH('Model inputs'!U11),1)="","",DATE(2027,1,1)>=DATE(YEAR('Model inputs'!U11),MONTH('Model inputs'!U11),1)))),IF('Model inputs'!U24="","",'Model inputs'!U24),0) -> 0 | F15: =IF(IF(IF(ISERROR(DATE(2027,2,1)>=DATE(YEAR('Model inputs'!U11),MONTH('Model inputs'!U11),1)),DATE(2027,2,1)>=DATE(YEAR('Model inputs'!U11),MONTH('Model inputs'!U11),1),IF(DATE(YEAR('Model inputs'!U11),MONTH('Model inputs'!U11),1)="","",DATE(2027,2,1)>=DATE(YEAR('Model inputs'!U11),MONTH('Model inputs'!U11),1)))="",FALSE,IF(ISERROR(DATE(2027,2,1)>=DATE(YEAR('Model inputs'!U11),MONTH('Model inputs'!U11),1)),DATE(2027,2,1)>=DATE(YEAR('Model inputs'!U11),MONTH('Model inputs'!U11),1),IF(DATE(YEAR('Model inputs'!U11),MONTH('Model inputs'!U11),1)="","",DATE(2027,2,1)>=DATE(YEAR('Model inputs'!U11),MONTH('Model inputs'!U11),1)))),IF('Model inputs'!U24="","",'Model inputs'!U24),0) -> 0 | G15: =IF(IF(IF(ISERROR(DATE(2027,3,1)>=DATE(YEAR('Model inputs'!U11),MONTH('Model inputs'!U11),1)),DATE(2027,3,1)>=DATE(YEAR('Model inputs'!U11),MONTH('Model inputs'!U11),1),IF(DATE(YEAR('Model inputs'!U11),MONTH('Model inputs'!U11),1)="","",DATE(2027,3,1)>=DATE(YEAR('Model inputs'!U11),MONTH('Model inputs'!U11),1)))="",FALSE,IF(ISERROR(DATE(2027,3,1)>=DATE(YEAR('Model inputs'!U11),MONTH('Model inputs'!U11),1)),DATE(2027,3,1)>=DATE(YEAR('Model inputs'!U11),MONTH('Model inputs'!U11),1),IF(DATE(YEAR('Model inputs'!U11),MONTH('Model inputs'!U11),1)="","",DATE(2027,3,1)>=DATE(YEAR('Model inputs'!U11),MONTH('Model inputs'!U11),1)))),IF('Model inputs'!U24="","",'Model inputs'!U24),0) -> 0 | H15: =IF(IF(IF(ISERROR(DATE(2027,4,1)>=DATE(YEAR('Model inputs'!U11),MONTH('Model inputs'!U11),1)),DATE(2027,4,1)>=DATE(YEAR('Model inputs'!U11),MONTH('Model inputs'!U11),1),IF(DATE(YEAR('Model inputs'!U11),MONTH('Model inputs'!U11),1)="","",DATE(2027,4,1)>=DATE(YEAR('Model inputs'!U11),MONTH('Model inputs'!U11),1)))="",FALSE,IF(ISERROR(DATE(2027,4,1)>=DATE(YEAR('Model inputs'!U11),MONTH('Model inputs'!U11),1)),DATE(2027,4,1)>=DATE(YEAR('Model inputs'!U11),MONTH('Model inputs'!U11),1),IF(DATE(YEAR('Model inputs'!U11),MONTH('Model inputs'!U11),1)="","",DATE(2027,4,1)>=DATE(YEAR('Model inputs'!U11),MONTH('Model inputs'!U11),1)))),IF('Model inputs'!U24="","",'Model inputs'!U24),0) -> 2000 | I15: =IF(IF(IF(ISERROR(DATE(2027,5,1)>=DATE(YEAR('Model inputs'!U11),MONTH('Model inputs'!U11),1)),DATE(2027,5,1)>=DATE(YEAR('Model inputs'!U11),MONTH('Model inputs'!U11),1),IF(DATE(YEAR('Model inputs'!U11),MONTH('Model inputs'!U11),1)="","",DATE(2027,5,1)>=DATE(YEAR('Model inputs'!U11),MONTH('Model inputs'!U11),1)))="",FALSE,IF(ISERROR(DATE(2027,5,1)>=DATE(YEAR('Model inputs'!U11),MONTH('Model inputs'!U11),1)),DATE(2027,5,1)>=DATE(YEAR('Model inputs'!U11),MONTH('Model inputs'!U11),1),IF(DATE(YEAR('Model inputs'!U11),MONTH('Model inputs'!U11),1)="","",DATE(2027,5,1)>=DATE(YEAR('Model inputs'!U11),MONTH('Model inputs'!U11),1)))),IF('Model inputs'!U24="","",'Model inputs'!U24),0) -> 2000 | J15: =IF(IF(IF(ISERROR(DATE(2027,6,1)>=DATE(YEAR('Model inputs'!U11),MONTH('Model inputs'!U11),1)),DATE(2027,6,1)>=DATE(YEAR('Model inputs'!U11),MONTH('Model inputs'!U11),1),IF(DATE(YEAR('Model inputs'!U11),MONTH('Model inputs'!U11),1)="","",DATE(2027,6,1)>=DATE(YEAR('Model inputs'!U11),MONTH('Model inputs'!U11),1)))="",FALSE,IF(ISERROR(DATE(2027,6,1)>=DATE(YEAR('Model inputs'!U11),MONTH('Model inputs'!U11),1)),DATE(2027,6,1)>=DATE(YEAR('Model inputs'!U11),MONTH('Model inputs'!U11),1),IF(DATE(YEAR('Model inputs'!U11),MONTH('Model inputs'!U11),1)="","",DATE(2027,6,1)>=DATE(YEAR('Model inputs'!U11),MONTH('Model inputs'!U11),1)))),IF('Model inputs'!U24="","",'Model inputs'!U24),0) -> 2000 | K15: =IF(IF(IF(ISERROR(DATE(2027,7,1)>=DATE(YEAR('Model inputs'!U11),MONTH('Model inputs'!U11),1)),DATE(2027,7,1)>=DATE(YEAR('Model inputs'!U11),MONTH('Model inputs'!U11),1),IF(DATE(YEAR('Model inputs'!U11),MONTH('Model inputs'!U11),1)="","",DATE(2027,7,1)>=DATE(YEAR('Model inputs'!U11),MONTH('Model inputs'!U11),1)))="",FALSE,IF(ISERROR(DATE(2027,7,1)>=DATE(YEAR('Model inputs'!U11),MONTH('Model inputs'!U11),1)),DATE(2027,7,1)>=DATE(YEAR('Model inputs'!U11),MONTH('Model inputs'!U11),1),IF(DATE(YEAR('Model inputs'!U11),MONTH('Model inputs'!U11),1)="","",DATE(2027,7,1)>=DATE(YEAR('Model inputs'!U11),MONTH('Model inputs'!U11),1)))),IF('Model inputs'!U24="","",'Model inputs'!U24),0) -> 2000 | L15: =IF(IF(IF(ISERROR(DATE(2027,8,1)>=DATE(YEAR('Model inputs'!U11),MONTH('Model inputs'!U11),1)),DATE(2027,8,1)>=DATE(YEAR('Model inputs'!U11),MONTH('Model inputs'!U11),1),IF(DATE(YEAR('Model inputs'!U11),MONTH('Model inputs'!U11),1)="","",DATE(2027,8,1)>=DATE(YEAR('Model inputs'!U11),MONTH('Model inputs'!U11),1)))="",FALSE,IF(ISERROR(DATE(2027,8,1)>=DATE(YEAR('Model inputs'!U11),MONTH('Model inputs'!U11),1)),DATE(2027,8,1)>=DATE(YEAR('Model inputs'!U11),MONTH('Model inputs'!U11),1),IF(DATE(YEAR('Model inputs'!U11),MONTH('Model inputs'!U11),1)="","",DATE(2027,8,1)>=DATE(YEAR('Model inputs'!U11),MONTH('Model inputs'!U11),1)))),IF('Model inputs'!U24="","",'Model inputs'!U24),0) -> 2000 | M15: =IF(IF(IF(ISERROR(DATE(2027,9,1)>=DATE(YEAR('Model inputs'!U11),MONTH('Model inputs'!U11),1)),DATE(2027,9,1)>=DATE(YEAR('Model inputs'!U11),MONTH('Model inputs'!U11),1),IF(DATE(YEAR('Model inputs'!U11),MONTH('Model inputs'!U11),1)="","",DATE(2027,9,1)>=DATE(YEAR('Model inputs'!U11),MONTH('Model inputs'!U11),1)))="",FALSE,IF(ISERROR(DATE(2027,9,1)>=DATE(YEAR('Model inputs'!U11),MONTH('Model inputs'!U11),1)),DATE(2027,9,1)>=DATE(YEAR('Model inputs'!U11),MONTH('Model inputs'!U11),1),IF(DATE(YEAR('Model inputs'!U11),MONTH('Model inputs'!U11),1)="","",DATE(2027,9,1)>=DATE(YEAR('Model inputs'!U11),MONTH('Model inputs'!U11),1)))),IF('Model inputs'!U24="","",'Model inputs'!U24),0) -> 2000 | N15: =IF(IF(IF(ISERROR(DATE(2027,10,1)>=DATE(YEAR('Model inputs'!U11),MONTH('Model inputs'!U11),1)),DATE(2027,10,1)>=DATE(YEAR('Model inputs'!U11),MONTH('Model inputs'!U11),1),IF(DATE(YEAR('Model inputs'!U11),MONTH('Model inputs'!U11),1)="","",DATE(2027,10,1)>=DATE(YEAR('Model inputs'!U11),MONTH('Model inputs'!U11),1)))="",FALSE,IF(ISERROR(DATE(2027,10,1)>=DATE(YEAR('Model inputs'!U11),MONTH('Model inputs'!U11),1)),DATE(2027,10,1)>=DATE(YEAR('Model inputs'!U11),MONTH('Model inputs'!U11),1),IF(DATE(YEAR('Model inputs'!U11),MONTH('Model inputs'!U11),1)="","",DATE(2027,10,1)>=DATE(YEAR('Model inputs'!U11),MONTH('Model inputs'!U11),1)))),IF('Model inputs'!U24="","",'Model inputs'!U24),0) -> 2000 | O15: =IF(IF(IF(ISERROR(DATE(2027,11,1)>=DATE(YEAR('Model inputs'!U11),MONTH('Model inputs'!U11),1)),DATE(2027,11,1)>=DATE(YEAR('Model inputs'!U11),MONTH('Model inputs'!U11),1),IF(DATE(YEAR('Model inputs'!U11),MONTH('Model inputs'!U11),1)="","",DATE(2027,11,1)>=DATE(YEAR('Model inputs'!U11),MONTH('Model inputs'!U11),1)))="",FALSE,IF(ISERROR(DATE(2027,11,1)>=DATE(YEAR('Model inputs'!U11),MONTH('Model inputs'!U11),1)),DATE(2027,11,1)>=DATE(YEAR('Model inputs'!U11),MONTH('Model inputs'!U11),1),IF(DATE(YEAR('Model inputs'!U11),MONTH('Model inputs'!U11),1)="","",DATE(2027,11,1)>=DATE(YEAR('Model inputs'!U11),MONTH('Model inputs'!U11),1)))),IF('Model inputs'!U24="","",'Model inputs'!U24),0) -> 2000 | P15: =IF(IF(IF(ISERROR(DATE(2027,12,1)>=DATE(YEAR('Model inputs'!U11),MONTH('Model inputs'!U11),1)),DATE(2027,12,1)>=DATE(YEAR('Model inputs'!U11),MONTH('Model inputs'!U11),1),IF(DATE(YEAR('Model inputs'!U11),MONTH('Model inputs'!U11),1)="","",DATE(2027,12,1)>=DATE(YEAR('Model inputs'!U11),MONTH('Model inputs'!U11),1)))="",FALSE,IF(ISERROR(DATE(2027,12,1)>=DATE(YEAR('Model inputs'!U11),MONTH('Model inputs'!U11),1)),DATE(2027,12,1)>=DATE(YEAR('Model inputs'!U11),MONTH('Model inputs'!U11),1),IF(DATE(YEAR('Model inputs'!U11),MONTH('Model inputs'!U11),1)="","",DATE(2027,12,1)>=DATE(YEAR('Model inputs'!U11),MONTH('Model inputs'!U11),1)))),IF('Model inputs'!U24="","",'Model inputs'!U24),0) -> 2000 | Q15: =IF(IF(IF(ISERROR(DATE(2028,1,1)>=DATE(YEAR('Model inputs'!U11),MONTH('Model inputs'!U11),1)),DATE(2028,1,1)>=DATE(YEAR('Model inputs'!U11),MONTH('Model inputs'!U11),1),IF(DATE(YEAR('Model inputs'!U11),MONTH('Model inputs'!U11),1)="","",DATE(2028,1,1)>=DATE(YEAR('Model inputs'!U11),MONTH('Model inputs'!U11),1)))="",FALSE,IF(ISERROR(DATE(2028,1,1)>=DATE(YEAR('Model inputs'!U11),MONTH('Model inputs'!U11),1)),DATE(2028,1,1)>=DATE(YEAR('Model inputs'!U11),MONTH('Model inputs'!U11),1),IF(DATE(YEAR('Model inputs'!U11),MONTH('Model inputs'!U11),1)="","",DATE(2028,1,1)>=DATE(YEAR('Model inputs'!U11),MONTH('Model inputs'!U11),1)))),IF('Model inputs'!U24="","",'Model inputs'!U24),0) -> 2000 | R15: =IF(IF(IF(ISERROR(DATE(2028,2,1)>=DATE(YEAR('Model inputs'!U11),MONTH('Model inputs'!U11),1)),DATE(2028,2,1)>=DATE(YEAR('Model inputs'!U11),MONTH('Model inputs'!U11),1),IF(DATE(YEAR('Model inputs'!U11),MONTH('Model inputs'!U11),1)="","",DATE(2028,2,1)>=DATE(YEAR('Model inputs'!U11),MONTH('Model inputs'!U11),1)))="",FALSE,IF(ISERROR(DATE(2028,2,1)>=DATE(YEAR('Model inputs'!U11),MONTH('Model inputs'!U11),1)),DATE(2028,2,1)>=DATE(YEAR('Model inputs'!U11),MONTH('Model inputs'!U11),1),IF(DATE(YEAR('Model inputs'!U11),MONTH('Model inputs'!U11),1)="","",DATE(2028,2,1)>=DATE(YEAR('Model inputs'!U11),MONTH('Model inputs'!U11),1)))),IF('Model inputs'!U24="","",'Model inputs'!U24),0) -> 2000 | S15: =IF(IF(IF(ISERROR(DATE(2028,3,1)>=DATE(YEAR('Model inputs'!U11),MONTH('Model inputs'!U11),1)),DATE(2028,3,1)>=DATE(YEAR('Model inputs'!U11),MONTH('Model inputs'!U11),1),IF(DATE(YEAR('Model inputs'!U11),MONTH('Model inputs'!U11),1)="","",DATE(2028,3,1)>=DATE(YEAR('Model inputs'!U11),MONTH('Model inputs'!U11),1)))="",FALSE,IF(ISERROR(DATE(2028,3,1)>=DATE(YEAR('Model inputs'!U11),MONTH('Model inputs'!U11),1)),DATE(2028,3,1)>=DATE(YEAR('Model inputs'!U11),MONTH('Model inputs'!U11),1),IF(DATE(YEAR('Model inputs'!U11),MONTH('Model inputs'!U11),1)="","",DATE(2028,3,1)>=DATE(YEAR('Model inputs'!U11),MONTH('Model inputs'!U11),1)))),IF('Model inputs'!U24="","",'Model inputs'!U24),0) -> 2000
A16: Placeholder founder 3 | B16: =IF(IF(IF(ISERROR(DATE(2026,10,1)>=DATE(YEAR('Model inputs'!U12),MONTH('Model inputs'!U12),1)),DATE(2026,10,1)>=DATE(YEAR('Model inputs'!U12),MONTH('Model inputs'!U12),1),IF(DATE(YEAR('Model inputs'!U12),MONTH('Model inputs'!U12),1)="","",DATE(2026,10,1)>=DATE(YEAR('Model inputs'!U12),MONTH('Model inputs'!U12),1)))="",FALSE,IF(ISERROR(DATE(2026,10,1)>=DATE(YEAR('Model inputs'!U12),MONTH('Model inputs'!U12),1)),DATE(2026,10,1)>=DATE(YEAR('Model inputs'!U12),MONTH('Model inputs'!U12),1),IF(DATE(YEAR('Model inputs'!U12),MONTH('Model inputs'!U12),1)="","",DATE(2026,10,1)>=DATE(YEAR('Model inputs'!U12),MONTH('Model inputs'!U12),1)))),IF('Model inputs'!U25="","",'Model inputs'!U25),0) -> 0 | C16: =IF(IF(IF(ISERROR(DATE(2026,11,1)>=DATE(YEAR('Model inputs'!U12),MONTH('Model inputs'!U12),1)),DATE(2026,11,1)>=DATE(YEAR('Model inputs'!U12),MONTH('Model inputs'!U12),1),IF(DATE(YEAR('Model inputs'!U12),MONTH('Model inputs'!U12),1)="","",DATE(2026,11,1)>=DATE(YEAR('Model inputs'!U12),MONTH('Model inputs'!U12),1)))="",FALSE,IF(ISERROR(DATE(2026,11,1)>=DATE(YEAR('Model inputs'!U12),MONTH('Model inputs'!U12),1)),DATE(2026,11,1)>=DATE(YEAR('Model inputs'!U12),MONTH('Model inputs'!U12),1),IF(DATE(YEAR('Model inputs'!U12),MONTH('Model inputs'!U12),1)="","",DATE(2026,11,1)>=DATE(YEAR('Model inputs'!U12),MONTH('Model inputs'!U12),1)))),IF('Model inputs'!U25="","",'Model inputs'!U25),0) -> 0 | D16: =IF(IF(IF(ISERROR(DATE(2026,12,1)>=DATE(YEAR('Model inputs'!U12),MONTH('Model inputs'!U12),1)),DATE(2026,12,1)>=DATE(YEAR('Model inputs'!U12),MONTH('Model inputs'!U12),1),IF(DATE(YEAR('Model inputs'!U12),MONTH('Model inputs'!U12),1)="","",DATE(2026,12,1)>=DATE(YEAR('Model inputs'!U12),MONTH('Model inputs'!U12),1)))="",FALSE,IF(ISERROR(DATE(2026,12,1)>=DATE(YEAR('Model inputs'!U12),MONTH('Model inputs'!U12),1)),DATE(2026,12,1)>=DATE(YEAR('Model inputs'!U12),MONTH('Model inputs'!U12),1),IF(DATE(YEAR('Model inputs'!U12),MONTH('Model inputs'!U12),1)="","",DATE(2026,12,1)>=DATE(YEAR('Model inputs'!U12),MONTH('Model inputs'!U12),1)))),IF('Model inputs'!U25="","",'Model inputs'!U25),0) -> 0 | E16: =IF(IF(IF(ISERROR(DATE(2027,1,1)>=DATE(YEAR('Model inputs'!U12),MONTH('Model inputs'!U12),1)),DATE(2027,1,1)>=DATE(YEAR('Model inputs'!U12),MONTH('Model inputs'!U12),1),IF(DATE(YEAR('Model inputs'!U12),MONTH('Model inputs'!U12),1)="","",DATE(2027,1,1)>=DATE(YEAR('Model inputs'!U12),MONTH('Model inputs'!U12),1)))="",FALSE,IF(ISERROR(DATE(2027,1,1)>=DATE(YEAR('Model inputs'!U12),MONTH('Model inputs'!U12),1)),DATE(2027,1,1)>=DATE(YEAR('Model inputs'!U12),MONTH('Model inputs'!U12),1),IF(DATE(YEAR('Model inputs'!U12),MONTH('Model inputs'!U12),1)="","",DATE(2027,1,1)>=DATE(YEAR('Model inputs'!U12),MONTH('Model inputs'!U12),1)))),IF('Model inputs'!U25="","",'Model inputs'!U25),0) -> 0 | F16: =IF(IF(IF(ISERROR(DATE(2027,2,1)>=DATE(YEAR('Model inputs'!U12),MONTH('Model inputs'!U12),1)),DATE(2027,2,1)>=DATE(YEAR('Model inputs'!U12),MONTH('Model inputs'!U12),1),IF(DATE(YEAR('Model inputs'!U12),MONTH('Model inputs'!U12),1)="","",DATE(2027,2,1)>=DATE(YEAR('Model inputs'!U12),MONTH('Model inputs'!U12),1)))="",FALSE,IF(ISERROR(DATE(2027,2,1)>=DATE(YEAR('Model inputs'!U12),MONTH('Model inputs'!U12),1)),DATE(2027,2,1)>=DATE(YEAR('Model inputs'!U12),MONTH('Model inputs'!U12),1),IF(DATE(YEAR('Model inputs'!U12),MONTH('Model inputs'!U12),1)="","",DATE(2027,2,1)>=DATE(YEAR('Model inputs'!U12),MONTH('Model inputs'!U12),1)))),IF('Model inputs'!U25="","",'Model inputs'!U25),0) -> 0 | G16: =IF(IF(IF(ISERROR(DATE(2027,3,1)>=DATE(YEAR('Model inputs'!U12),MONTH('Model inputs'!U12),1)),DATE(2027,3,1)>=DATE(YEAR('Model inputs'!U12),MONTH('Model inputs'!U12),1),IF(DATE(YEAR('Model inputs'!U12),MONTH('Model inputs'!U12),1)="","",DATE(2027,3,1)>=DATE(YEAR('Model inputs'!U12),MONTH('Model inputs'!U12),1)))="",FALSE,IF(ISERROR(DATE(2027,3,1)>=DATE(YEAR('Model inputs'!U12),MONTH('Model inputs'!U12),1)),DATE(2027,3,1)>=DATE(YEAR('Model inputs'!U12),MONTH('Model inputs'!U12),1),IF(DATE(YEAR('Model inputs'!U12),MONTH('Model inputs'!U12),1)="","",DATE(2027,3,1)>=DATE(YEAR('Model inputs'!U12),MONTH('Model inputs'!U12),1)))),IF('Model inputs'!U25="","",'Model inputs'!U25),0) -> 0 | H16: =IF(IF(IF(ISERROR(DATE(2027,4,1)>=DATE(YEAR('Model inputs'!U12),MONTH('Model inputs'!U12),1)),DATE(2027,4,1)>=DATE(YEAR('Model inputs'!U12),MONTH('Model inputs'!U12),1),IF(DATE(YEAR('Model inputs'!U12),MONTH('Model inputs'!U12),1)="","",DATE(2027,4,1)>=DATE(YEAR('Model inputs'!U12),MONTH('Model inputs'!U12),1)))="",FALSE,IF(ISERROR(DATE(2027,4,1)>=DATE(YEAR('Model inputs'!U12),MONTH('Model inputs'!U12),1)),DATE(2027,4,1)>=DATE(YEAR('Model inputs'!U12),MONTH('Model inputs'!U12),1),IF(DATE(YEAR('Model inputs'!U12),MONTH('Model inputs'!U12),1)="","",DATE(2027,4,1)>=DATE(YEAR('Model inputs'!U12),MONTH('Model inputs'!U12),1)))),IF('Model inputs'!U25="","",'Model inputs'!U25),0) -> 2000 | I16: =IF(IF(IF(ISERROR(DATE(2027,5,1)>=DATE(YEAR('Model inputs'!U12),MONTH('Model inputs'!U12),1)),DATE(2027,5,1)>=DATE(YEAR('Model inputs'!U12),MONTH('Model inputs'!U12),1),IF(DATE(YEAR('Model inputs'!U12),MONTH('Model inputs'!U12),1)="","",DATE(2027,5,1)>=DATE(YEAR('Model inputs'!U12),MONTH('Model inputs'!U12),1)))="",FALSE,IF(ISERROR(DATE(2027,5,1)>=DATE(YEAR('Model inputs'!U12),MONTH('Model inputs'!U12),1)),DATE(2027,5,1)>=DATE(YEAR('Model inputs'!U12),MONTH('Model inputs'!U12),1),IF(DATE(YEAR('Model inputs'!U12),MONTH('Model inputs'!U12),1)="","",DATE(2027,5,1)>=DATE(YEAR('Model inputs'!U12),MONTH('Model inputs'!U12),1)))),IF('Model inputs'!U25="","",'Model inputs'!U25),0) -> 2000 | J16: =IF(IF(IF(ISERROR(DATE(2027,6,1)>=DATE(YEAR('Model inputs'!U12),MONTH('Model inputs'!U12),1)),DATE(2027,6,1)>=DATE(YEAR('Model inputs'!U12),MONTH('Model inputs'!U12),1),IF(DATE(YEAR('Model inputs'!U12),MONTH('Model inputs'!U12),1)="","",DATE(2027,6,1)>=DATE(YEAR('Model inputs'!U12),MONTH('Model inputs'!U12),1)))="",FALSE,IF(ISERROR(DATE(2027,6,1)>=DATE(YEAR('Model inputs'!U12),MONTH('Model inputs'!U12),1)),DATE(2027,6,1)>=DATE(YEAR('Model inputs'!U12),MONTH('Model inputs'!U12),1),IF(DATE(YEAR('Model inputs'!U12),MONTH('Model inputs'!U12),1)="","",DATE(2027,6,1)>=DATE(YEAR('Model inputs'!U12),MONTH('Model inputs'!U12),1)))),IF('Model inputs'!U25="","",'Model inputs'!U25),0) -> 2000 | K16: =IF(IF(IF(ISERROR(DATE(2027,7,1)>=DATE(YEAR('Model inputs'!U12),MONTH('Model inputs'!U12),1)),DATE(2027,7,1)>=DATE(YEAR('Model inputs'!U12),MONTH('Model inputs'!U12),1),IF(DATE(YEAR('Model inputs'!U12),MONTH('Model inputs'!U12),1)="","",DATE(2027,7,1)>=DATE(YEAR('Model inputs'!U12),MONTH('Model inputs'!U12),1)))="",FALSE,IF(ISERROR(DATE(2027,7,1)>=DATE(YEAR('Model inputs'!U12),MONTH('Model inputs'!U12),1)),DATE(2027,7,1)>=DATE(YEAR('Model inputs'!U12),MONTH('Model inputs'!U12),1),IF(DATE(YEAR('Model inputs'!U12),MONTH('Model inputs'!U12),1)="","",DATE(2027,7,1)>=DATE(YEAR('Model inputs'!U12),MONTH('Model inputs'!U12),1)))),IF('Model inputs'!U25="","",'Model inputs'!U25),0) -> 2000 | L16: =IF(IF(IF(ISERROR(DATE(2027,8,1)>=DATE(YEAR('Model inputs'!U12),MONTH('Model inputs'!U12),1)),DATE(2027,8,1)>=DATE(YEAR('Model inputs'!U12),MONTH('Model inputs'!U12),1),IF(DATE(YEAR('Model inputs'!U12),MONTH('Model inputs'!U12),1)="","",DATE(2027,8,1)>=DATE(YEAR('Model inputs'!U12),MONTH('Model inputs'!U12),1)))="",FALSE,IF(ISERROR(DATE(2027,8,1)>=DATE(YEAR('Model inputs'!U12),MONTH('Model inputs'!U12),1)),DATE(2027,8,1)>=DATE(YEAR('Model inputs'!U12),MONTH('Model inputs'!U12),1),IF(DATE(YEAR('Model inputs'!U12),MONTH('Model inputs'!U12),1)="","",DATE(2027,8,1)>=DATE(YEAR('Model inputs'!U12),MONTH('Model inputs'!U12),1)))),IF('Model inputs'!U25="","",'Model inputs'!U25),0) -> 2000 | M16: =IF(IF(IF(ISERROR(DATE(2027,9,1)>=DATE(YEAR('Model inputs'!U12),MONTH('Model inputs'!U12),1)),DATE(2027,9,1)>=DATE(YEAR('Model inputs'!U12),MONTH('Model inputs'!U12),1),IF(DATE(YEAR('Model inputs'!U12),MONTH('Model inputs'!U12),1)="","",DATE(2027,9,1)>=DATE(YEAR('Model inputs'!U12),MONTH('Model inputs'!U12),1)))="",FALSE,IF(ISERROR(DATE(2027,9,1)>=DATE(YEAR('Model inputs'!U12),MONTH('Model inputs'!U12),1)),DATE(2027,9,1)>=DATE(YEAR('Model inputs'!U12),MONTH('Model inputs'!U12),1),IF(DATE(YEAR('Model inputs'!U12),MONTH('Model inputs'!U12),1)="","",DATE(2027,9,1)>=DATE(YEAR('Model inputs'!U12),MONTH('Model inputs'!U12),1)))),IF('Model inputs'!U25="","",'Model inputs'!U25),0) -> 2000 | N16: =IF(IF(IF(ISERROR(DATE(2027,10,1)>=DATE(YEAR('Model inputs'!U12),MONTH('Model inputs'!U12),1)),DATE(2027,10,1)>=DATE(YEAR('Model inputs'!U12),MONTH('Model inputs'!U12),1),IF(DATE(YEAR('Model inputs'!U12),MONTH('Model inputs'!U12),1)="","",DATE(2027,10,1)>=DATE(YEAR('Model inputs'!U12),MONTH('Model inputs'!U12),1)))="",FALSE,IF(ISERROR(DATE(2027,10,1)>=DATE(YEAR('Model inputs'!U12),MONTH('Model inputs'!U12),1)),DATE(2027,10,1)>=DATE(YEAR('Model inputs'!U12),MONTH('Model inputs'!U12),1),IF(DATE(YEAR('Model inputs'!U12),MONTH('Model inputs'!U12),1)="","",DATE(2027,10,1)>=DATE(YEAR('Model inputs'!U12),MONTH('Model inputs'!U12),1)))),IF('Model inputs'!U25="","",'Model inputs'!U25),0) -> 2000 | O16: =IF(IF(IF(ISERROR(DATE(2027,11,1)>=DATE(YEAR('Model inputs'!U12),MONTH('Model inputs'!U12),1)),DATE(2027,11,1)>=DATE(YEAR('Model inputs'!U12),MONTH('Model inputs'!U12),1),IF(DATE(YEAR('Model inputs'!U12),MONTH('Model inputs'!U12),1)="","",DATE(2027,11,1)>=DATE(YEAR('Model inputs'!U12),MONTH('Model inputs'!U12),1)))="",FALSE,IF(ISERROR(DATE(2027,11,1)>=DATE(YEAR('Model inputs'!U12),MONTH('Model inputs'!U12),1)),DATE(2027,11,1)>=DATE(YEAR('Model inputs'!U12),MONTH('Model inputs'!U12),1),IF(DATE(YEAR('Model inputs'!U12),MONTH('Model inputs'!U12),1)="","",DATE(2027,11,1)>=DATE(YEAR('Model inputs'!U12),MONTH('Model inputs'!U12),1)))),IF('Model inputs'!U25="","",'Model inputs'!U25),0) -> 2000 | P16: =IF(IF(IF(ISERROR(DATE(2027,12,1)>=DATE(YEAR('Model inputs'!U12),MONTH('Model inputs'!U12),1)),DATE(2027,12,1)>=DATE(YEAR('Model inputs'!U12),MONTH('Model inputs'!U12),1),IF(DATE(YEAR('Model inputs'!U12),MONTH('Model inputs'!U12),1)="","",DATE(2027,12,1)>=DATE(YEAR('Model inputs'!U12),MONTH('Model inputs'!U12),1)))="",FALSE,IF(ISERROR(DATE(2027,12,1)>=DATE(YEAR('Model inputs'!U12),MONTH('Model inputs'!U12),1)),DATE(2027,12,1)>=DATE(YEAR('Model inputs'!U12),MONTH('Model inputs'!U12),1),IF(DATE(YEAR('Model inputs'!U12),MONTH('Model inputs'!U12),1)="","",DATE(2027,12,1)>=DATE(YEAR('Model inputs'!U12),MONTH('Model inputs'!U12),1)))),IF('Model inputs'!U25="","",'Model inputs'!U25),0) -> 2000 | Q16: =IF(IF(IF(ISERROR(DATE(2028,1,1)>=DATE(YEAR('Model inputs'!U12),MONTH('Model inputs'!U12),1)),DATE(2028,1,1)>=DATE(YEAR('Model inputs'!U12),MONTH('Model inputs'!U12),1),IF(DATE(YEAR('Model inputs'!U12),MONTH('Model inputs'!U12),1)="","",DATE(2028,1,1)>=DATE(YEAR('Model inputs'!U12),MONTH('Model inputs'!U12),1)))="",FALSE,IF(ISERROR(DATE(2028,1,1)>=DATE(YEAR('Model inputs'!U12),MONTH('Model inputs'!U12),1)),DATE(2028,1,1)>=DATE(YEAR('Model inputs'!U12),MONTH('Model inputs'!U12),1),IF(DATE(YEAR('Model inputs'!U12),MONTH('Model inputs'!U12),1)="","",DATE(2028,1,1)>=DATE(YEAR('Model inputs'!U12),MONTH('Model inputs'!U12),1)))),IF('Model inputs'!U25="","",'Model inputs'!U25),0) -> 2000 | R16: =IF(IF(IF(ISERROR(DATE(2028,2,1)>=DATE(YEAR('Model inputs'!U12),MONTH('Model inputs'!U12),1)),DATE(2028,2,1)>=DATE(YEAR('Model inputs'!U12),MONTH('Model inputs'!U12),1),IF(DATE(YEAR('Model inputs'!U12),MONTH('Model inputs'!U12),1)="","",DATE(2028,2,1)>=DATE(YEAR('Model inputs'!U12),MONTH('Model inputs'!U12),1)))="",FALSE,IF(ISERROR(DATE(2028,2,1)>=DATE(YEAR('Model inputs'!U12),MONTH('Model inputs'!U12),1)),DATE(2028,2,1)>=DATE(YEAR('Model inputs'!U12),MONTH('Model inputs'!U12),1),IF(DATE(YEAR('Model inputs'!U12),MONTH('Model inputs'!U12),1)="","",DATE(2028,2,1)>=DATE(YEAR('Model inputs'!U12),MONTH('Model inputs'!U12),1)))),IF('Model inputs'!U25="","",'Model inputs'!U25),0) -> 2000 | S16: =IF(IF(IF(ISERROR(DATE(2028,3,1)>=DATE(YEAR('Model inputs'!U12),MONTH('Model inputs'!U12),1)),DATE(2028,3,1)>=DATE(YEAR('Model inputs'!U12),MONTH('Model inputs'!U12),1),IF(DATE(YEAR('Model inputs'!U12),MONTH('Model inputs'!U12),1)="","",DATE(2028,3,1)>=DATE(YEAR('Model inputs'!U12),MONTH('Model inputs'!U12),1)))="",FALSE,IF(ISERROR(DATE(2028,3,1)>=DATE(YEAR('Model inputs'!U12),MONTH('Model inputs'!U12),1)),DATE(2028,3,1)>=DATE(YEAR('Model inputs'!U12),MONTH('Model inputs'!U12),1),IF(DATE(YEAR('Model inputs'!U12),MONTH('Model inputs'!U12),1)="","",DATE(2028,3,1)>=DATE(YEAR('Model inputs'!U12),MONTH('Model inputs'!U12),1)))),IF('Model inputs'!U25="","",'Model inputs'!U25),0) -> 2000
A17: Placeholder founder 4 | B17: =IF(IF(IF(ISERROR(DATE(2026,10,1)>=DATE(YEAR('Model inputs'!U13),MONTH('Model inputs'!U13),1)),DATE(2026,10,1)>=DATE(YEAR('Model inputs'!U13),MONTH('Model inputs'!U13),1),IF(DATE(YEAR('Model inputs'!U13),MONTH('Model inputs'!U13),1)="","",DATE(2026,10,1)>=DATE(YEAR('Model inputs'!U13),MONTH('Model inputs'!U13),1)))="",FALSE,IF(ISERROR(DATE(2026,10,1)>=DATE(YEAR('Model inputs'!U13),MONTH('Model inputs'!U13),1)),DATE(2026,10,1)>=DATE(YEAR('Model inputs'!U13),MONTH('Model inputs'!U13),1),IF(DATE(YEAR('Model inputs'!U13),MONTH('Model inputs'!U13),1)="","",DATE(2026,10,1)>=DATE(YEAR('Model inputs'!U13),MONTH('Model inputs'!U13),1)))),IF('Model inputs'!U26="","",'Model inputs'!U26),0) -> 0 | C17: =IF(IF(IF(ISERROR(DATE(2026,11,1)>=DATE(YEAR('Model inputs'!U13),MONTH('Model inputs'!U13),1)),DATE(2026,11,1)>=DATE(YEAR('Model inputs'!U13),MONTH('Model inputs'!U13),1),IF(DATE(YEAR('Model inputs'!U13),MONTH('Model inputs'!U13),1)="","",DATE(2026,11,1)>=DATE(YEAR('Model inputs'!U13),MONTH('Model inputs'!U13),1)))="",FALSE,IF(ISERROR(DATE(2026,11,1)>=DATE(YEAR('Model inputs'!U13),MONTH('Model inputs'!U13),1)),DATE(2026,11,1)>=DATE(YEAR('Model inputs'!U13),MONTH('Model inputs'!U13),1),IF(DATE(YEAR('Model inputs'!U13),MONTH('Model inputs'!U13),1)="","",DATE(2026,11,1)>=DATE(YEAR('Model inputs'!U13),MONTH('Model inputs'!U13),1)))),IF('Model inputs'!U26="","",'Model inputs'!U26),0) -> 0 | D17: =IF(IF(IF(ISERROR(DATE(2026,12,1)>=DATE(YEAR('Model inputs'!U13),MONTH('Model inputs'!U13),1)),DATE(2026,12,1)>=DATE(YEAR('Model inputs'!U13),MONTH('Model inputs'!U13),1),IF(DATE(YEAR('Model inputs'!U13),MONTH('Model inputs'!U13),1)="","",DATE(2026,12,1)>=DATE(YEAR('Model inputs'!U13),MONTH('Model inputs'!U13),1)))="",FALSE,IF(ISERROR(DATE(2026,12,1)>=DATE(YEAR('Model inputs'!U13),MONTH('Model inputs'!U13),1)),DATE(2026,12,1)>=DATE(YEAR('Model inputs'!U13),MONTH('Model inputs'!U13),1),IF(DATE(YEAR('Model inputs'!U13),MONTH('Model inputs'!U13),1)="","",DATE(2026,12,1)>=DATE(YEAR('Model inputs'!U13),MONTH('Model inputs'!U13),1)))),IF('Model inputs'!U26="","",'Model inputs'!U26),0) -> 0 | E17: =IF(IF(IF(ISERROR(DATE(2027,1,1)>=DATE(YEAR('Model inputs'!U13),MONTH('Model inputs'!U13),1)),DATE(2027,1,1)>=DATE(YEAR('Model inputs'!U13),MONTH('Model inputs'!U13),1),IF(DATE(YEAR('Model inputs'!U13),MONTH('Model inputs'!U13),1)="","",DATE(2027,1,1)>=DATE(YEAR('Model inputs'!U13),MONTH('Model inputs'!U13),1)))="",FALSE,IF(ISERROR(DATE(2027,1,1)>=DATE(YEAR('Model inputs'!U13),MONTH('Model inputs'!U13),1)),DATE(2027,1,1)>=DATE(YEAR('Model inputs'!U13),MONTH('Model inputs'!U13),1),IF(DATE(YEAR('Model inputs'!U13),MONTH('Model inputs'!U13),1)="","",DATE(2027,1,1)>=DATE(YEAR('Model inputs'!U13),MONTH('Model inputs'!U13),1)))),IF('Model inputs'!U26="","",'Model inputs'!U26),0) -> 0 | F17: =IF(IF(IF(ISERROR(DATE(2027,2,1)>=DATE(YEAR('Model inputs'!U13),MONTH('Model inputs'!U13),1)),DATE(2027,2,1)>=DATE(YEAR('Model inputs'!U13),MONTH('Model inputs'!U13),1),IF(DATE(YEAR('Model inputs'!U13),MONTH('Model inputs'!U13),1)="","",DATE(2027,2,1)>=DATE(YEAR('Model inputs'!U13),MONTH('Model inputs'!U13),1)))="",FALSE,IF(ISERROR(DATE(2027,2,1)>=DATE(YEAR('Model inputs'!U13),MONTH('Model inputs'!U13),1)),DATE(2027,2,1)>=DATE(YEAR('Model inputs'!U13),MONTH('Model inputs'!U13),1),IF(DATE(YEAR('Model inputs'!U13),MONTH('Model inputs'!U13),1)="","",DATE(2027,2,1)>=DATE(YEAR('Model inputs'!U13),MONTH('Model inputs'!U13),1)))),IF('Model inputs'!U26="","",'Model inputs'!U26),0) -> 0 | G17: =IF(IF(IF(ISERROR(DATE(2027,3,1)>=DATE(YEAR('Model inputs'!U13),MONTH('Model inputs'!U13),1)),DATE(2027,3,1)>=DATE(YEAR('Model inputs'!U13),MONTH('Model inputs'!U13),1),IF(DATE(YEAR('Model inputs'!U13),MONTH('Model inputs'!U13),1)="","",DATE(2027,3,1)>=DATE(YEAR('Model inputs'!U13),MONTH('Model inputs'!U13),1)))="",FALSE,IF(ISERROR(DATE(2027,3,1)>=DATE(YEAR('Model inputs'!U13),MONTH('Model inputs'!U13),1)),DATE(2027,3,1)>=DATE(YEAR('Model inputs'!U13),MONTH('Model inputs'!U13),1),IF(DATE(YEAR('Model inputs'!U13),MONTH('Model inputs'!U13),1)="","",DATE(2027,3,1)>=DATE(YEAR('Model inputs'!U13),MONTH('Model inputs'!U13),1)))),IF('Model inputs'!U26="","",'Model inputs'!U26),0) -> 0 | H17: =IF(IF(IF(ISERROR(DATE(2027,4,1)>=DATE(YEAR('Model inputs'!U13),MONTH('Model inputs'!U13),1)),DATE(2027,4,1)>=DATE(YEAR('Model inputs'!U13),MONTH('Model inputs'!U13),1),IF(DATE(YEAR('Model inputs'!U13),MONTH('Model inputs'!U13),1)="","",DATE(2027,4,1)>=DATE(YEAR('Model inputs'!U13),MONTH('Model inputs'!U13),1)))="",FALSE,IF(ISERROR(DATE(2027,4,1)>=DATE(YEAR('Model inputs'!U13),MONTH('Model inputs'!U13),1)),DATE(2027,4,1)>=DATE(YEAR('Model inputs'!U13),MONTH('Model inputs'!U13),1),IF(DATE(YEAR('Model inputs'!U13),MONTH('Model inputs'!U13),1)="","",DATE(2027,4,1)>=DATE(YEAR('Model inputs'!U13),MONTH('Model inputs'!U13),1)))),IF('Model inputs'!U26="","",'Model inputs'!U26),0) -> 2000 | I17: =IF(IF(IF(ISERROR(DATE(2027,5,1)>=DATE(YEAR('Model inputs'!U13),MONTH('Model inputs'!U13),1)),DATE(2027,5,1)>=DATE(YEAR('Model inputs'!U13),MONTH('Model inputs'!U13),1),IF(DATE(YEAR('Model inputs'!U13),MONTH('Model inputs'!U13),1)="","",DATE(2027,5,1)>=DATE(YEAR('Model inputs'!U13),MONTH('Model inputs'!U13),1)))="",FALSE,IF(ISERROR(DATE(2027,5,1)>=DATE(YEAR('Model inputs'!U13),MONTH('Model inputs'!U13),1)),DATE(2027,5,1)>=DATE(YEAR('Model inputs'!U13),MONTH('Model inputs'!U13),1),IF(DATE(YEAR('Model inputs'!U13),MONTH('Model inputs'!U13),1)="","",DATE(2027,5,1)>=DATE(YEAR('Model inputs'!U13),MONTH('Model inputs'!U13),1)))),IF('Model inputs'!U26="","",'Model inputs'!U26),0) -> 2000 | J17: =IF(IF(IF(ISERROR(DATE(2027,6,1)>=DATE(YEAR('Model inputs'!U13),MONTH('Model inputs'!U13),1)),DATE(2027,6,1)>=DATE(YEAR('Model inputs'!U13),MONTH('Model inputs'!U13),1),IF(DATE(YEAR('Model inputs'!U13),MONTH('Model inputs'!U13),1)="","",DATE(2027,6,1)>=DATE(YEAR('Model inputs'!U13),MONTH('Model inputs'!U13),1)))="",FALSE,IF(ISERROR(DATE(2027,6,1)>=DATE(YEAR('Model inputs'!U13),MONTH('Model inputs'!U13),1)),DATE(2027,6,1)>=DATE(YEAR('Model inputs'!U13),MONTH('Model inputs'!U13),1),IF(DATE(YEAR('Model inputs'!U13),MONTH('Model inputs'!U13),1)="","",DATE(2027,6,1)>=DATE(YEAR('Model inputs'!U13),MONTH('Model inputs'!U13),1)))),IF('Model inputs'!U26="","",'Model inputs'!U26),0) -> 2000 | K17: =IF(IF(IF(ISERROR(DATE(2027,7,1)>=DATE(YEAR('Model inputs'!U13),MONTH('Model inputs'!U13),1)),DATE(2027,7,1)>=DATE(YEAR('Model inputs'!U13),MONTH('Model inputs'!U13),1),IF(DATE(YEAR('Model inputs'!U13),MONTH('Model inputs'!U13),1)="","",DATE(2027,7,1)>=DATE(YEAR('Model inputs'!U13),MONTH('Model inputs'!U13),1)))="",FALSE,IF(ISERROR(DATE(2027,7,1)>=DATE(YEAR('Model inputs'!U13),MONTH('Model inputs'!U13),1)),DATE(2027,7,1)>=DATE(YEAR('Model inputs'!U13),MONTH('Model inputs'!U13),1),IF(DATE(YEAR('Model inputs'!U13),MONTH('Model inputs'!U13),1)="","",DATE(2027,7,1)>=DATE(YEAR('Model inputs'!U13),MONTH('Model inputs'!U13),1)))),IF('Model inputs'!U26="","",'Model inputs'!U26),0) -> 2000 | L17: =IF(IF(IF(ISERROR(DATE(2027,8,1)>=DATE(YEAR('Model inputs'!U13),MONTH('Model inputs'!U13),1)),DATE(2027,8,1)>=DATE(YEAR('Model inputs'!U13),MONTH('Model inputs'!U13),1),IF(DATE(YEAR('Model inputs'!U13),MONTH('Model inputs'!U13),1)="","",DATE(2027,8,1)>=DATE(YEAR('Model inputs'!U13),MONTH('Model inputs'!U13),1)))="",FALSE,IF(ISERROR(DATE(2027,8,1)>=DATE(YEAR('Model inputs'!U13),MONTH('Model inputs'!U13),1)),DATE(2027,8,1)>=DATE(YEAR('Model inputs'!U13),MONTH('Model inputs'!U13),1),IF(DATE(YEAR('Model inputs'!U13),MONTH('Model inputs'!U13),1)="","",DATE(2027,8,1)>=DATE(YEAR('Model inputs'!U13),MONTH('Model inputs'!U13),1)))),IF('Model inputs'!U26="","",'Model inputs'!U26),0) -> 2000 | M17: =IF(IF(IF(ISERROR(DATE(2027,9,1)>=DATE(YEAR('Model inputs'!U13),MONTH('Model inputs'!U13),1)),DATE(2027,9,1)>=DATE(YEAR('Model inputs'!U13),MONTH('Model inputs'!U13),1),IF(DATE(YEAR('Model inputs'!U13),MONTH('Model inputs'!U13),1)="","",DATE(2027,9,1)>=DATE(YEAR('Model inputs'!U13),MONTH('Model inputs'!U13),1)))="",FALSE,IF(ISERROR(DATE(2027,9,1)>=DATE(YEAR('Model inputs'!U13),MONTH('Model inputs'!U13),1)),DATE(2027,9,1)>=DATE(YEAR('Model inputs'!U13),MONTH('Model inputs'!U13),1),IF(DATE(YEAR('Model inputs'!U13),MONTH('Model inputs'!U13),1)="","",DATE(2027,9,1)>=DATE(YEAR('Model inputs'!U13),MONTH('Model inputs'!U13),1)))),IF('Model inputs'!U26="","",'Model inputs'!U26),0) -> 2000 | N17: =IF(IF(IF(ISERROR(DATE(2027,10,1)>=DATE(YEAR('Model inputs'!U13),MONTH('Model inputs'!U13),1)),DATE(2027,10,1)>=DATE(YEAR('Model inputs'!U13),MONTH('Model inputs'!U13),1),IF(DATE(YEAR('Model inputs'!U13),MONTH('Model inputs'!U13),1)="","",DATE(2027,10,1)>=DATE(YEAR('Model inputs'!U13),MONTH('Model inputs'!U13),1)))="",FALSE,IF(ISERROR(DATE(2027,10,1)>=DATE(YEAR('Model inputs'!U13),MONTH('Model inputs'!U13),1)),DATE(2027,10,1)>=DATE(YEAR('Model inputs'!U13),MONTH('Model inputs'!U13),1),IF(DATE(YEAR('Model inputs'!U13),MONTH('Model inputs'!U13),1)="","",DATE(2027,10,1)>=DATE(YEAR('Model inputs'!U13),MONTH('Model inputs'!U13),1)))),IF('Model inputs'!U26="","",'Model inputs'!U26),0) -> 2000 | O17: =IF(IF(IF(ISERROR(DATE(2027,11,1)>=DATE(YEAR('Model inputs'!U13),MONTH('Model inputs'!U13),1)),DATE(2027,11,1)>=DATE(YEAR('Model inputs'!U13),MONTH('Model inputs'!U13),1),IF(DATE(YEAR('Model inputs'!U13),MONTH('Model inputs'!U13),1)="","",DATE(2027,11,1)>=DATE(YEAR('Model inputs'!U13),MONTH('Model inputs'!U13),1)))="",FALSE,IF(ISERROR(DATE(2027,11,1)>=DATE(YEAR('Model inputs'!U13),MONTH('Model inputs'!U13),1)),DATE(2027,11,1)>=DATE(YEAR('Model inputs'!U13),MONTH('Model inputs'!U13),1),IF(DATE(YEAR('Model inputs'!U13),MONTH('Model inputs'!U13),1)="","",DATE(2027,11,1)>=DATE(YEAR('Model inputs'!U13),MONTH('Model inputs'!U13),1)))),IF('Model inputs'!U26="","",'Model inputs'!U26),0) -> 2000 | P17: =IF(IF(IF(ISERROR(DATE(2027,12,1)>=DATE(YEAR('Model inputs'!U13),MONTH('Model inputs'!U13),1)),DATE(2027,12,1)>=DATE(YEAR('Model inputs'!U13),MONTH('Model inputs'!U13),1),IF(DATE(YEAR('Model inputs'!U13),MONTH('Model inputs'!U13),1)="","",DATE(2027,12,1)>=DATE(YEAR('Model inputs'!U13),MONTH('Model inputs'!U13),1)))="",FALSE,IF(ISERROR(DATE(2027,12,1)>=DATE(YEAR('Model inputs'!U13),MONTH('Model inputs'!U13),1)),DATE(2027,12,1)>=DATE(YEAR('Model inputs'!U13),MONTH('Model inputs'!U13),1),IF(DATE(YEAR('Model inputs'!U13),MONTH('Model inputs'!U13),1)="","",DATE(2027,12,1)>=DATE(YEAR('Model inputs'!U13),MONTH('Model inputs'!U13),1)))),IF('Model inputs'!U26="","",'Model inputs'!U26),0) -> 2000 | Q17: =IF(IF(IF(ISERROR(DATE(2028,1,1)>=DATE(YEAR('Model inputs'!U13),MONTH('Model inputs'!U13),1)),DATE(2028,1,1)>=DATE(YEAR('Model inputs'!U13),MONTH('Model inputs'!U13),1),IF(DATE(YEAR('Model inputs'!U13),MONTH('Model inputs'!U13),1)="","",DATE(2028,1,1)>=DATE(YEAR('Model inputs'!U13),MONTH('Model inputs'!U13),1)))="",FALSE,IF(ISERROR(DATE(2028,1,1)>=DATE(YEAR('Model inputs'!U13),MONTH('Model inputs'!U13),1)),DATE(2028,1,1)>=DATE(YEAR('Model inputs'!U13),MONTH('Model inputs'!U13),1),IF(DATE(YEAR('Model inputs'!U13),MONTH('Model inputs'!U13),1)="","",DATE(2028,1,1)>=DATE(YEAR('Model inputs'!U13),MONTH('Model inputs'!U13),1)))),IF('Model inputs'!U26="","",'Model inputs'!U26),0) -> 2000 | R17: =IF(IF(IF(ISERROR(DATE(2028,2,1)>=DATE(YEAR('Model inputs'!U13),MONTH('Model inputs'!U13),1)),DATE(2028,2,1)>=DATE(YEAR('Model inputs'!U13),MONTH('Model inputs'!U13),1),IF(DATE(YEAR('Model inputs'!U13),MONTH('Model inputs'!U13),1)="","",DATE(2028,2,1)>=DATE(YEAR('Model inputs'!U13),MONTH('Model inputs'!U13),1)))="",FALSE,IF(ISERROR(DATE(2028,2,1)>=DATE(YEAR('Model inputs'!U13),MONTH('Model inputs'!U13),1)),DATE(2028,2,1)>=DATE(YEAR('Model inputs'!U13),MONTH('Model inputs'!U13),1),IF(DATE(YEAR('Model inputs'!U13),MONTH('Model inputs'!U13),1)="","",DATE(2028,2,1)>=DATE(YEAR('Model inputs'!U13),MONTH('Model inputs'!U13),1)))),IF('Model inputs'!U26="","",'Model inputs'!U26),0) -> 2000 | S17: =IF(IF(IF(ISERROR(DATE(2028,3,1)>=DATE(YEAR('Model inputs'!U13),MONTH('Model inputs'!U13),1)),DATE(2028,3,1)>=DATE(YEAR('Model inputs'!U13),MONTH('Model inputs'!U13),1),IF(DATE(YEAR('Model inputs'!U13),MONTH('Model inputs'!U13),1)="","",DATE(2028,3,1)>=DATE(YEAR('Model inputs'!U13),MONTH('Model inputs'!U13),1)))="",FALSE,IF(ISERROR(DATE(2028,3,1)>=DATE(YEAR('Model inputs'!U13),MONTH('Model inputs'!U13),1)),DATE(2028,3,1)>=DATE(YEAR('Model inputs'!U13),MONTH('Model inputs'!U13),1),IF(DATE(YEAR('Model inputs'!U13),MONTH('Model inputs'!U13),1)="","",DATE(2028,3,1)>=DATE(YEAR('Model inputs'!U13),MONTH('Model inputs'!U13),1)))),IF('Model inputs'!U26="","",'Model inputs'!U26),0) -> 2000
A18: Net cash flow | B18: ='18-month forecast'!B11-'18-month forecast'!B13 -> 750 | C18: ='18-month forecast'!C11-'18-month forecast'!C13 -> 750 | D18: ='18-month forecast'!D11-'18-month forecast'!D13 -> 750 | E18: ='18-month forecast'!E11-'18-month forecast'!E13 -> 750 | F18: ='18-month forecast'!F11-'18-month forecast'!F13 -> 750 | G18: ='18-month forecast'!G11-'18-month forecast'!G13 -> 750 | H18: ='18-month forecast'!H11-'18-month forecast'!H13 -> -7250 | I18: ='18-month forecast'!I11-'18-month forecast'!I13 -> -7250 | ... S18: ='18-month forecast'!S11-'18-month forecast'!S13 -> -7250
A19: Closing cash | B19: =IF(IF(DATE(2026,10,1)=DATE(2026,10,1),IF('Model inputs'!U38="","",'Model inputs'!U38),IF('Model inputs'!B6="","",'Model inputs'!B6))="",0,IF(DATE(2026,10,1)=DATE(2026,10,1),IF('Model inputs'!U38="","",'Model inputs'!U38),IF('Model inputs'!B6="","",'Model inputs'!B6)))+'18-month forecast'!B18 -> 10750 | C19: =IF(IF(DATE(2026,11,1)=DATE(2026,10,1),IF('Model inputs'!U38="","",'Model inputs'!U38),IF('18-month forecast'!B19="","",'18-month forecast'!B19))="",0,IF(DATE(2026,11,1)=DATE(2026,10,1),IF('Model inputs'!U38="","",'Model inputs'!U38),IF('18-month forecast'!B19="","",'18-month forecast'!B19)))+'18-month forecast'!C18 -> 11500 | D19: =IF(IF(DATE(2026,12,1)=DATE(2026,10,1),IF('Model inputs'!U38="","",'Model inputs'!U38),IF('18-month forecast'!C19="","",'18-month forecast'!C19))="",0,IF(DATE(2026,12,1)=DATE(2026,10,1),IF('Model inputs'!U38="","",'Model inputs'!U38),IF('18-month forecast'!C19="","",'18-month forecast'!C19)))+'18-month forecast'!D18 -> 12250 | E19: =IF(IF(DATE(2027,1,1)=DATE(2026,10,1),IF('Model inputs'!U38="","",'Model inputs'!U38),IF('18-month forecast'!D19="","",'18-month forecast'!D19))="",0,IF(DATE(2027,1,1)=DATE(2026,10,1),IF('Model inputs'!U38="","",'Model inputs'!U38),IF('18-month forecast'!D19="","",'18-month forecast'!D19)))+'18-month forecast'!E18 -> 13000 | F19: =IF(IF(DATE(2027,2,1)=DATE(2026,10,1),IF('Model inputs'!U38="","",'Model inputs'!U38),IF('18-month forecast'!E19="","",'18-month forecast'!E19))="",0,IF(DATE(2027,2,1)=DATE(2026,10,1),IF('Model inputs'!U38="","",'Model inputs'!U38),IF('18-month forecast'!E19="","",'18-month forecast'!E19)))+'18-month forecast'!F18 -> 13750 | G19: =IF(IF(DATE(2027,3,1)=DATE(2026,10,1),IF('Model inputs'!U38="","",'Model inputs'!U38),IF('18-month forecast'!F19="","",'18-month forecast'!F19))="",0,IF(DATE(2027,3,1)=DATE(2026,10,1),IF('Model inputs'!U38="","",'Model inputs'!U38),IF('18-month forecast'!F19="","",'18-month forecast'!F19)))+'18-month forecast'!G18 -> 14500 | H19: =IF(IF(DATE(2027,4,1)=DATE(2026,10,1),IF('Model inputs'!U38="","",'Model inputs'!U38),IF('18-month forecast'!G19="","",'18-month forecast'!G19))="",0,IF(DATE(2027,4,1)=DATE(2026,10,1),IF('Model inputs'!U38="","",'Model inputs'!U38),IF('18-month forecast'!G19="","",'18-month forecast'!G19)))+'18-month forecast'!H18 -> 7250 | I19: =IF(IF(DATE(2027,5,1)=DATE(2026,10,1),IF('Model inputs'!U38="","",'Model inputs'!U38),IF('18-month forecast'!H19="","",'18-month forecast'!H19))="",0,IF(DATE(2027,5,1)=DATE(2026,10,1),IF('Model inputs'!U38="","",'Model inputs'!U38),IF('18-month forecast'!H19="","",'18-month forecast'!H19)))+'18-month forecast'!I18 -> 0 | J19: =IF(IF(DATE(2027,6,1)=DATE(2026,10,1),IF('Model inputs'!U38="","",'Model inputs'!U38),IF('18-month forecast'!I19="","",'18-month forecast'!I19))="",0,IF(DATE(2027,6,1)=DATE(2026,10,1),IF('Model inputs'!U38="","",'Model inputs'!U38),IF('18-month forecast'!I19="","",'18-month forecast'!I19)))+'18-month forecast'!J18 -> -7250 | K19: =IF(IF(DATE(2027,7,1)=DATE(2026,10,1),IF('Model inputs'!U38="","",'Model inputs'!U38),IF('18-month forecast'!J19="","",'18-month forecast'!J19))="",0,IF(DATE(2027,7,1)=DATE(2026,10,1),IF('Model inputs'!U38="","",'Model inputs'!U38),IF('18-month forecast'!J19="","",'18-month forecast'!J19)))+'18-month forecast'!K18 -> -14500 | L19: =IF(IF(DATE(2027,8,1)=DATE(2026,10,1),IF('Model inputs'!U38="","",'Model inputs'!U38),IF('18-month forecast'!K19="","",'18-month forecast'!K19))="",0,IF(DATE(2027,8,1)=DATE(2026,10,1),IF('Model inputs'!U38="","",'Model inputs'!U38),IF('18-month forecast'!K19="","",'18-month forecast'!K19)))+'18-month forecast'!L18 -> -21750 | M19: =IF(IF(DATE(2027,9,1)=DATE(2026,10,1),IF('Model inputs'!U38="","",'Model inputs'!U38),IF('18-month forecast'!L19="","",'18-month forecast'!L19))="",0,IF(DATE(2027,9,1)=DATE(2026,10,1),IF('Model inputs'!U38="","",'Model inputs'!U38),IF('18-month forecast'!L19="","",'18-month forecast'!L19)))+'18-month forecast'!M18 -> -29000 | N19: =IF(IF(DATE(2027,10,1)=DATE(2026,10,1),IF('Model inputs'!U38="","",'Model inputs'!U38),IF('18-month forecast'!M19="","",'18-month forecast'!M19))="",0,IF(DATE(2027,10,1)=DATE(2026,10,1),IF('Model inputs'!U38="","",'Model inputs'!U38),IF('18-month forecast'!M19="","",'18-month forecast'!M19)))+'18-month forecast'!N18 -> -36250 | O19: =IF(IF(DATE(2027,11,1)=DATE(2026,10,1),IF('Model inputs'!U38="","",'Model inputs'!U38),IF('18-month forecast'!N19="","",'18-month forecast'!N19))="",0,IF(DATE(2027,11,1)=DATE(2026,10,1),IF('Model inputs'!U38="","",'Model inputs'!U38),IF('18-month forecast'!N19="","",'18-month forecast'!N19)))+'18-month forecast'!O18 -> -43500 | P19: =IF(IF(DATE(2027,12,1)=DATE(2026,10,1),IF('Model inputs'!U38="","",'Model inputs'!U38),IF('18-month forecast'!O19="","",'18-month forecast'!O19))="",0,IF(DATE(2027,12,1)=DATE(2026,10,1),IF('Model inputs'!U38="","",'Model inputs'!U38),IF('18-month forecast'!O19="","",'18-month forecast'!O19)))+'18-month forecast'!P18 -> -50750 | Q19: =IF(IF(DATE(2028,1,1)=DATE(2026,10,1),IF('Model inputs'!U38="","",'Model inputs'!U38),IF('18-month forecast'!P19="","",'18-month forecast'!P19))="",0,IF(DATE(2028,1,1)=DATE(2026,10,1),IF('Model inputs'!U38="","",'Model inputs'!U38),IF('18-month forecast'!P19="","",'18-month forecast'!P19)))+'18-month forecast'!Q18 -> -58000 | R19: =IF(IF(DATE(2028,2,1)=DATE(2026,10,1),IF('Model inputs'!U38="","",'Model inputs'!U38),IF('18-month forecast'!Q19="","",'18-month forecast'!Q19))="",0,IF(DATE(2028,2,1)=DATE(2026,10,1),IF('Model inputs'!U38="","",'Model inputs'!U38),IF('18-month forecast'!Q19="","",'18-month forecast'!Q19)))+'18-month forecast'!R18 -> -65250 | S19: =IF(IF(DATE(2028,3,1)=DATE(2026,10,1),IF('Model inputs'!U38="","",'Model inputs'!U38),IF('18-month forecast'!R19="","",'18-month forecast'!R19))="",0,IF(DATE(2028,3,1)=DATE(2026,10,1),IF('Model inputs'!U38="","",'Model inputs'!U38),IF('18-month forecast'!R19="","",'18-month forecast'!R19)))+'18-month forecast'!S18 -> -72500

Sheet Model inputs
A1: Model inputs
A2: Integration values are aggregated snapshots; raw source records are not included.
A4: Variables
A5: Variable / segment | B5: 2026-09 | C5: 2026-10 | D5: 2026-11 | E5: 2026-12 | F5: 2027-01 | G5: 2027-02 | H5: 2027-03 | I5: 2027-04 | J5: 2027-05 | K5: 2027-06 | L5: 2027-07 | M5: 2027-08 | N5: 2027-09 | O5: 2027-10 | P5: 2027-11 | Q5: 2027-12 | R5: 2028-01 | S5: 2028-02 | T5: 2028-03 | U5: Value
A6: Closing cash · Base | B6: 0 | C6: =IF(IF(DATE(2026,10,1)=DATE(2026,10,1),IF('Model inputs'!U38="","",'Model inputs'!U38),IF('Model inputs'!B6="","",'Model inputs'!B6))="",0,IF(DATE(2026,10,1)=DATE(2026,10,1),IF('Model inputs'!U38="","",'Model inputs'!U38),IF('Model inputs'!B6="","",'Model inputs'!B6)))+'Model inputs'!C28 -> 10750 | D6: =IF(IF(DATE(2026,11,1)=DATE(2026,10,1),IF('Model inputs'!U38="","",'Model inputs'!U38),IF('Model inputs'!C6="","",'Model inputs'!C6))="",0,IF(DATE(2026,11,1)=DATE(2026,10,1),IF('Model inputs'!U38="","",'Model inputs'!U38),IF('Model inputs'!C6="","",'Model inputs'!C6)))+'Model inputs'!D28 -> 11500 | E6: =IF(IF(DATE(2026,12,1)=DATE(2026,10,1),IF('Model inputs'!U38="","",'Model inputs'!U38),IF('Model inputs'!D6="","",'Model inputs'!D6))="",0,IF(DATE(2026,12,1)=DATE(2026,10,1),IF('Model inputs'!U38="","",'Model inputs'!U38),IF('Model inputs'!D6="","",'Model inputs'!D6)))+'Model inputs'!E28 -> 12250 | F6: =IF(IF(DATE(2027,1,1)=DATE(2026,10,1),IF('Model inputs'!U38="","",'Model inputs'!U38),IF('Model inputs'!E6="","",'Model inputs'!E6))="",0,IF(DATE(2027,1,1)=DATE(2026,10,1),IF('Model inputs'!U38="","",'Model inputs'!U38),IF('Model inputs'!E6="","",'Model inputs'!E6)))+'Model inputs'!F28 -> 13000 | G6: =IF(IF(DATE(2027,2,1)=DATE(2026,10,1),IF('Model inputs'!U38="","",'Model inputs'!U38),IF('Model inputs'!F6="","",'Model inputs'!F6))="",0,IF(DATE(2027,2,1)=DATE(2026,10,1),IF('Model inputs'!U38="","",'Model inputs'!U38),IF('Model inputs'!F6="","",'Model inputs'!F6)))+'Model inputs'!G28 -> 13750 | H6: =IF(IF(DATE(2027,3,1)=DATE(2026,10,1),IF('Model inputs'!U38="","",'Model inputs'!U38),IF('Model inputs'!G6="","",'Model inputs'!G6))="",0,IF(DATE(2027,3,1)=DATE(2026,10,1),IF('Model inputs'!U38="","",'Model inputs'!U38),IF('Model inputs'!G6="","",'Model inputs'!G6)))+'Model inputs'!H28 -> 14500 | I6: =IF(IF(DATE(2027,4,1)=DATE(2026,10,1),IF('Model inputs'!U38="","",'Model inputs'!U38),IF('Model inputs'!H6="","",'Model inputs'!H6))="",0,IF(DATE(2027,4,1)=DATE(2026,10,1),IF('Model inputs'!U38="","",'Model inputs'!U38),IF('Model inputs'!H6="","",'Model inputs'!H6)))+'Model inputs'!I28 -> 7250 | J6: =IF(IF(DATE(2027,5,1)=DATE(2026,10,1),IF('Model inputs'!U38="","",'Model inputs'!U38),IF('Model inputs'!I6="","",'Model inputs'!I6))="",0,IF(DATE(2027,5,1)=DATE(2026,10,1),IF('Model inputs'!U38="","",'Model inputs'!U38),IF('Model inputs'!I6="","",'Model inputs'!I6)))+'Model inputs'!J28 -> 0 | K6: =IF(IF(DATE(2027,6,1)=DATE(2026,10,1),IF('Model inputs'!U38="","",'Model inputs'!U38),IF('Model inputs'!J6="","",'Model inputs'!J6))="",0,IF(DATE(2027,6,1)=DATE(2026,10,1),IF('Model inputs'!U38="","",'Model inputs'!U38),IF('Model inputs'!J6="","",'Model inputs'!J6)))+'Model inputs'!K28 -> -7250 | L6: =IF(IF(DATE(2027,7,1)=DATE(2026,10,1),IF('Model inputs'!U38="","",'Model inputs'!U38),IF('Model inputs'!K6="","",'Model inputs'!K6))="",0,IF(DATE(2027,7,1)=DATE(2026,10,1),IF('Model inputs'!U38="","",'Model inputs'!U38),IF('Model inputs'!K6="","",'Model inputs'!K6)))+'Model inputs'!L28 -> -14500 | M6: =IF(IF(DATE(2027,8,1)=DATE(2026,10,1),IF('Model inputs'!U38="","",'Model inputs'!U38),IF('Model inputs'!L6="","",'Model inputs'!L6))="",0,IF(DATE(2027,8,1)=DATE(2026,10,1),IF('Model inputs'!U38="","",'Model inputs'!U38),IF('Model inputs'!L6="","",'Model inputs'!L6)))+'Model inputs'!M28 -> -21750 | N6: =IF(IF(DATE(2027,9,1)=DATE(2026,10,1),IF('Model inputs'!U38="","",'Model inputs'!U38),IF('Model inputs'!M6="","",'Model inputs'!M6))="",0,IF(DATE(2027,9,1)=DATE(2026,10,1),IF('Model inputs'!U38="","",'Model inputs'!U38),IF('Model inputs'!M6="","",'Model inputs'!M6)))+'Model inputs'!N28 -> -29000 | O6: =IF(IF(DATE(2027,10,1)=DATE(2026,10,1),IF('Model inputs'!U38="","",'Model inputs'!U38),IF('Model inputs'!N6="","",'Model inputs'!N6))="",0,IF(DATE(2027,10,1)=DATE(2026,10,1),IF('Model inputs'!U38="","",'Model inputs'!U38),IF('Model inputs'!N6="","",'Model inputs'!N6)))+'Model inputs'!O28 -> -36250 | P6: =IF(IF(DATE(2027,11,1)=DATE(2026,10,1),IF('Model inputs'!U38="","",'Model inputs'!U38),IF('Model inputs'!O6="","",'Model inputs'!O6))="",0,IF(DATE(2027,11,1)=DATE(2026,10,1),IF('Model inputs'!U38="","",'Model inputs'!U38),IF('Model inputs'!O6="","",'Model inputs'!O6)))+'Model inputs'!P28 -> -43500 | Q6: =IF(IF(DATE(2027,12,1)=DATE(2026,10,1),IF('Model inputs'!U38="","",'Model inputs'!U38),IF('Model inputs'!P6="","",'Model inputs'!P6))="",0,IF(DATE(2027,12,1)=DATE(2026,10,1),IF('Model inputs'!U38="","",'Model inputs'!U38),IF('Model inputs'!P6="","",'Model inputs'!P6)))+'Model inputs'!Q28 -> -50750 | R6: =IF(IF(DATE(2028,1,1)=DATE(2026,10,1),IF('Model inputs'!U38="","",'Model inputs'!U38),IF('Model inputs'!Q6="","",'Model inputs'!Q6))="",0,IF(DATE(2028,1,1)=DATE(2026,10,1),IF('Model inputs'!U38="","",'Model inputs'!U38),IF('Model inputs'!Q6="","",'Model inputs'!Q6)))+'Model inputs'!R28 -> -58000 | S6: =IF(IF(DATE(2028,2,1)=DATE(2026,10,1),IF('Model inputs'!U38="","",'Model inputs'!U38),IF('Model inputs'!R6="","",'Model inputs'!R6))="",0,IF(DATE(2028,2,1)=DATE(2026,10,1),IF('Model inputs'!U38="","",'Model inputs'!U38),IF('Model inputs'!R6="","",'Model inputs'!R6)))+'Model inputs'!S28 -> -65250 | T6: =IF(IF(DATE(2028,3,1)=DATE(2026,10,1),IF('Model inputs'!U38="","",'Model inputs'!U38),IF('Model inputs'!S6="","",'Model inputs'!S6))="",0,IF(DATE(2028,3,1)=DATE(2026,10,1),IF('Model inputs'!U38="","",'Model inputs'!U38),IF('Model inputs'!S6="","",'Model inputs'!S6)))+'Model inputs'!T28 -> -72500
A7: Closing cash · Growth | B7: 0 | C7: =IF(IF(DATE(2026,10,1)=DATE(2026,10,1),IF('Model inputs'!U39="","",'Model inputs'!U39),IF('Model inputs'!B7="","",'Model inputs'!B7))="",0,IF(DATE(2026,10,1)=DATE(2026,10,1),IF('Model inputs'!U39="","",'Model inputs'!U39),IF('Model inputs'!B7="","",'Model inputs'!B7)))+'Model inputs'!C29 -> 10750 | D7: =IF(IF(DATE(2026,11,1)=DATE(2026,10,1),IF('Model inputs'!U39="","",'Model inputs'!U39),IF('Model inputs'!C7="","",'Model inputs'!C7))="",0,IF(DATE(2026,11,1)=DATE(2026,10,1),IF('Model inputs'!U39="","",'Model inputs'!U39),IF('Model inputs'!C7="","",'Model inputs'!C7)))+'Model inputs'!D29 -> 11595 | E7: =IF(IF(DATE(2026,12,1)=DATE(2026,10,1),IF('Model inputs'!U39="","",'Model inputs'!U39),IF('Model inputs'!D7="","",'Model inputs'!D7))="",0,IF(DATE(2026,12,1)=DATE(2026,10,1),IF('Model inputs'!U39="","",'Model inputs'!U39),IF('Model inputs'!D7="","",'Model inputs'!D7)))+'Model inputs'!E29 -> 12544.5 | F7: =IF(IF(DATE(2027,1,1)=DATE(2026,10,1),IF('Model inputs'!U39="","",'Model inputs'!U39),IF('Model inputs'!E7="","",'Model inputs'!E7))="",0,IF(DATE(2027,1,1)=DATE(2026,10,1),IF('Model inputs'!U39="","",'Model inputs'!U39),IF('Model inputs'!E7="","",'Model inputs'!E7)))+'Model inputs'!F29 -> 13608.95 | G7: =IF(IF(DATE(2027,2,1)=DATE(2026,10,1),IF('Model inputs'!U39="","",'Model inputs'!U39),IF('Model inputs'!F7="","",'Model inputs'!F7))="",0,IF(DATE(2027,2,1)=DATE(2026,10,1),IF('Model inputs'!U39="","",'Model inputs'!U39),IF('Model inputs'!F7="","",'Model inputs'!F7)))+'Model inputs'!G29 -> 14799.845 | H7: =IF(IF(DATE(2027,3,1)=DATE(2026,10,1),IF('Model inputs'!U39="","",'Model inputs'!U39),IF('Model inputs'!G7="","",'Model inputs'!G7))="",0,IF(DATE(2027,3,1)=DATE(2026,10,1),IF('Model inputs'!U39="","",'Model inputs'!U39),IF('Model inputs'!G7="","",'Model inputs'!G7)))+'Model inputs'!H29 -> 16129.83 | I7: =IF(IF(DATE(2027,4,1)=DATE(2026,10,1),IF('Model inputs'!U39="","",'Model inputs'!U39),IF('Model inputs'!H7="","",'Model inputs'!H7))="",0,IF(DATE(2027,4,1)=DATE(2026,10,1),IF('Model inputs'!U39="","",'Model inputs'!U39),IF('Model inputs'!H7="","",'Model inputs'!H7)))+'Model inputs'!I29 -> 9612.8125 | J7: =IF(IF(DATE(2027,5,1)=DATE(2026,10,1),IF('Model inputs'!U39="","",'Model inputs'!U39),IF('Model inputs'!I7="","",'Model inputs'!I7))="",0,IF(DATE(2027,5,1)=DATE(2026,10,1),IF('Model inputs'!U39="","",'Model inputs'!U39),IF('Model inputs'!I7="","",'Model inputs'!I7)))+'Model inputs'!J29 -> 3264.0937 | K7: =IF(IF(DATE(2027,6,1)=DATE(2026,10,1),IF('Model inputs'!U39="","",'Model inputs'!U39),IF('Model inputs'!J7="","",'Model inputs'!J7))="",0,IF(DATE(2027,6,1)=DATE(2026,10,1),IF('Model inputs'!U39="","",'Model inputs'!U39),IF('Model inputs'!J7="","",'Model inputs'!J7)))+'Model inputs'!K29 -> -2899.4969 | L7: =IF(IF(DATE(2027,7,1)=DATE(2026,10,1),IF('Model inputs'!U39="","",'Model inputs'!U39),IF('Model inputs'!K7="","",'Model inputs'!K7))="",0,IF(DATE(2027,7,1)=DATE(2026,10,1),IF('Model inputs'!U39="","",'Model inputs'!U39),IF('Model inputs'!K7="","",'Model inputs'!K7)))+'Model inputs'!L29 -> -8859.4466 | M7: =IF(IF(DATE(2027,8,1)=DATE(2026,10,1),IF('Model inputs'!U39="","",'Model inputs'!U39),IF('Model inputs'!L7="","",'Model inputs'!L7))="",0,IF(DATE(2027,8,1)=DATE(2026,10,1),IF('Model inputs'!U39="","",'Model inputs'!U39),IF('Model inputs'!L7="","",'Model inputs'!L7)))+'Model inputs'!M29 -> -14595.391 | N7: =IF(IF(DATE(2027,9,1)=DATE(2026,10,1),IF('Model inputs'!U39="","",'Model inputs'!U39),IF('Model inputs'!M7="","",'Model inputs'!M7))="",0,IF(DATE(2027,9,1)=DATE(2026,10,1),IF('Model inputs'!U39="","",'Model inputs'!U39),IF('Model inputs'!M7="","",'Model inputs'!M7)))+'Model inputs'!N29 -> -20084.93 | O7: =IF(IF(DATE(2027,10,1)=DATE(2026,10,1),IF('Model inputs'!U39="","",'Model inputs'!U39),IF('Model inputs'!N7="","",'Model inputs'!N7))="",0,IF(DATE(2027,10,1)=DATE(2026,10,1),IF('Model inputs'!U39="","",'Model inputs'!U39),IF('Model inputs'!N7="","",'Model inputs'!N7)))+'Model inputs'!O29 -> -25303.423 | P7: =IF(IF(DATE(2027,11,1)=DATE(2026,10,1),IF('Model inputs'!U39="","",'Model inputs'!U39),IF('Model inputs'!O7="","",'Model inputs'!O7))="",0,IF(DATE(2027,11,1)=DATE(2026,10,1),IF('Model inputs'!U39="","",'Model inputs'!U39),IF('Model inputs'!O7="","",'Model inputs'!O7)))+'Model inputs'!P29 -> -30223.766 | Q7: =IF(IF(DATE(2027,12,1)=DATE(2026,10,1),IF('Model inputs'!U39="","",'Model inputs'!U39),IF('Model inputs'!P7="","",'Model inputs'!P7))="",0,IF(DATE(2027,12,1)=DATE(2026,10,1),IF('Model inputs'!U39="","",'Model inputs'!U39),IF('Model inputs'!P7="","",'Model inputs'!P7)))+'Model inputs'!Q29 -> -34816.142 | R7: =IF(IF(DATE(2028,1,1)=DATE(2026,10,1),IF('Model inputs'!U39="","",'Model inputs'!U39),IF('Model inputs'!Q7="","",'Model inputs'!Q7))="",0,IF(DATE(2028,1,1)=DATE(2026,10,1),IF('Model inputs'!U39="","",'Model inputs'!U39),IF('Model inputs'!Q7="","",'Model inputs'!Q7)))+'Model inputs'!R29 -> -39047.757 | S7: =IF(IF(DATE(2028,2,1)=DATE(2026,10,1),IF('Model inputs'!U39="","",'Model inputs'!U39),IF('Model inputs'!R7="","",'Model inputs'!R7))="",0,IF(DATE(2028,2,1)=DATE(2026,10,1),IF('Model inputs'!U39="","",'Model inputs'!U39),IF('Model inputs'!R7="","",'Model inputs'!R7)))+'Model inputs'!S29 -> -42882.532 | T7: =IF(IF(DATE(2028,3,1)=DATE(2026,10,1),IF('Model inputs'!U39="","",'Model inputs'!U39),IF('Model inputs'!S7="","",'Model inputs'!S7))="",0,IF(DATE(2028,3,1)=DATE(2026,10,1),IF('Model inputs'!U39="","",'Model inputs'!U39),IF('Model inputs'!S7="","",'Model inputs'!S7)))+'Model inputs'!T29 -> -46280.786
A8: Fixed infrastructure · 18-month forecast | U8: =200 -> 200
A9: Founder pay starts
A10: Founder pay starts > Placeholder founder 1 | U10: =DATE(2027,4,1) -> 46478
A11: Founder pay starts > Placeholder founder 2 | U11: =DATE(2027,4,1) -> 46478
A12: Founder pay starts > Placeholder founder 3 | U12: =DATE(2027,4,1) -> 46478
A13: Founder pay starts > Placeholder founder 4 | U13: =DATE(2027,4,1) -> 46478
A14: Founder payroll | B14: =SUM('Model inputs'!B15,'Model inputs'!B16,'Model inputs'!B17,'Model inputs'!B18) -> 0 | C14: =SUM('Model inputs'!C15,'Model inputs'!C16,'Model inputs'!C17,'Model inputs'!C18) -> 0 | D14: =SUM('Model inputs'!D15,'Model inputs'!D16,'Model inputs'!D17,'Model inputs'!D18) -> 0 | E14: =SUM('Model inputs'!E15,'Model inputs'!E16,'Model inputs'!E17,'Model inputs'!E18) -> 0 | F14: =SUM('Model inputs'!F15,'Model inputs'!F16,'Model inputs'!F17,'Model inputs'!F18) -> 0 | G14: =SUM('Model inputs'!G15,'Model inputs'!G16,'Model inputs'!G17,'Model inputs'!G18) -> 0 | H14: =SUM('Model inputs'!H15,'Model inputs'!H16,'Model inputs'!H17,'Model inputs'!H18) -> 0 | I14: =SUM('Model inputs'!I15,'Model inputs'!I16,'Model inputs'!I17,'Model inputs'!I18) -> 8000 | ... T14: =SUM('Model inputs'!T15,'Model inputs'!T16,'Model inputs'!T17,'Model inputs'!T18) -> 8000
A15: Founder payroll > Placeholder founder 1 | B15: =0 -> 0 | C15: =IF(IF(IF(ISERROR(DATE(2026,10,1)>=DATE(YEAR('Model inputs'!U10),MONTH('Model inputs'!U10),1)),DATE(2026,10,1)>=DATE(YEAR('Model inputs'!U10),MONTH('Model inputs'!U10),1),IF(DATE(YEAR('Model inputs'!U10),MONTH('Model inputs'!U10),1)="","",DATE(2026,10,1)>=DATE(YEAR('Model inputs'!U10),MONTH('Model inputs'!U10),1)))="",FALSE,IF(ISERROR(DATE(2026,10,1)>=DATE(YEAR('Model inputs'!U10),MONTH('Model inputs'!U10),1)),DATE(2026,10,1)>=DATE(YEAR('Model inputs'!U10),MONTH('Model inputs'!U10),1),IF(DATE(YEAR('Model inputs'!U10),MONTH('Model inputs'!U10),1)="","",DATE(2026,10,1)>=DATE(YEAR('Model inputs'!U10),MONTH('Model inputs'!U10),1)))),IF('Model inputs'!U23="","",'Model inputs'!U23),0) -> 0 | D15: =IF(IF(IF(ISERROR(DATE(2026,11,1)>=DATE(YEAR('Model inputs'!U10),MONTH('Model inputs'!U10),1)),DATE(2026,11,1)>=DATE(YEAR('Model inputs'!U10),MONTH('Model inputs'!U10),1),IF(DATE(YEAR('Model inputs'!U10),MONTH('Model inputs'!U10),1)="","",DATE(2026,11,1)>=DATE(YEAR('Model inputs'!U10),MONTH('Model inputs'!U10),1)))="",FALSE,IF(ISERROR(DATE(2026,11,1)>=DATE(YEAR('Model inputs'!U10),MONTH('Model inputs'!U10),1)),DATE(2026,11,1)>=DATE(YEAR('Model inputs'!U10),MONTH('Model inputs'!U10),1),IF(DATE(YEAR('Model inputs'!U10),MONTH('Model inputs'!U10),1)="","",DATE(2026,11,1)>=DATE(YEAR('Model inputs'!U10),MONTH('Model inputs'!U10),1)))),IF('Model inputs'!U23="","",'Model inputs'!U23),0) -> 0 | E15: =IF(IF(IF(ISERROR(DATE(2026,12,1)>=DATE(YEAR('Model inputs'!U10),MONTH('Model inputs'!U10),1)),DATE(2026,12,1)>=DATE(YEAR('Model inputs'!U10),MONTH('Model inputs'!U10),1),IF(DATE(YEAR('Model inputs'!U10),MONTH('Model inputs'!U10),1)="","",DATE(2026,12,1)>=DATE(YEAR('Model inputs'!U10),MONTH('Model inputs'!U10),1)))="",FALSE,IF(ISERROR(DATE(2026,12,1)>=DATE(YEAR('Model inputs'!U10),MONTH('Model inputs'!U10),1)),DATE(2026,12,1)>=DATE(YEAR('Model inputs'!U10),MONTH('Model inputs'!U10),1),IF(DATE(YEAR('Model inputs'!U10),MONTH('Model inputs'!U10),1)="","",DATE(2026,12,1)>=DATE(YEAR('Model inputs'!U10),MONTH('Model inputs'!U10),1)))),IF('Model inputs'!U23="","",'Model inputs'!U23),0) -> 0 | F15: =IF(IF(IF(ISERROR(DATE(2027,1,1)>=DATE(YEAR('Model inputs'!U10),MONTH('Model inputs'!U10),1)),DATE(2027,1,1)>=DATE(YEAR('Model inputs'!U10),MONTH('Model inputs'!U10),1),IF(DATE(YEAR('Model inputs'!U10),MONTH('Model inputs'!U10),1)="","",DATE(2027,1,1)>=DATE(YEAR('Model inputs'!U10),MONTH('Model inputs'!U10),1)))="",FALSE,IF(ISERROR(DATE(2027,1,1)>=DATE(YEAR('Model inputs'!U10),MONTH('Model inputs'!U10),1)),DATE(2027,1,1)>=DATE(YEAR('Model inputs'!U10),MONTH('Model inputs'!U10),1),IF(DATE(YEAR('Model inputs'!U10),MONTH('Model inputs'!U10),1)="","",DATE(2027,1,1)>=DATE(YEAR('Model inputs'!U10),MONTH('Model inputs'!U10),1)))),IF('Model inputs'!U23="","",'Model inputs'!U23),0) -> 0 | G15: =IF(IF(IF(ISERROR(DATE(2027,2,1)>=DATE(YEAR('Model inputs'!U10),MONTH('Model inputs'!U10),1)),DATE(2027,2,1)>=DATE(YEAR('Model inputs'!U10),MONTH('Model inputs'!U10),1),IF(DATE(YEAR('Model inputs'!U10),MONTH('Model inputs'!U10),1)="","",DATE(2027,2,1)>=DATE(YEAR('Model inputs'!U10),MONTH('Model inputs'!U10),1)))="",FALSE,IF(ISERROR(DATE(2027,2,1)>=DATE(YEAR('Model inputs'!U10),MONTH('Model inputs'!U10),1)),DATE(2027,2,1)>=DATE(YEAR('Model inputs'!U10),MONTH('Model inputs'!U10),1),IF(DATE(YEAR('Model inputs'!U10),MONTH('Model inputs'!U10),1)="","",DATE(2027,2,1)>=DATE(YEAR('Model inputs'!U10),MONTH('Model inputs'!U10),1)))),IF('Model inputs'!U23="","",'Model inputs'!U23),0) -> 0 | H15: =IF(IF(IF(ISERROR(DATE(2027,3,1)>=DATE(YEAR('Model inputs'!U10),MONTH('Model inputs'!U10),1)),DATE(2027,3,1)>=DATE(YEAR('Model inputs'!U10),MONTH('Model inputs'!U10),1),IF(DATE(YEAR('Model inputs'!U10),MONTH('Model inputs'!U10),1)="","",DATE(2027,3,1)>=DATE(YEAR('Model inputs'!U10),MONTH('Model inputs'!U10),1)))="",FALSE,IF(ISERROR(DATE(2027,3,1)>=DATE(YEAR('Model inputs'!U10),MONTH('Model inputs'!U10),1)),DATE(2027,3,1)>=DATE(YEAR('Model inputs'!U10),MONTH('Model inputs'!U10),1),IF(DATE(YEAR('Model inputs'!U10),MONTH('Model inputs'!U10),1)="","",DATE(2027,3,1)>=DATE(YEAR('Model inputs'!U10),MONTH('Model inputs'!U10),1)))),IF('Model inputs'!U23="","",'Model inputs'!U23),0) -> 0 | I15: =IF(IF(IF(ISERROR(DATE(2027,4,1)>=DATE(YEAR('Model inputs'!U10),MONTH('Model inputs'!U10),1)),DATE(2027,4,1)>=DATE(YEAR('Model inputs'!U10),MONTH('Model inputs'!U10),1),IF(DATE(YEAR('Model inputs'!U10),MONTH('Model inputs'!U10),1)="","",DATE(2027,4,1)>=DATE(YEAR('Model inputs'!U10),MONTH('Model inputs'!U10),1)))="",FALSE,IF(ISERROR(DATE(2027,4,1)>=DATE(YEAR('Model inputs'!U10),MONTH('Model inputs'!U10),1)),DATE(2027,4,1)>=DATE(YEAR('Model inputs'!U10),MONTH('Model inputs'!U10),1),IF(DATE(YEAR('Model inputs'!U10),MONTH('Model inputs'!U10),1)="","",DATE(2027,4,1)>=DATE(YEAR('Model inputs'!U10),MONTH('Model inputs'!U10),1)))),IF('Model inputs'!U23="","",'Model inputs'!U23),0) -> 2000 | J15: =IF(IF(IF(ISERROR(DATE(2027,5,1)>=DATE(YEAR('Model inputs'!U10),MONTH('Model inputs'!U10),1)),DATE(2027,5,1)>=DATE(YEAR('Model inputs'!U10),MONTH('Model inputs'!U10),1),IF(DATE(YEAR('Model inputs'!U10),MONTH('Model inputs'!U10),1)="","",DATE(2027,5,1)>=DATE(YEAR('Model inputs'!U10),MONTH('Model inputs'!U10),1)))="",FALSE,IF(ISERROR(DATE(2027,5,1)>=DATE(YEAR('Model inputs'!U10),MONTH('Model inputs'!U10),1)),DATE(2027,5,1)>=DATE(YEAR('Model inputs'!U10),MONTH('Model inputs'!U10),1),IF(DATE(YEAR('Model inputs'!U10),MONTH('Model inputs'!U10),1)="","",DATE(2027,5,1)>=DATE(YEAR('Model inputs'!U10),MONTH('Model inputs'!U10),1)))),IF('Model inputs'!U23="","",'Model inputs'!U23),0) -> 2000 | K15: =IF(IF(IF(ISERROR(DATE(2027,6,1)>=DATE(YEAR('Model inputs'!U10),MONTH('Model inputs'!U10),1)),DATE(2027,6,1)>=DATE(YEAR('Model inputs'!U10),MONTH('Model inputs'!U10),1),IF(DATE(YEAR('Model inputs'!U10),MONTH('Model inputs'!U10),1)="","",DATE(2027,6,1)>=DATE(YEAR('Model inputs'!U10),MONTH('Model inputs'!U10),1)))="",FALSE,IF(ISERROR(DATE(2027,6,1)>=DATE(YEAR('Model inputs'!U10),MONTH('Model inputs'!U10),1)),DATE(2027,6,1)>=DATE(YEAR('Model inputs'!U10),MONTH('Model inputs'!U10),1),IF(DATE(YEAR('Model inputs'!U10),MONTH('Model inputs'!U10),1)="","",DATE(2027,6,1)>=DATE(YEAR('Model inputs'!U10),MONTH('Model inputs'!U10),1)))),IF('Model inputs'!U23="","",'Model inputs'!U23),0) -> 2000 | L15: =IF(IF(IF(ISERROR(DATE(2027,7,1)>=DATE(YEAR('Model inputs'!U10),MONTH('Model inputs'!U10),1)),DATE(2027,7,1)>=DATE(YEAR('Model inputs'!U10),MONTH('Model inputs'!U10),1),IF(DATE(YEAR('Model inputs'!U10),MONTH('Model inputs'!U10),1)="","",DATE(2027,7,1)>=DATE(YEAR('Model inputs'!U10),MONTH('Model inputs'!U10),1)))="",FALSE,IF(ISERROR(DATE(2027,7,1)>=DATE(YEAR('Model inputs'!U10),MONTH('Model inputs'!U10),1)),DATE(2027,7,1)>=DATE(YEAR('Model inputs'!U10),MONTH('Model inputs'!U10),1),IF(DATE(YEAR('Model inputs'!U10),MONTH('Model inputs'!U10),1)="","",DATE(2027,7,1)>=DATE(YEAR('Model inputs'!U10),MONTH('Model inputs'!U10),1)))),IF('Model inputs'!U23="","",'Model inputs'!U23),0) -> 2000 | M15: =IF(IF(IF(ISERROR(DATE(2027,8,1)>=DATE(YEAR('Model inputs'!U10),MONTH('Model inputs'!U10),1)),DATE(2027,8,1)>=DATE(YEAR('Model inputs'!U10),MONTH('Model inputs'!U10),1),IF(DATE(YEAR('Model inputs'!U10),MONTH('Model inputs'!U10),1)="","",DATE(2027,8,1)>=DATE(YEAR('Model inputs'!U10),MONTH('Model inputs'!U10),1)))="",FALSE,IF(ISERROR(DATE(2027,8,1)>=DATE(YEAR('Model inputs'!U10),MONTH('Model inputs'!U10),1)),DATE(2027,8,1)>=DATE(YEAR('Model inputs'!U10),MONTH('Model inputs'!U10),1),IF(DATE(YEAR('Model inputs'!U10),MONTH('Model inputs'!U10),1)="","",DATE(2027,8,1)>=DATE(YEAR('Model inputs'!U10),MONTH('Model inputs'!U10),1)))),IF('Model inputs'!U23="","",'Model inputs'!U23),0) -> 2000 | N15: =IF(IF(IF(ISERROR(DATE(2027,9,1)>=DATE(YEAR('Model inputs'!U10),MONTH('Model inputs'!U10),1)),DATE(2027,9,1)>=DATE(YEAR('Model inputs'!U10),MONTH('Model inputs'!U10),1),IF(DATE(YEAR('Model inputs'!U10),MONTH('Model inputs'!U10),1)="","",DATE(2027,9,1)>=DATE(YEAR('Model inputs'!U10),MONTH('Model inputs'!U10),1)))="",FALSE,IF(ISERROR(DATE(2027,9,1)>=DATE(YEAR('Model inputs'!U10),MONTH('Model inputs'!U10),1)),DATE(2027,9,1)>=DATE(YEAR('Model inputs'!U10),MONTH('Model inputs'!U10),1),IF(DATE(YEAR('Model inputs'!U10),MONTH('Model inputs'!U10),1)="","",DATE(2027,9,1)>=DATE(YEAR('Model inputs'!U10),MONTH('Model inputs'!U10),1)))),IF('Model inputs'!U23="","",'Model inputs'!U23),0) -> 2000 | O15: =IF(IF(IF(ISERROR(DATE(2027,10,1)>=DATE(YEAR('Model inputs'!U10),MONTH('Model inputs'!U10),1)),DATE(2027,10,1)>=DATE(YEAR('Model inputs'!U10),MONTH('Model inputs'!U10),1),IF(DATE(YEAR('Model inputs'!U10),MONTH('Model inputs'!U10),1)="","",DATE(2027,10,1)>=DATE(YEAR('Model inputs'!U10),MONTH('Model inputs'!U10),1)))="",FALSE,IF(ISERROR(DATE(2027,10,1)>=DATE(YEAR('Model inputs'!U10),MONTH('Model inputs'!U10),1)),DATE(2027,10,1)>=DATE(YEAR('Model inputs'!U10),MONTH('Model inputs'!U10),1),IF(DATE(YEAR('Model inputs'!U10),MONTH('Model inputs'!U10),1)="","",DATE(2027,10,1)>=DATE(YEAR('Model inputs'!U10),MONTH('Model inputs'!U10),1)))),IF('Model inputs'!U23="","",'Model inputs'!U23),0) -> 2000 | P15: =IF(IF(IF(ISERROR(DATE(2027,11,1)>=DATE(YEAR('Model inputs'!U10),MONTH('Model inputs'!U10),1)),DATE(2027,11,1)>=DATE(YEAR('Model inputs'!U10),MONTH('Model inputs'!U10),1),IF(DATE(YEAR('Model inputs'!U10),MONTH('Model inputs'!U10),1)="","",DATE(2027,11,1)>=DATE(YEAR('Model inputs'!U10),MONTH('Model inputs'!U10),1)))="",FALSE,IF(ISERROR(DATE(2027,11,1)>=DATE(YEAR('Model inputs'!U10),MONTH('Model inputs'!U10),1)),DATE(2027,11,1)>=DATE(YEAR('Model inputs'!U10),MONTH('Model inputs'!U10),1),IF(DATE(YEAR('Model inputs'!U10),MONTH('Model inputs'!U10),1)="","",DATE(2027,11,1)>=DATE(YEAR('Model inputs'!U10),MONTH('Model inputs'!U10),1)))),IF('Model inputs'!U23="","",'Model inputs'!U23),0) -> 2000 | Q15: =IF(IF(IF(ISERROR(DATE(2027,12,1)>=DATE(YEAR('Model inputs'!U10),MONTH('Model inputs'!U10),1)),DATE(2027,12,1)>=DATE(YEAR('Model inputs'!U10),MONTH('Model inputs'!U10),1),IF(DATE(YEAR('Model inputs'!U10),MONTH('Model inputs'!U10),1)="","",DATE(2027,12,1)>=DATE(YEAR('Model inputs'!U10),MONTH('Model inputs'!U10),1)))="",FALSE,IF(ISERROR(DATE(2027,12,1)>=DATE(YEAR('Model inputs'!U10),MONTH('Model inputs'!U10),1)),DATE(2027,12,1)>=DATE(YEAR('Model inputs'!U10),MONTH('Model inputs'!U10),1),IF(DATE(YEAR('Model inputs'!U10),MONTH('Model inputs'!U10),1)="","",DATE(2027,12,1)>=DATE(YEAR('Model inputs'!U10),MONTH('Model inputs'!U10),1)))),IF('Model inputs'!U23="","",'Model inputs'!U23),0) -> 2000 | R15: =IF(IF(IF(ISERROR(DATE(2028,1,1)>=DATE(YEAR('Model inputs'!U10),MONTH('Model inputs'!U10),1)),DATE(2028,1,1)>=DATE(YEAR('Model inputs'!U10),MONTH('Model inputs'!U10),1),IF(DATE(YEAR('Model inputs'!U10),MONTH('Model inputs'!U10),1)="","",DATE(2028,1,1)>=DATE(YEAR('Model inputs'!U10),MONTH('Model inputs'!U10),1)))="",FALSE,IF(ISERROR(DATE(2028,1,1)>=DATE(YEAR('Model inputs'!U10),MONTH('Model inputs'!U10),1)),DATE(2028,1,1)>=DATE(YEAR('Model inputs'!U10),MONTH('Model inputs'!U10),1),IF(DATE(YEAR('Model inputs'!U10),MONTH('Model inputs'!U10),1)="","",DATE(2028,1,1)>=DATE(YEAR('Model inputs'!U10),MONTH('Model inputs'!U10),1)))),IF('Model inputs'!U23="","",'Model inputs'!U23),0) -> 2000 | S15: =IF(IF(IF(ISERROR(DATE(2028,2,1)>=DATE(YEAR('Model inputs'!U10),MONTH('Model inputs'!U10),1)),DATE(2028,2,1)>=DATE(YEAR('Model inputs'!U10),MONTH('Model inputs'!U10),1),IF(DATE(YEAR('Model inputs'!U10),MONTH('Model inputs'!U10),1)="","",DATE(2028,2,1)>=DATE(YEAR('Model inputs'!U10),MONTH('Model inputs'!U10),1)))="",FALSE,IF(ISERROR(DATE(2028,2,1)>=DATE(YEAR('Model inputs'!U10),MONTH('Model inputs'!U10),1)),DATE(2028,2,1)>=DATE(YEAR('Model inputs'!U10),MONTH('Model inputs'!U10),1),IF(DATE(YEAR('Model inputs'!U10),MONTH('Model inputs'!U10),1)="","",DATE(2028,2,1)>=DATE(YEAR('Model inputs'!U10),MONTH('Model inputs'!U10),1)))),IF('Model inputs'!U23="","",'Model inputs'!U23),0) -> 2000 | T15: =IF(IF(IF(ISERROR(DATE(2028,3,1)>=DATE(YEAR('Model inputs'!U10),MONTH('Model inputs'!U10),1)),DATE(2028,3,1)>=DATE(YEAR('Model inputs'!U10),MONTH('Model inputs'!U10),1),IF(DATE(YEAR('Model inputs'!U10),MONTH('Model inputs'!U10),1)="","",DATE(2028,3,1)>=DATE(YEAR('Model inputs'!U10),MONTH('Model inputs'!U10),1)))="",FALSE,IF(ISERROR(DATE(2028,3,1)>=DATE(YEAR('Model inputs'!U10),MONTH('Model inputs'!U10),1)),DATE(2028,3,1)>=DATE(YEAR('Model inputs'!U10),MONTH('Model inputs'!U10),1),IF(DATE(YEAR('Model inputs'!U10),MONTH('Model inputs'!U10),1)="","",DATE(2028,3,1)>=DATE(YEAR('Model inputs'!U10),MONTH('Model inputs'!U10),1)))),IF('Model inputs'!U23="","",'Model inputs'!U23),0) -> 2000
A16: Founder payroll > Placeholder founder 2 | B16: =0 -> 0 | C16: =IF(IF(IF(ISERROR(DATE(2026,10,1)>=DATE(YEAR('Model inputs'!U11),MONTH('Model inputs'!U11),1)),DATE(2026,10,1)>=DATE(YEAR('Model inputs'!U11),MONTH('Model inputs'!U11),1),IF(DATE(YEAR('Model inputs'!U11),MONTH('Model inputs'!U11),1)="","",DATE(2026,10,1)>=DATE(YEAR('Model inputs'!U11),MONTH('Model inputs'!U11),1)))="",FALSE,IF(ISERROR(DATE(2026,10,1)>=DATE(YEAR('Model inputs'!U11),MONTH('Model inputs'!U11),1)),DATE(2026,10,1)>=DATE(YEAR('Model inputs'!U11),MONTH('Model inputs'!U11),1),IF(DATE(YEAR('Model inputs'!U11),MONTH('Model inputs'!U11),1)="","",DATE(2026,10,1)>=DATE(YEAR('Model inputs'!U11),MONTH('Model inputs'!U11),1)))),IF('Model inputs'!U24="","",'Model inputs'!U24),0) -> 0 | D16: =IF(IF(IF(ISERROR(DATE(2026,11,1)>=DATE(YEAR('Model inputs'!U11),MONTH('Model inputs'!U11),1)),DATE(2026,11,1)>=DATE(YEAR('Model inputs'!U11),MONTH('Model inputs'!U11),1),IF(DATE(YEAR('Model inputs'!U11),MONTH('Model inputs'!U11),1)="","",DATE(2026,11,1)>=DATE(YEAR('Model inputs'!U11),MONTH('Model inputs'!U11),1)))="",FALSE,IF(ISERROR(DATE(2026,11,1)>=DATE(YEAR('Model inputs'!U11),MONTH('Model inputs'!U11),1)),DATE(2026,11,1)>=DATE(YEAR('Model inputs'!U11),MONTH('Model inputs'!U11),1),IF(DATE(YEAR('Model inputs'!U11),MONTH('Model inputs'!U11),1)="","",DATE(2026,11,1)>=DATE(YEAR('Model inputs'!U11),MONTH('Model inputs'!U11),1)))),IF('Model inputs'!U24="","",'Model inputs'!U24),0) -> 0 | E16: =IF(IF(IF(ISERROR(DATE(2026,12,1)>=DATE(YEAR('Model inputs'!U11),MONTH('Model inputs'!U11),1)),DATE(2026,12,1)>=DATE(YEAR('Model inputs'!U11),MONTH('Model inputs'!U11),1),IF(DATE(YEAR('Model inputs'!U11),MONTH('Model inputs'!U11),1)="","",DATE(2026,12,1)>=DATE(YEAR('Model inputs'!U11),MONTH('Model inputs'!U11),1)))="",FALSE,IF(ISERROR(DATE(2026,12,1)>=DATE(YEAR('Model inputs'!U11),MONTH('Model inputs'!U11),1)),DATE(2026,12,1)>=DATE(YEAR('Model inputs'!U11),MONTH('Model inputs'!U11),1),IF(DATE(YEAR('Model inputs'!U11),MONTH('Model inputs'!U11),1)="","",DATE(2026,12,1)>=DATE(YEAR('Model inputs'!U11),MONTH('Model inputs'!U11),1)))),IF('Model inputs'!U24="","",'Model inputs'!U24),0) -> 0 | F16: =IF(IF(IF(ISERROR(DATE(2027,1,1)>=DATE(YEAR('Model inputs'!U11),MONTH('Model inputs'!U11),1)),DATE(2027,1,1)>=DATE(YEAR('Model inputs'!U11),MONTH('Model inputs'!U11),1),IF(DATE(YEAR('Model inputs'!U11),MONTH('Model inputs'!U11),1)="","",DATE(2027,1,1)>=DATE(YEAR('Model inputs'!U11),MONTH('Model inputs'!U11),1)))="",FALSE,IF(ISERROR(DATE(2027,1,1)>=DATE(YEAR('Model inputs'!U11),MONTH('Model inputs'!U11),1)),DATE(2027,1,1)>=DATE(YEAR('Model inputs'!U11),MONTH('Model inputs'!U11),1),IF(DATE(YEAR('Model inputs'!U11),MONTH('Model inputs'!U11),1)="","",DATE(2027,1,1)>=DATE(YEAR('Model inputs'!U11),MONTH('Model inputs'!U11),1)))),IF('Model inputs'!U24="","",'Model inputs'!U24),0) -> 0 | G16: =IF(IF(IF(ISERROR(DATE(2027,2,1)>=DATE(YEAR('Model inputs'!U11),MONTH('Model inputs'!U11),1)),DATE(2027,2,1)>=DATE(YEAR('Model inputs'!U11),MONTH('Model inputs'!U11),1),IF(DATE(YEAR('Model inputs'!U11),MONTH('Model inputs'!U11),1)="","",DATE(2027,2,1)>=DATE(YEAR('Model inputs'!U11),MONTH('Model inputs'!U11),1)))="",FALSE,IF(ISERROR(DATE(2027,2,1)>=DATE(YEAR('Model inputs'!U11),MONTH('Model inputs'!U11),1)),DATE(2027,2,1)>=DATE(YEAR('Model inputs'!U11),MONTH('Model inputs'!U11),1),IF(DATE(YEAR('Model inputs'!U11),MONTH('Model inputs'!U11),1)="","",DATE(2027,2,1)>=DATE(YEAR('Model inputs'!U11),MONTH('Model inputs'!U11),1)))),IF('Model inputs'!U24="","",'Model inputs'!U24),0) -> 0 | H16: =IF(IF(IF(ISERROR(DATE(2027,3,1)>=DATE(YEAR('Model inputs'!U11),MONTH('Model inputs'!U11),1)),DATE(2027,3,1)>=DATE(YEAR('Model inputs'!U11),MONTH('Model inputs'!U11),1),IF(DATE(YEAR('Model inputs'!U11),MONTH('Model inputs'!U11),1)="","",DATE(2027,3,1)>=DATE(YEAR('Model inputs'!U11),MONTH('Model inputs'!U11),1)))="",FALSE,IF(ISERROR(DATE(2027,3,1)>=DATE(YEAR('Model inputs'!U11),MONTH('Model inputs'!U11),1)),DATE(2027,3,1)>=DATE(YEAR('Model inputs'!U11),MONTH('Model inputs'!U11),1),IF(DATE(YEAR('Model inputs'!U11),MONTH('Model inputs'!U11),1)="","",DATE(2027,3,1)>=DATE(YEAR('Model inputs'!U11),MONTH('Model inputs'!U11),1)))),IF('Model inputs'!U24="","",'Model inputs'!U24),0) -> 0 | I16: =IF(IF(IF(ISERROR(DATE(2027,4,1)>=DATE(YEAR('Model inputs'!U11),MONTH('Model inputs'!U11),1)),DATE(2027,4,1)>=DATE(YEAR('Model inputs'!U11),MONTH('Model inputs'!U11),1),IF(DATE(YEAR('Model inputs'!U11),MONTH('Model inputs'!U11),1)="","",DATE(2027,4,1)>=DATE(YEAR('Model inputs'!U11),MONTH('Model inputs'!U11),1)))="",FALSE,IF(ISERROR(DATE(2027,4,1)>=DATE(YEAR('Model inputs'!U11),MONTH('Model inputs'!U11),1)),DATE(2027,4,1)>=DATE(YEAR('Model inputs'!U11),MONTH('Model inputs'!U11),1),IF(DATE(YEAR('Model inputs'!U11),MONTH('Model inputs'!U11),1)="","",DATE(2027,4,1)>=DATE(YEAR('Model inputs'!U11),MONTH('Model inputs'!U11),1)))),IF('Model inputs'!U24="","",'Model inputs'!U24),0) -> 2000 | J16: =IF(IF(IF(ISERROR(DATE(2027,5,1)>=DATE(YEAR('Model inputs'!U11),MONTH('Model inputs'!U11),1)),DATE(2027,5,1)>=DATE(YEAR('Model inputs'!U11),MONTH('Model inputs'!U11),1),IF(DATE(YEAR('Model inputs'!U11),MONTH('Model inputs'!U11),1)="","",DATE(2027,5,1)>=DATE(YEAR('Model inputs'!U11),MONTH('Model inputs'!U11),1)))="",FALSE,IF(ISERROR(DATE(2027,5,1)>=DATE(YEAR('Model inputs'!U11),MONTH('Model inputs'!U11),1)),DATE(2027,5,1)>=DATE(YEAR('Model inputs'!U11),MONTH('Model inputs'!U11),1),IF(DATE(YEAR('Model inputs'!U11),MONTH('Model inputs'!U11),1)="","",DATE(2027,5,1)>=DATE(YEAR('Model inputs'!U11),MONTH('Model inputs'!U11),1)))),IF('Model inputs'!U24="","",'Model inputs'!U24),0) -> 2000 | K16: =IF(IF(IF(ISERROR(DATE(2027,6,1)>=DATE(YEAR('Model inputs'!U11),MONTH('Model inputs'!U11),1)),DATE(2027,6,1)>=DATE(YEAR('Model inputs'!U11),MONTH('Model inputs'!U11),1),IF(DATE(YEAR('Model inputs'!U11),MONTH('Model inputs'!U11),1)="","",DATE(2027,6,1)>=DATE(YEAR('Model inputs'!U11),MONTH('Model inputs'!U11),1)))="",FALSE,IF(ISERROR(DATE(2027,6,1)>=DATE(YEAR('Model inputs'!U11),MONTH('Model inputs'!U11),1)),DATE(2027,6,1)>=DATE(YEAR('Model inputs'!U11),MONTH('Model inputs'!U11),1),IF(DATE(YEAR('Model inputs'!U11),MONTH('Model inputs'!U11),1)="","",DATE(2027,6,1)>=DATE(YEAR('Model inputs'!U11),MONTH('Model inputs'!U11),1)))),IF('Model inputs'!U24="","",'Model inputs'!U24),0) -> 2000 | L16: =IF(IF(IF(ISERROR(DATE(2027,7,1)>=DATE(YEAR('Model inputs'!U11),MONTH('Model inputs'!U11),1)),DATE(2027,7,1)>=DATE(YEAR('Model inputs'!U11),MONTH('Model inputs'!U11),1),IF(DATE(YEAR('Model inputs'!U11),MONTH('Model inputs'!U11),1)="","",DATE(2027,7,1)>=DATE(YEAR('Model inputs'!U11),MONTH('Model inputs'!U11),1)))="",FALSE,IF(ISERROR(DATE(2027,7,1)>=DATE(YEAR('Model inputs'!U11),MONTH('Model inputs'!U11),1)),DATE(2027,7,1)>=DATE(YEAR('Model inputs'!U11),MONTH('Model inputs'!U11),1),IF(DATE(YEAR('Model inputs'!U11),MONTH('Model inputs'!U11),1)="","",DATE(2027,7,1)>=DATE(YEAR('Model inputs'!U11),MONTH('Model inputs'!U11),1)))),IF('Model inputs'!U24="","",'Model inputs'!U24),0) -> 2000 | M16: =IF(IF(IF(ISERROR(DATE(2027,8,1)>=DATE(YEAR('Model inputs'!U11),MONTH('Model inputs'!U11),1)),DATE(2027,8,1)>=DATE(YEAR('Model inputs'!U11),MONTH('Model inputs'!U11),1),IF(DATE(YEAR('Model inputs'!U11),MONTH('Model inputs'!U11),1)="","",DATE(2027,8,1)>=DATE(YEAR('Model inputs'!U11),MONTH('Model inputs'!U11),1)))="",FALSE,IF(ISERROR(DATE(2027,8,1)>=DATE(YEAR('Model inputs'!U11),MONTH('Model inputs'!U11),1)),DATE(2027,8,1)>=DATE(YEAR('Model inputs'!U11),MONTH('Model inputs'!U11),1),IF(DATE(YEAR('Model inputs'!U11),MONTH('Model inputs'!U11),1)="","",DATE(2027,8,1)>=DATE(YEAR('Model inputs'!U11),MONTH('Model inputs'!U11),1)))),IF('Model inputs'!U24="","",'Model inputs'!U24),0) -> 2000 | N16: =IF(IF(IF(ISERROR(DATE(2027,9,1)>=DATE(YEAR('Model inputs'!U11),MONTH('Model inputs'!U11),1)),DATE(2027,9,1)>=DATE(YEAR('Model inputs'!U11),MONTH('Model inputs'!U11),1),IF(DATE(YEAR('Model inputs'!U11),MONTH('Model inputs'!U11),1)="","",DATE(2027,9,1)>=DATE(YEAR('Model inputs'!U11),MONTH('Model inputs'!U11),1)))="",FALSE,IF(ISERROR(DATE(2027,9,1)>=DATE(YEAR('Model inputs'!U11),MONTH('Model inputs'!U11),1)),DATE(2027,9,1)>=DATE(YEAR('Model inputs'!U11),MONTH('Model inputs'!U11),1),IF(DATE(YEAR('Model inputs'!U11),MONTH('Model inputs'!U11),1)="","",DATE(2027,9,1)>=DATE(YEAR('Model inputs'!U11),MONTH('Model inputs'!U11),1)))),IF('Model inputs'!U24="","",'Model inputs'!U24),0) -> 2000 | O16: =IF(IF(IF(ISERROR(DATE(2027,10,1)>=DATE(YEAR('Model inputs'!U11),MONTH('Model inputs'!U11),1)),DATE(2027,10,1)>=DATE(YEAR('Model inputs'!U11),MONTH('Model inputs'!U11),1),IF(DATE(YEAR('Model inputs'!U11),MONTH('Model inputs'!U11),1)="","",DATE(2027,10,1)>=DATE(YEAR('Model inputs'!U11),MONTH('Model inputs'!U11),1)))="",FALSE,IF(ISERROR(DATE(2027,10,1)>=DATE(YEAR('Model inputs'!U11),MONTH('Model inputs'!U11),1)),DATE(2027,10,1)>=DATE(YEAR('Model inputs'!U11),MONTH('Model inputs'!U11),1),IF(DATE(YEAR('Model inputs'!U11),MONTH('Model inputs'!U11),1)="","",DATE(2027,10,1)>=DATE(YEAR('Model inputs'!U11),MONTH('Model inputs'!U11),1)))),IF('Model inputs'!U24="","",'Model inputs'!U24),0) -> 2000 | P16: =IF(IF(IF(ISERROR(DATE(2027,11,1)>=DATE(YEAR('Model inputs'!U11),MONTH('Model inputs'!U11),1)),DATE(2027,11,1)>=DATE(YEAR('Model inputs'!U11),MONTH('Model inputs'!U11),1),IF(DATE(YEAR('Model inputs'!U11),MONTH('Model inputs'!U11),1)="","",DATE(2027,11,1)>=DATE(YEAR('Model inputs'!U11),MONTH('Model inputs'!U11),1)))="",FALSE,IF(ISERROR(DATE(2027,11,1)>=DATE(YEAR('Model inputs'!U11),MONTH('Model inputs'!U11),1)),DATE(2027,11,1)>=DATE(YEAR('Model inputs'!U11),MONTH('Model inputs'!U11),1),IF(DATE(YEAR('Model inputs'!U11),MONTH('Model inputs'!U11),1)="","",DATE(2027,11,1)>=DATE(YEAR('Model inputs'!U11),MONTH('Model inputs'!U11),1)))),IF('Model inputs'!U24="","",'Model inputs'!U24),0) -> 2000 | Q16: =IF(IF(IF(ISERROR(DATE(2027,12,1)>=DATE(YEAR('Model inputs'!U11),MONTH('Model inputs'!U11),1)),DATE(2027,12,1)>=DATE(YEAR('Model inputs'!U11),MONTH('Model inputs'!U11),1),IF(DATE(YEAR('Model inputs'!U11),MONTH('Model inputs'!U11),1)="","",DATE(2027,12,1)>=DATE(YEAR('Model inputs'!U11),MONTH('Model inputs'!U11),1)))="",FALSE,IF(ISERROR(DATE(2027,12,1)>=DATE(YEAR('Model inputs'!U11),MONTH('Model inputs'!U11),1)),DATE(2027,12,1)>=DATE(YEAR('Model inputs'!U11),MONTH('Model inputs'!U11),1),IF(DATE(YEAR('Model inputs'!U11),MONTH('Model inputs'!U11),1)="","",DATE(2027,12,1)>=DATE(YEAR('Model inputs'!U11),MONTH('Model inputs'!U11),1)))),IF('Model inputs'!U24="","",'Model inputs'!U24),0) -> 2000 | R16: =IF(IF(IF(ISERROR(DATE(2028,1,1)>=DATE(YEAR('Model inputs'!U11),MONTH('Model inputs'!U11),1)),DATE(2028,1,1)>=DATE(YEAR('Model inputs'!U11),MONTH('Model inputs'!U11),1),IF(DATE(YEAR('Model inputs'!U11),MONTH('Model inputs'!U11),1)="","",DATE(2028,1,1)>=DATE(YEAR('Model inputs'!U11),MONTH('Model inputs'!U11),1)))="",FALSE,IF(ISERROR(DATE(2028,1,1)>=DATE(YEAR('Model inputs'!U11),MONTH('Model inputs'!U11),1)),DATE(2028,1,1)>=DATE(YEAR('Model inputs'!U11),MONTH('Model inputs'!U11),1),IF(DATE(YEAR('Model inputs'!U11),MONTH('Model inputs'!U11),1)="","",DATE(2028,1,1)>=DATE(YEAR('Model inputs'!U11),MONTH('Model inputs'!U11),1)))),IF('Model inputs'!U24="","",'Model inputs'!U24),0) -> 2000 | S16: =IF(IF(IF(ISERROR(DATE(2028,2,1)>=DATE(YEAR('Model inputs'!U11),MONTH('Model inputs'!U11),1)),DATE(2028,2,1)>=DATE(YEAR('Model inputs'!U11),MONTH('Model inputs'!U11),1),IF(DATE(YEAR('Model inputs'!U11),MONTH('Model inputs'!U11),1)="","",DATE(2028,2,1)>=DATE(YEAR('Model inputs'!U11),MONTH('Model inputs'!U11),1)))="",FALSE,IF(ISERROR(DATE(2028,2,1)>=DATE(YEAR('Model inputs'!U11),MONTH('Model inputs'!U11),1)),DATE(2028,2,1)>=DATE(YEAR('Model inputs'!U11),MONTH('Model inputs'!U11),1),IF(DATE(YEAR('Model inputs'!U11),MONTH('Model inputs'!U11),1)="","",DATE(2028,2,1)>=DATE(YEAR('Model inputs'!U11),MONTH('Model inputs'!U11),1)))),IF('Model inputs'!U24="","",'Model inputs'!U24),0) -> 2000 | T16: =IF(IF(IF(ISERROR(DATE(2028,3,1)>=DATE(YEAR('Model inputs'!U11),MONTH('Model inputs'!U11),1)),DATE(2028,3,1)>=DATE(YEAR('Model inputs'!U11),MONTH('Model inputs'!U11),1),IF(DATE(YEAR('Model inputs'!U11),MONTH('Model inputs'!U11),1)="","",DATE(2028,3,1)>=DATE(YEAR('Model inputs'!U11),MONTH('Model inputs'!U11),1)))="",FALSE,IF(ISERROR(DATE(2028,3,1)>=DATE(YEAR('Model inputs'!U11),MONTH('Model inputs'!U11),1)),DATE(2028,3,1)>=DATE(YEAR('Model inputs'!U11),MONTH('Model inputs'!U11),1),IF(DATE(YEAR('Model inputs'!U11),MONTH('Model inputs'!U11),1)="","",DATE(2028,3,1)>=DATE(YEAR('Model inputs'!U11),MONTH('Model inputs'!U11),1)))),IF('Model inputs'!U24="","",'Model inputs'!U24),0) -> 2000
A17: Founder payroll > Placeholder founder 3 | B17: =0 -> 0 | C17: =IF(IF(IF(ISERROR(DATE(2026,10,1)>=DATE(YEAR('Model inputs'!U12),MONTH('Model inputs'!U12),1)),DATE(2026,10,1)>=DATE(YEAR('Model inputs'!U12),MONTH('Model inputs'!U12),1),IF(DATE(YEAR('Model inputs'!U12),MONTH('Model inputs'!U12),1)="","",DATE(2026,10,1)>=DATE(YEAR('Model inputs'!U12),MONTH('Model inputs'!U12),1)))="",FALSE,IF(ISERROR(DATE(2026,10,1)>=DATE(YEAR('Model inputs'!U12),MONTH('Model inputs'!U12),1)),DATE(2026,10,1)>=DATE(YEAR('Model inputs'!U12),MONTH('Model inputs'!U12),1),IF(DATE(YEAR('Model inputs'!U12),MONTH('Model inputs'!U12),1)="","",DATE(2026,10,1)>=DATE(YEAR('Model inputs'!U12),MONTH('Model inputs'!U12),1)))),IF('Model inputs'!U25="","",'Model inputs'!U25),0) -> 0 | D17: =IF(IF(IF(ISERROR(DATE(2026,11,1)>=DATE(YEAR('Model inputs'!U12),MONTH('Model inputs'!U12),1)),DATE(2026,11,1)>=DATE(YEAR('Model inputs'!U12),MONTH('Model inputs'!U12),1),IF(DATE(YEAR('Model inputs'!U12),MONTH('Model inputs'!U12),1)="","",DATE(2026,11,1)>=DATE(YEAR('Model inputs'!U12),MONTH('Model inputs'!U12),1)))="",FALSE,IF(ISERROR(DATE(2026,11,1)>=DATE(YEAR('Model inputs'!U12),MONTH('Model inputs'!U12),1)),DATE(2026,11,1)>=DATE(YEAR('Model inputs'!U12),MONTH('Model inputs'!U12),1),IF(DATE(YEAR('Model inputs'!U12),MONTH('Model inputs'!U12),1)="","",DATE(2026,11,1)>=DATE(YEAR('Model inputs'!U12),MONTH('Model inputs'!U12),1)))),IF('Model inputs'!U25="","",'Model inputs'!U25),0) -> 0 | E17: =IF(IF(IF(ISERROR(DATE(2026,12,1)>=DATE(YEAR('Model inputs'!U12),MONTH('Model inputs'!U12),1)),DATE(2026,12,1)>=DATE(YEAR('Model inputs'!U12),MONTH('Model inputs'!U12),1),IF(DATE(YEAR('Model inputs'!U12),MONTH('Model inputs'!U12),1)="","",DATE(2026,12,1)>=DATE(YEAR('Model inputs'!U12),MONTH('Model inputs'!U12),1)))="",FALSE,IF(ISERROR(DATE(2026,12,1)>=DATE(YEAR('Model inputs'!U12),MONTH('Model inputs'!U12),1)),DATE(2026,12,1)>=DATE(YEAR('Model inputs'!U12),MONTH('Model inputs'!U12),1),IF(DATE(YEAR('Model inputs'!U12),MONTH('Model inputs'!U12),1)="","",DATE(2026,12,1)>=DATE(YEAR('Model inputs'!U12),MONTH('Model inputs'!U12),1)))),IF('Model inputs'!U25="","",'Model inputs'!U25),0) -> 0 | F17: =IF(IF(IF(ISERROR(DATE(2027,1,1)>=DATE(YEAR('Model inputs'!U12),MONTH('Model inputs'!U12),1)),DATE(2027,1,1)>=DATE(YEAR('Model inputs'!U12),MONTH('Model inputs'!U12),1),IF(DATE(YEAR('Model inputs'!U12),MONTH('Model inputs'!U12),1)="","",DATE(2027,1,1)>=DATE(YEAR('Model inputs'!U12),MONTH('Model inputs'!U12),1)))="",FALSE,IF(ISERROR(DATE(2027,1,1)>=DATE(YEAR('Model inputs'!U12),MONTH('Model inputs'!U12),1)),DATE(2027,1,1)>=DATE(YEAR('Model inputs'!U12),MONTH('Model inputs'!U12),1),IF(DATE(YEAR('Model inputs'!U12),MONTH('Model inputs'!U12),1)="","",DATE(2027,1,1)>=DATE(YEAR('Model inputs'!U12),MONTH('Model inputs'!U12),1)))),IF('Model inputs'!U25="","",'Model inputs'!U25),0) -> 0 | G17: =IF(IF(IF(ISERROR(DATE(2027,2,1)>=DATE(YEAR('Model inputs'!U12),MONTH('Model inputs'!U12),1)),DATE(2027,2,1)>=DATE(YEAR('Model inputs'!U12),MONTH('Model inputs'!U12),1),IF(DATE(YEAR('Model inputs'!U12),MONTH('Model inputs'!U12),1)="","",DATE(2027,2,1)>=DATE(YEAR('Model inputs'!U12),MONTH('Model inputs'!U12),1)))="",FALSE,IF(ISERROR(DATE(2027,2,1)>=DATE(YEAR('Model inputs'!U12),MONTH('Model inputs'!U12),1)),DATE(2027,2,1)>=DATE(YEAR('Model inputs'!U12),MONTH('Model inputs'!U12),1),IF(DATE(YEAR('Model inputs'!U12),MONTH('Model inputs'!U12),1)="","",DATE(2027,2,1)>=DATE(YEAR('Model inputs'!U12),MONTH('Model inputs'!U12),1)))),IF('Model inputs'!U25="","",'Model inputs'!U25),0) -> 0 | H17: =IF(IF(IF(ISERROR(DATE(2027,3,1)>=DATE(YEAR('Model inputs'!U12),MONTH('Model inputs'!U12),1)),DATE(2027,3,1)>=DATE(YEAR('Model inputs'!U12),MONTH('Model inputs'!U12),1),IF(DATE(YEAR('Model inputs'!U12),MONTH('Model inputs'!U12),1)="","",DATE(2027,3,1)>=DATE(YEAR('Model inputs'!U12),MONTH('Model inputs'!U12),1)))="",FALSE,IF(ISERROR(DATE(2027,3,1)>=DATE(YEAR('Model inputs'!U12),MONTH('Model inputs'!U12),1)),DATE(2027,3,1)>=DATE(YEAR('Model inputs'!U12),MONTH('Model inputs'!U12),1),IF(DATE(YEAR('Model inputs'!U12),MONTH('Model inputs'!U12),1)="","",DATE(2027,3,1)>=DATE(YEAR('Model inputs'!U12),MONTH('Model inputs'!U12),1)))),IF('Model inputs'!U25="","",'Model inputs'!U25),0) -> 0 | I17: =IF(IF(IF(ISERROR(DATE(2027,4,1)>=DATE(YEAR('Model inputs'!U12),MONTH('Model inputs'!U12),1)),DATE(2027,4,1)>=DATE(YEAR('Model inputs'!U12),MONTH('Model inputs'!U12),1),IF(DATE(YEAR('Model inputs'!U12),MONTH('Model inputs'!U12),1)="","",DATE(2027,4,1)>=DATE(YEAR('Model inputs'!U12),MONTH('Model inputs'!U12),1)))="",FALSE,IF(ISERROR(DATE(2027,4,1)>=DATE(YEAR('Model inputs'!U12),MONTH('Model inputs'!U12),1)),DATE(2027,4,1)>=DATE(YEAR('Model inputs'!U12),MONTH('Model inputs'!U12),1),IF(DATE(YEAR('Model inputs'!U12),MONTH('Model inputs'!U12),1)="","",DATE(2027,4,1)>=DATE(YEAR('Model inputs'!U12),MONTH('Model inputs'!U12),1)))),IF('Model inputs'!U25="","",'Model inputs'!U25),0) -> 2000 | J17: =IF(IF(IF(ISERROR(DATE(2027,5,1)>=DATE(YEAR('Model inputs'!U12),MONTH('Model inputs'!U12),1)),DATE(2027,5,1)>=DATE(YEAR('Model inputs'!U12),MONTH('Model inputs'!U12),1),IF(DATE(YEAR('Model inputs'!U12),MONTH('Model inputs'!U12),1)="","",DATE(2027,5,1)>=DATE(YEAR('Model inputs'!U12),MONTH('Model inputs'!U12),1)))="",FALSE,IF(ISERROR(DATE(2027,5,1)>=DATE(YEAR('Model inputs'!U12),MONTH('Model inputs'!U12),1)),DATE(2027,5,1)>=DATE(YEAR('Model inputs'!U12),MONTH('Model inputs'!U12),1),IF(DATE(YEAR('Model inputs'!U12),MONTH('Model inputs'!U12),1)="","",DATE(2027,5,1)>=DATE(YEAR('Model inputs'!U12),MONTH('Model inputs'!U12),1)))),IF('Model inputs'!U25="","",'Model inputs'!U25),0) -> 2000 | K17: =IF(IF(IF(ISERROR(DATE(2027,6,1)>=DATE(YEAR('Model inputs'!U12),MONTH('Model inputs'!U12),1)),DATE(2027,6,1)>=DATE(YEAR('Model inputs'!U12),MONTH('Model inputs'!U12),1),IF(DATE(YEAR('Model inputs'!U12),MONTH('Model inputs'!U12),1)="","",DATE(2027,6,1)>=DATE(YEAR('Model inputs'!U12),MONTH('Model inputs'!U12),1)))="",FALSE,IF(ISERROR(DATE(2027,6,1)>=DATE(YEAR('Model inputs'!U12),MONTH('Model inputs'!U12),1)),DATE(2027,6,1)>=DATE(YEAR('Model inputs'!U12),MONTH('Model inputs'!U12),1),IF(DATE(YEAR('Model inputs'!U12),MONTH('Model inputs'!U12),1)="","",DATE(2027,6,1)>=DATE(YEAR('Model inputs'!U12),MONTH('Model inputs'!U12),1)))),IF('Model inputs'!U25="","",'Model inputs'!U25),0) -> 2000 | L17: =IF(IF(IF(ISERROR(DATE(2027,7,1)>=DATE(YEAR('Model inputs'!U12),MONTH('Model inputs'!U12),1)),DATE(2027,7,1)>=DATE(YEAR('Model inputs'!U12),MONTH('Model inputs'!U12),1),IF(DATE(YEAR('Model inputs'!U12),MONTH('Model inputs'!U12),1)="","",DATE(2027,7,1)>=DATE(YEAR('Model inputs'!U12),MONTH('Model inputs'!U12),1)))="",FALSE,IF(ISERROR(DATE(2027,7,1)>=DATE(YEAR('Model inputs'!U12),MONTH('Model inputs'!U12),1)),DATE(2027,7,1)>=DATE(YEAR('Model inputs'!U12),MONTH('Model inputs'!U12),1),IF(DATE(YEAR('Model inputs'!U12),MONTH('Model inputs'!U12),1)="","",DATE(2027,7,1)>=DATE(YEAR('Model inputs'!U12),MONTH('Model inputs'!U12),1)))),IF('Model inputs'!U25="","",'Model inputs'!U25),0) -> 2000 | M17: =IF(IF(IF(ISERROR(DATE(2027,8,1)>=DATE(YEAR('Model inputs'!U12),MONTH('Model inputs'!U12),1)),DATE(2027,8,1)>=DATE(YEAR('Model inputs'!U12),MONTH('Model inputs'!U12),1),IF(DATE(YEAR('Model inputs'!U12),MONTH('Model inputs'!U12),1)="","",DATE(2027,8,1)>=DATE(YEAR('Model inputs'!U12),MONTH('Model inputs'!U12),1)))="",FALSE,IF(ISERROR(DATE(2027,8,1)>=DATE(YEAR('Model inputs'!U12),MONTH('Model inputs'!U12),1)),DATE(2027,8,1)>=DATE(YEAR('Model inputs'!U12),MONTH('Model inputs'!U12),1),IF(DATE(YEAR('Model inputs'!U12),MONTH('Model inputs'!U12),1)="","",DATE(2027,8,1)>=DATE(YEAR('Model inputs'!U12),MONTH('Model inputs'!U12),1)))),IF('Model inputs'!U25="","",'Model inputs'!U25),0) -> 2000 | N17: =IF(IF(IF(ISERROR(DATE(2027,9,1)>=DATE(YEAR('Model inputs'!U12),MONTH('Model inputs'!U12),1)),DATE(2027,9,1)>=DATE(YEAR('Model inputs'!U12),MONTH('Model inputs'!U12),1),IF(DATE(YEAR('Model inputs'!U12),MONTH('Model inputs'!U12),1)="","",DATE(2027,9,1)>=DATE(YEAR('Model inputs'!U12),MONTH('Model inputs'!U12),1)))="",FALSE,IF(ISERROR(DATE(2027,9,1)>=DATE(YEAR('Model inputs'!U12),MONTH('Model inputs'!U12),1)),DATE(2027,9,1)>=DATE(YEAR('Model inputs'!U12),MONTH('Model inputs'!U12),1),IF(DATE(YEAR('Model inputs'!U12),MONTH('Model inputs'!U12),1)="","",DATE(2027,9,1)>=DATE(YEAR('Model inputs'!U12),MONTH('Model inputs'!U12),1)))),IF('Model inputs'!U25="","",'Model inputs'!U25),0) -> 2000 | O17: =IF(IF(IF(ISERROR(DATE(2027,10,1)>=DATE(YEAR('Model inputs'!U12),MONTH('Model inputs'!U12),1)),DATE(2027,10,1)>=DATE(YEAR('Model inputs'!U12),MONTH('Model inputs'!U12),1),IF(DATE(YEAR('Model inputs'!U12),MONTH('Model inputs'!U12),1)="","",DATE(2027,10,1)>=DATE(YEAR('Model inputs'!U12),MONTH('Model inputs'!U12),1)))="",FALSE,IF(ISERROR(DATE(2027,10,1)>=DATE(YEAR('Model inputs'!U12),MONTH('Model inputs'!U12),1)),DATE(2027,10,1)>=DATE(YEAR('Model inputs'!U12),MONTH('Model inputs'!U12),1),IF(DATE(YEAR('Model inputs'!U12),MONTH('Model inputs'!U12),1)="","",DATE(2027,10,1)>=DATE(YEAR('Model inputs'!U12),MONTH('Model inputs'!U12),1)))),IF('Model inputs'!U25="","",'Model inputs'!U25),0) -> 2000 | P17: =IF(IF(IF(ISERROR(DATE(2027,11,1)>=DATE(YEAR('Model inputs'!U12),MONTH('Model inputs'!U12),1)),DATE(2027,11,1)>=DATE(YEAR('Model inputs'!U12),MONTH('Model inputs'!U12),1),IF(DATE(YEAR('Model inputs'!U12),MONTH('Model inputs'!U12),1)="","",DATE(2027,11,1)>=DATE(YEAR('Model inputs'!U12),MONTH('Model inputs'!U12),1)))="",FALSE,IF(ISERROR(DATE(2027,11,1)>=DATE(YEAR('Model inputs'!U12),MONTH('Model inputs'!U12),1)),DATE(2027,11,1)>=DATE(YEAR('Model inputs'!U12),MONTH('Model inputs'!U12),1),IF(DATE(YEAR('Model inputs'!U12),MONTH('Model inputs'!U12),1)="","",DATE(2027,11,1)>=DATE(YEAR('Model inputs'!U12),MONTH('Model inputs'!U12),1)))),IF('Model inputs'!U25="","",'Model inputs'!U25),0) -> 2000 | Q17: =IF(IF(IF(ISERROR(DATE(2027,12,1)>=DATE(YEAR('Model inputs'!U12),MONTH('Model inputs'!U12),1)),DATE(2027,12,1)>=DATE(YEAR('Model inputs'!U12),MONTH('Model inputs'!U12),1),IF(DATE(YEAR('Model inputs'!U12),MONTH('Model inputs'!U12),1)="","",DATE(2027,12,1)>=DATE(YEAR('Model inputs'!U12),MONTH('Model inputs'!U12),1)))="",FALSE,IF(ISERROR(DATE(2027,12,1)>=DATE(YEAR('Model inputs'!U12),MONTH('Model inputs'!U12),1)),DATE(2027,12,1)>=DATE(YEAR('Model inputs'!U12),MONTH('Model inputs'!U12),1),IF(DATE(YEAR('Model inputs'!U12),MONTH('Model inputs'!U12),1)="","",DATE(2027,12,1)>=DATE(YEAR('Model inputs'!U12),MONTH('Model inputs'!U12),1)))),IF('Model inputs'!U25="","",'Model inputs'!U25),0) -> 2000 | R17: =IF(IF(IF(ISERROR(DATE(2028,1,1)>=DATE(YEAR('Model inputs'!U12),MONTH('Model inputs'!U12),1)),DATE(2028,1,1)>=DATE(YEAR('Model inputs'!U12),MONTH('Model inputs'!U12),1),IF(DATE(YEAR('Model inputs'!U12),MONTH('Model inputs'!U12),1)="","",DATE(2028,1,1)>=DATE(YEAR('Model inputs'!U12),MONTH('Model inputs'!U12),1)))="",FALSE,IF(ISERROR(DATE(2028,1,1)>=DATE(YEAR('Model inputs'!U12),MONTH('Model inputs'!U12),1)),DATE(2028,1,1)>=DATE(YEAR('Model inputs'!U12),MONTH('Model inputs'!U12),1),IF(DATE(YEAR('Model inputs'!U12),MONTH('Model inputs'!U12),1)="","",DATE(2028,1,1)>=DATE(YEAR('Model inputs'!U12),MONTH('Model inputs'!U12),1)))),IF('Model inputs'!U25="","",'Model inputs'!U25),0) -> 2000 | S17: =IF(IF(IF(ISERROR(DATE(2028,2,1)>=DATE(YEAR('Model inputs'!U12),MONTH('Model inputs'!U12),1)),DATE(2028,2,1)>=DATE(YEAR('Model inputs'!U12),MONTH('Model inputs'!U12),1),IF(DATE(YEAR('Model inputs'!U12),MONTH('Model inputs'!U12),1)="","",DATE(2028,2,1)>=DATE(YEAR('Model inputs'!U12),MONTH('Model inputs'!U12),1)))="",FALSE,IF(ISERROR(DATE(2028,2,1)>=DATE(YEAR('Model inputs'!U12),MONTH('Model inputs'!U12),1)),DATE(2028,2,1)>=DATE(YEAR('Model inputs'!U12),MONTH('Model inputs'!U12),1),IF(DATE(YEAR('Model inputs'!U12),MONTH('Model inputs'!U12),1)="","",DATE(2028,2,1)>=DATE(YEAR('Model inputs'!U12),MONTH('Model inputs'!U12),1)))),IF('Model inputs'!U25="","",'Model inputs'!U25),0) -> 2000 | T17: =IF(IF(IF(ISERROR(DATE(2028,3,1)>=DATE(YEAR('Model inputs'!U12),MONTH('Model inputs'!U12),1)),DATE(2028,3,1)>=DATE(YEAR('Model inputs'!U12),MONTH('Model inputs'!U12),1),IF(DATE(YEAR('Model inputs'!U12),MONTH('Model inputs'!U12),1)="","",DATE(2028,3,1)>=DATE(YEAR('Model inputs'!U12),MONTH('Model inputs'!U12),1)))="",FALSE,IF(ISERROR(DATE(2028,3,1)>=DATE(YEAR('Model inputs'!U12),MONTH('Model inputs'!U12),1)),DATE(2028,3,1)>=DATE(YEAR('Model inputs'!U12),MONTH('Model inputs'!U12),1),IF(DATE(YEAR('Model inputs'!U12),MONTH('Model inputs'!U12),1)="","",DATE(2028,3,1)>=DATE(YEAR('Model inputs'!U12),MONTH('Model inputs'!U12),1)))),IF('Model inputs'!U25="","",'Model inputs'!U25),0) -> 2000
A18: Founder payroll > Placeholder founder 4 | B18: =0 -> 0 | C18: =IF(IF(IF(ISERROR(DATE(2026,10,1)>=DATE(YEAR('Model inputs'!U13),MONTH('Model inputs'!U13),1)),DATE(2026,10,1)>=DATE(YEAR('Model inputs'!U13),MONTH('Model inputs'!U13),1),IF(DATE(YEAR('Model inputs'!U13),MONTH('Model inputs'!U13),1)="","",DATE(2026,10,1)>=DATE(YEAR('Model inputs'!U13),MONTH('Model inputs'!U13),1)))="",FALSE,IF(ISERROR(DATE(2026,10,1)>=DATE(YEAR('Model inputs'!U13),MONTH('Model inputs'!U13),1)),DATE(2026,10,1)>=DATE(YEAR('Model inputs'!U13),MONTH('Model inputs'!U13),1),IF(DATE(YEAR('Model inputs'!U13),MONTH('Model inputs'!U13),1)="","",DATE(2026,10,1)>=DATE(YEAR('Model inputs'!U13),MONTH('Model inputs'!U13),1)))),IF('Model inputs'!U26="","",'Model inputs'!U26),0) -> 0 | D18: =IF(IF(IF(ISERROR(DATE(2026,11,1)>=DATE(YEAR('Model inputs'!U13),MONTH('Model inputs'!U13),1)),DATE(2026,11,1)>=DATE(YEAR('Model inputs'!U13),MONTH('Model inputs'!U13),1),IF(DATE(YEAR('Model inputs'!U13),MONTH('Model inputs'!U13),1)="","",DATE(2026,11,1)>=DATE(YEAR('Model inputs'!U13),MONTH('Model inputs'!U13),1)))="",FALSE,IF(ISERROR(DATE(2026,11,1)>=DATE(YEAR('Model inputs'!U13),MONTH('Model inputs'!U13),1)),DATE(2026,11,1)>=DATE(YEAR('Model inputs'!U13),MONTH('Model inputs'!U13),1),IF(DATE(YEAR('Model inputs'!U13),MONTH('Model inputs'!U13),1)="","",DATE(2026,11,1)>=DATE(YEAR('Model inputs'!U13),MONTH('Model inputs'!U13),1)))),IF('Model inputs'!U26="","",'Model inputs'!U26),0) -> 0 | E18: =IF(IF(IF(ISERROR(DATE(2026,12,1)>=DATE(YEAR('Model inputs'!U13),MONTH('Model inputs'!U13),1)),DATE(2026,12,1)>=DATE(YEAR('Model inputs'!U13),MONTH('Model inputs'!U13),1),IF(DATE(YEAR('Model inputs'!U13),MONTH('Model inputs'!U13),1)="","",DATE(2026,12,1)>=DATE(YEAR('Model inputs'!U13),MONTH('Model inputs'!U13),1)))="",FALSE,IF(ISERROR(DATE(2026,12,1)>=DATE(YEAR('Model inputs'!U13),MONTH('Model inputs'!U13),1)),DATE(2026,12,1)>=DATE(YEAR('Model inputs'!U13),MONTH('Model inputs'!U13),1),IF(DATE(YEAR('Model inputs'!U13),MONTH('Model inputs'!U13),1)="","",DATE(2026,12,1)>=DATE(YEAR('Model inputs'!U13),MONTH('Model inputs'!U13),1)))),IF('Model inputs'!U26="","",'Model inputs'!U26),0) -> 0 | F18: =IF(IF(IF(ISERROR(DATE(2027,1,1)>=DATE(YEAR('Model inputs'!U13),MONTH('Model inputs'!U13),1)),DATE(2027,1,1)>=DATE(YEAR('Model inputs'!U13),MONTH('Model inputs'!U13),1),IF(DATE(YEAR('Model inputs'!U13),MONTH('Model inputs'!U13),1)="","",DATE(2027,1,1)>=DATE(YEAR('Model inputs'!U13),MONTH('Model inputs'!U13),1)))="",FALSE,IF(ISERROR(DATE(2027,1,1)>=DATE(YEAR('Model inputs'!U13),MONTH('Model inputs'!U13),1)),DATE(2027,1,1)>=DATE(YEAR('Model inputs'!U13),MONTH('Model inputs'!U13),1),IF(DATE(YEAR('Model inputs'!U13),MONTH('Model inputs'!U13),1)="","",DATE(2027,1,1)>=DATE(YEAR('Model inputs'!U13),MONTH('Model inputs'!U13),1)))),IF('Model inputs'!U26="","",'Model inputs'!U26),0) -> 0 | G18: =IF(IF(IF(ISERROR(DATE(2027,2,1)>=DATE(YEAR('Model inputs'!U13),MONTH('Model inputs'!U13),1)),DATE(2027,2,1)>=DATE(YEAR('Model inputs'!U13),MONTH('Model inputs'!U13),1),IF(DATE(YEAR('Model inputs'!U13),MONTH('Model inputs'!U13),1)="","",DATE(2027,2,1)>=DATE(YEAR('Model inputs'!U13),MONTH('Model inputs'!U13),1)))="",FALSE,IF(ISERROR(DATE(2027,2,1)>=DATE(YEAR('Model inputs'!U13),MONTH('Model inputs'!U13),1)),DATE(2027,2,1)>=DATE(YEAR('Model inputs'!U13),MONTH('Model inputs'!U13),1),IF(DATE(YEAR('Model inputs'!U13),MONTH('Model inputs'!U13),1)="","",DATE(2027,2,1)>=DATE(YEAR('Model inputs'!U13),MONTH('Model inputs'!U13),1)))),IF('Model inputs'!U26="","",'Model inputs'!U26),0) -> 0 | H18: =IF(IF(IF(ISERROR(DATE(2027,3,1)>=DATE(YEAR('Model inputs'!U13),MONTH('Model inputs'!U13),1)),DATE(2027,3,1)>=DATE(YEAR('Model inputs'!U13),MONTH('Model inputs'!U13),1),IF(DATE(YEAR('Model inputs'!U13),MONTH('Model inputs'!U13),1)="","",DATE(2027,3,1)>=DATE(YEAR('Model inputs'!U13),MONTH('Model inputs'!U13),1)))="",FALSE,IF(ISERROR(DATE(2027,3,1)>=DATE(YEAR('Model inputs'!U13),MONTH('Model inputs'!U13),1)),DATE(2027,3,1)>=DATE(YEAR('Model inputs'!U13),MONTH('Model inputs'!U13),1),IF(DATE(YEAR('Model inputs'!U13),MONTH('Model inputs'!U13),1)="","",DATE(2027,3,1)>=DATE(YEAR('Model inputs'!U13),MONTH('Model inputs'!U13),1)))),IF('Model inputs'!U26="","",'Model inputs'!U26),0) -> 0 | I18: =IF(IF(IF(ISERROR(DATE(2027,4,1)>=DATE(YEAR('Model inputs'!U13),MONTH('Model inputs'!U13),1)),DATE(2027,4,1)>=DATE(YEAR('Model inputs'!U13),MONTH('Model inputs'!U13),1),IF(DATE(YEAR('Model inputs'!U13),MONTH('Model inputs'!U13),1)="","",DATE(2027,4,1)>=DATE(YEAR('Model inputs'!U13),MONTH('Model inputs'!U13),1)))="",FALSE,IF(ISERROR(DATE(2027,4,1)>=DATE(YEAR('Model inputs'!U13),MONTH('Model inputs'!U13),1)),DATE(2027,4,1)>=DATE(YEAR('Model inputs'!U13),MONTH('Model inputs'!U13),1),IF(DATE(YEAR('Model inputs'!U13),MONTH('Model inputs'!U13),1)="","",DATE(2027,4,1)>=DATE(YEAR('Model inputs'!U13),MONTH('Model inputs'!U13),1)))),IF('Model inputs'!U26="","",'Model inputs'!U26),0) -> 2000 | J18: =IF(IF(IF(ISERROR(DATE(2027,5,1)>=DATE(YEAR('Model inputs'!U13),MONTH('Model inputs'!U13),1)),DATE(2027,5,1)>=DATE(YEAR('Model inputs'!U13),MONTH('Model inputs'!U13),1),IF(DATE(YEAR('Model inputs'!U13),MONTH('Model inputs'!U13),1)="","",DATE(2027,5,1)>=DATE(YEAR('Model inputs'!U13),MONTH('Model inputs'!U13),1)))="",FALSE,IF(ISERROR(DATE(2027,5,1)>=DATE(YEAR('Model inputs'!U13),MONTH('Model inputs'!U13),1)),DATE(2027,5,1)>=DATE(YEAR('Model inputs'!U13),MONTH('Model inputs'!U13),1),IF(DATE(YEAR('Model inputs'!U13),MONTH('Model inputs'!U13),1)="","",DATE(2027,5,1)>=DATE(YEAR('Model inputs'!U13),MONTH('Model inputs'!U13),1)))),IF('Model inputs'!U26="","",'Model inputs'!U26),0) -> 2000 | K18: =IF(IF(IF(ISERROR(DATE(2027,6,1)>=DATE(YEAR('Model inputs'!U13),MONTH('Model inputs'!U13),1)),DATE(2027,6,1)>=DATE(YEAR('Model inputs'!U13),MONTH('Model inputs'!U13),1),IF(DATE(YEAR('Model inputs'!U13),MONTH('Model inputs'!U13),1)="","",DATE(2027,6,1)>=DATE(YEAR('Model inputs'!U13),MONTH('Model inputs'!U13),1)))="",FALSE,IF(ISERROR(DATE(2027,6,1)>=DATE(YEAR('Model inputs'!U13),MONTH('Model inputs'!U13),1)),DATE(2027,6,1)>=DATE(YEAR('Model inputs'!U13),MONTH('Model inputs'!U13),1),IF(DATE(YEAR('Model inputs'!U13),MONTH('Model inputs'!U13),1)="","",DATE(2027,6,1)>=DATE(YEAR('Model inputs'!U13),MONTH('Model inputs'!U13),1)))),IF('Model inputs'!U26="","",'Model inputs'!U26),0) -> 2000 | L18: =IF(IF(IF(ISERROR(DATE(2027,7,1)>=DATE(YEAR('Model inputs'!U13),MONTH('Model inputs'!U13),1)),DATE(2027,7,1)>=DATE(YEAR('Model inputs'!U13),MONTH('Model inputs'!U13),1),IF(DATE(YEAR('Model inputs'!U13),MONTH('Model inputs'!U13),1)="","",DATE(2027,7,1)>=DATE(YEAR('Model inputs'!U13),MONTH('Model inputs'!U13),1)))="",FALSE,IF(ISERROR(DATE(2027,7,1)>=DATE(YEAR('Model inputs'!U13),MONTH('Model inputs'!U13),1)),DATE(2027,7,1)>=DATE(YEAR('Model inputs'!U13),MONTH('Model inputs'!U13),1),IF(DATE(YEAR('Model inputs'!U13),MONTH('Model inputs'!U13),1)="","",DATE(2027,7,1)>=DATE(YEAR('Model inputs'!U13),MONTH('Model inputs'!U13),1)))),IF('Model inputs'!U26="","",'Model inputs'!U26),0) -> 2000 | M18: =IF(IF(IF(ISERROR(DATE(2027,8,1)>=DATE(YEAR('Model inputs'!U13),MONTH('Model inputs'!U13),1)),DATE(2027,8,1)>=DATE(YEAR('Model inputs'!U13),MONTH('Model inputs'!U13),1),IF(DATE(YEAR('Model inputs'!U13),MONTH('Model inputs'!U13),1)="","",DATE(2027,8,1)>=DATE(YEAR('Model inputs'!U13),MONTH('Model inputs'!U13),1)))="",FALSE,IF(ISERROR(DATE(2027,8,1)>=DATE(YEAR('Model inputs'!U13),MONTH('Model inputs'!U13),1)),DATE(2027,8,1)>=DATE(YEAR('Model inputs'!U13),MONTH('Model inputs'!U13),1),IF(DATE(YEAR('Model inputs'!U13),MONTH('Model inputs'!U13),1)="","",DATE(2027,8,1)>=DATE(YEAR('Model inputs'!U13),MONTH('Model inputs'!U13),1)))),IF('Model inputs'!U26="","",'Model inputs'!U26),0) -> 2000 | N18: =IF(IF(IF(ISERROR(DATE(2027,9,1)>=DATE(YEAR('Model inputs'!U13),MONTH('Model inputs'!U13),1)),DATE(2027,9,1)>=DATE(YEAR('Model inputs'!U13),MONTH('Model inputs'!U13),1),IF(DATE(YEAR('Model inputs'!U13),MONTH('Model inputs'!U13),1)="","",DATE(2027,9,1)>=DATE(YEAR('Model inputs'!U13),MONTH('Model inputs'!U13),1)))="",FALSE,IF(ISERROR(DATE(2027,9,1)>=DATE(YEAR('Model inputs'!U13),MONTH('Model inputs'!U13),1)),DATE(2027,9,1)>=DATE(YEAR('Model inputs'!U13),MONTH('Model inputs'!U13),1),IF(DATE(YEAR('Model inputs'!U13),MONTH('Model inputs'!U13),1)="","",DATE(2027,9,1)>=DATE(YEAR('Model inputs'!U13),MONTH('Model inputs'!U13),1)))),IF('Model inputs'!U26="","",'Model inputs'!U26),0) -> 2000 | O18: =IF(IF(IF(ISERROR(DATE(2027,10,1)>=DATE(YEAR('Model inputs'!U13),MONTH('Model inputs'!U13),1)),DATE(2027,10,1)>=DATE(YEAR('Model inputs'!U13),MONTH('Model inputs'!U13),1),IF(DATE(YEAR('Model inputs'!U13),MONTH('Model inputs'!U13),1)="","",DATE(2027,10,1)>=DATE(YEAR('Model inputs'!U13),MONTH('Model inputs'!U13),1)))="",FALSE,IF(ISERROR(DATE(2027,10,1)>=DATE(YEAR('Model inputs'!U13),MONTH('Model inputs'!U13),1)),DATE(2027,10,1)>=DATE(YEAR('Model inputs'!U13),MONTH('Model inputs'!U13),1),IF(DATE(YEAR('Model inputs'!U13),MONTH('Model inputs'!U13),1)="","",DATE(2027,10,1)>=DATE(YEAR('Model inputs'!U13),MONTH('Model inputs'!U13),1)))),IF('Model inputs'!U26="","",'Model inputs'!U26),0) -> 2000 | P18: =IF(IF(IF(ISERROR(DATE(2027,11,1)>=DATE(YEAR('Model inputs'!U13),MONTH('Model inputs'!U13),1)),DATE(2027,11,1)>=DATE(YEAR('Model inputs'!U13),MONTH('Model inputs'!U13),1),IF(DATE(YEAR('Model inputs'!U13),MONTH('Model inputs'!U13),1)="","",DATE(2027,11,1)>=DATE(YEAR('Model inputs'!U13),MONTH('Model inputs'!U13),1)))="",FALSE,IF(ISERROR(DATE(2027,11,1)>=DATE(YEAR('Model inputs'!U13),MONTH('Model inputs'!U13),1)),DATE(2027,11,1)>=DATE(YEAR('Model inputs'!U13),MONTH('Model inputs'!U13),1),IF(DATE(YEAR('Model inputs'!U13),MONTH('Model inputs'!U13),1)="","",DATE(2027,11,1)>=DATE(YEAR('Model inputs'!U13),MONTH('Model inputs'!U13),1)))),IF('Model inputs'!U26="","",'Model inputs'!U26),0) -> 2000 | Q18: =IF(IF(IF(ISERROR(DATE(2027,12,1)>=DATE(YEAR('Model inputs'!U13),MONTH('Model inputs'!U13),1)),DATE(2027,12,1)>=DATE(YEAR('Model inputs'!U13),MONTH('Model inputs'!U13),1),IF(DATE(YEAR('Model inputs'!U13),MONTH('Model inputs'!U13),1)="","",DATE(2027,12,1)>=DATE(YEAR('Model inputs'!U13),MONTH('Model inputs'!U13),1)))="",FALSE,IF(ISERROR(DATE(2027,12,1)>=DATE(YEAR('Model inputs'!U13),MONTH('Model inputs'!U13),1)),DATE(2027,12,1)>=DATE(YEAR('Model inputs'!U13),MONTH('Model inputs'!U13),1),IF(DATE(YEAR('Model inputs'!U13),MONTH('Model inputs'!U13),1)="","",DATE(2027,12,1)>=DATE(YEAR('Model inputs'!U13),MONTH('Model inputs'!U13),1)))),IF('Model inputs'!U26="","",'Model inputs'!U26),0) -> 2000 | R18: =IF(IF(IF(ISERROR(DATE(2028,1,1)>=DATE(YEAR('Model inputs'!U13),MONTH('Model inputs'!U13),1)),DATE(2028,1,1)>=DATE(YEAR('Model inputs'!U13),MONTH('Model inputs'!U13),1),IF(DATE(YEAR('Model inputs'!U13),MONTH('Model inputs'!U13),1)="","",DATE(2028,1,1)>=DATE(YEAR('Model inputs'!U13),MONTH('Model inputs'!U13),1)))="",FALSE,IF(ISERROR(DATE(2028,1,1)>=DATE(YEAR('Model inputs'!U13),MONTH('Model inputs'!U13),1)),DATE(2028,1,1)>=DATE(YEAR('Model inputs'!U13),MONTH('Model inputs'!U13),1),IF(DATE(YEAR('Model inputs'!U13),MONTH('Model inputs'!U13),1)="","",DATE(2028,1,1)>=DATE(YEAR('Model inputs'!U13),MONTH('Model inputs'!U13),1)))),IF('Model inputs'!U26="","",'Model inputs'!U26),0) -> 2000 | S18: =IF(IF(IF(ISERROR(DATE(2028,2,1)>=DATE(YEAR('Model inputs'!U13),MONTH('Model inputs'!U13),1)),DATE(2028,2,1)>=DATE(YEAR('Model inputs'!U13),MONTH('Model inputs'!U13),1),IF(DATE(YEAR('Model inputs'!U13),MONTH('Model inputs'!U13),1)="","",DATE(2028,2,1)>=DATE(YEAR('Model inputs'!U13),MONTH('Model inputs'!U13),1)))="",FALSE,IF(ISERROR(DATE(2028,2,1)>=DATE(YEAR('Model inputs'!U13),MONTH('Model inputs'!U13),1)),DATE(2028,2,1)>=DATE(YEAR('Model inputs'!U13),MONTH('Model inputs'!U13),1),IF(DATE(YEAR('Model inputs'!U13),MONTH('Model inputs'!U13),1)="","",DATE(2028,2,1)>=DATE(YEAR('Model inputs'!U13),MONTH('Model inputs'!U13),1)))),IF('Model inputs'!U26="","",'Model inputs'!U26),0) -> 2000 | T18: =IF(IF(IF(ISERROR(DATE(2028,3,1)>=DATE(YEAR('Model inputs'!U13),MONTH('Model inputs'!U13),1)),DATE(2028,3,1)>=DATE(YEAR('Model inputs'!U13),MONTH('Model inputs'!U13),1),IF(DATE(YEAR('Model inputs'!U13),MONTH('Model inputs'!U13),1)="","",DATE(2028,3,1)>=DATE(YEAR('Model inputs'!U13),MONTH('Model inputs'!U13),1)))="",FALSE,IF(ISERROR(DATE(2028,3,1)>=DATE(YEAR('Model inputs'!U13),MONTH('Model inputs'!U13),1)),DATE(2028,3,1)>=DATE(YEAR('Model inputs'!U13),MONTH('Model inputs'!U13),1),IF(DATE(YEAR('Model inputs'!U13),MONTH('Model inputs'!U13),1)="","",DATE(2028,3,1)>=DATE(YEAR('Model inputs'!U13),MONTH('Model inputs'!U13),1)))),IF('Model inputs'!U26="","",'Model inputs'!U26),0) -> 2000
A19: Founder payroll · Growth | B19: =SUM('Model inputs'!B53,'Model inputs'!B54,'Model inputs'!B55,'Model inputs'!B56) -> 0 | C19: =SUM('Model inputs'!C53,'Model inputs'!C54,'Model inputs'!C55,'Model inputs'!C56) -> 0 | D19: =SUM('Model inputs'!D53,'Model inputs'!D54,'Model inputs'!D55,'Model inputs'!D56) -> 0 | E19: =SUM('Model inputs'!E53,'Model inputs'!E54,'Model inputs'!E55,'Model inputs'!E56) -> 0 | F19: =SUM('Model inputs'!F53,'Model inputs'!F54,'Model inputs'!F55,'Model inputs'!F56) -> 0 | G19: =SUM('Model inputs'!G53,'Model inputs'!G54,'Model inputs'!G55,'Model inputs'!G56) -> 0 | H19: =SUM('Model inputs'!H53,'Model inputs'!H54,'Model inputs'!H55,'Model inputs'!H56) -> 0 | I19: =SUM('Model inputs'!I53,'Model inputs'!I54,'Model inputs'!I55,'Model inputs'!I56) -> 8000 | ... T19: =SUM('Model inputs'!T53,'Model inputs'!T54,'Model inputs'!T55,'Model inputs'!T56) -> 8000
A20: Gross profit · Base | B20: 0 | C20: ='Model inputs'!C27-'Model inputs'!C42 -> 750 | D20: ='Model inputs'!D27-'Model inputs'!D42 -> 750 | E20: ='Model inputs'!E27-'Model inputs'!E42 -> 750 | F20: ='Model inputs'!F27-'Model inputs'!F42 -> 750 | G20: ='Model inputs'!G27-'Model inputs'!G42 -> 750 | H20: ='Model inputs'!H27-'Model inputs'!H42 -> 750 | I20: ='Model inputs'!I27-'Model inputs'!I42 -> 750 | J20: ='Model inputs'!J27-'Model inputs'!J42 -> 750 | ... T20: ='Model inputs'!T27-'Model inputs'!T42 -> 750
A21: Gross profit · Growth | B21: 0 | C21: ='Model inputs'!C58-'Model inputs'!C46 -> 750 | D21: ='Model inputs'!D58-'Model inputs'!D46 -> 845 | E21: ='Model inputs'!E58-'Model inputs'!E46 -> 949.5 | F21: ='Model inputs'!F58-'Model inputs'!F46 -> 1064.45 | G21: ='Model inputs'!G58-'Model inputs'!G46 -> 1190.895 | H21: ='Model inputs'!H58-'Model inputs'!H46 -> 1329.9845 | I21: ='Model inputs'!I58-'Model inputs'!I46 -> 1482.983 | J21: ='Model inputs'!J58-'Model inputs'!J46 -> 1651.2812 | ... T21: ='Model inputs'!T58-'Model inputs'!T46 -> 4601.7468
A22: Monthly founder pay | U22: 0
A23: Monthly founder pay > Placeholder founder 1 | U23: =2000 -> 2000
A24: Monthly founder pay > Placeholder founder 2 | U24: =2000 -> 2000
A25: Monthly founder pay > Placeholder founder 3 | U25: =2000 -> 2000
A26: Monthly founder pay > Placeholder founder 4 | U26: =2000 -> 2000
A27: Monthly revenue | B27: 0 | C27: ='Model inputs'!C32*'Model inputs'!U35 -> 2450 | D27: ='Model inputs'!D32*'Model inputs'!U35 -> 2450 | E27: ='Model inputs'!E32*'Model inputs'!U35 -> 2450 | F27: ='Model inputs'!F32*'Model inputs'!U35 -> 2450 | G27: ='Model inputs'!G32*'Model inputs'!U35 -> 2450 | H27: ='Model inputs'!H32*'Model inputs'!U35 -> 2450 | I27: ='Model inputs'!I32*'Model inputs'!U35 -> 2450 | J27: ='Model inputs'!J32*'Model inputs'!U35 -> 2450 | K27: ='Model inputs'!K32*'Model inputs'!U35 -> 2450 | L27: ='Model inputs'!L32*'Model inputs'!U35 -> 2450 | M27: ='Model inputs'!M32*'Model inputs'!U35 -> 2450 | N27: ='Model inputs'!N32*'Model inputs'!U35 -> 2450 | O27: ='Model inputs'!O32*'Model inputs'!U35 -> 2450 | P27: ='Model inputs'!P32*'Model inputs'!U35 -> 2450 | Q27: ='Model inputs'!Q32*'Model inputs'!U35 -> 2450 | R27: ='Model inputs'!R32*'Model inputs'!U35 -> 2450 | S27: ='Model inputs'!S32*'Model inputs'!U35 -> 2450 | T27: ='Model inputs'!T32*'Model inputs'!U35 -> 2450
A28: Net cash flow · Base | B28: 0 | C28: ='Model inputs'!C20-'Model inputs'!C14 -> 750 | D28: ='Model inputs'!D20-'Model inputs'!D14 -> 750 | E28: ='Model inputs'!E20-'Model inputs'!E14 -> 750 | F28: ='Model inputs'!F20-'Model inputs'!F14 -> 750 | G28: ='Model inputs'!G20-'Model inputs'!G14 -> 750 | H28: ='Model inputs'!H20-'Model inputs'!H14 -> 750 | I28: ='Model inputs'!I20-'Model inputs'!I14 -> -7250 | J28: ='Model inputs'!J20-'Model inputs'!J14 -> -7250 | ... T28: ='Model inputs'!T20-'Model inputs'!T14 -> -7250
A29: Net cash flow · Growth | B29: 0 | C29: ='Model inputs'!C21-'Model inputs'!C19 -> 750 | D29: ='Model inputs'!D21-'Model inputs'!D19 -> 845 | E29: ='Model inputs'!E21-'Model inputs'!E19 -> 949.5 | F29: ='Model inputs'!F21-'Model inputs'!F19 -> 1064.45 | G29: ='Model inputs'!G21-'Model inputs'!G19 -> 1190.895 | H29: ='Model inputs'!H21-'Model inputs'!H19 -> 1329.9845 | I29: ='Model inputs'!I21-'Model inputs'!I19 -> -6517.017 | J29: ='Model inputs'!J21-'Model inputs'!J19 -> -6348.7188 | ... T29: ='Model inputs'!T21-'Model inputs'!T19 -> -3398.2532
A30: Net monthly customer growth · Base | U30: =0 -> 0
A31: Net monthly customer growth · Growth | U31: =0.1 -> 0.1
A32: Paying teams · Base | B32: 0 | C32: =IF('Model inputs'!U40="","",'Model inputs'!U40) -> 50 | D32: ='Model inputs'!C32*(1+'Model inputs'!U30) -> 50 | E32: ='Model inputs'!D32*(1+'Model inputs'!U30) -> 50 | F32: ='Model inputs'!E32*(1+'Model inputs'!U30) -> 50 | G32: ='Model inputs'!F32*(1+'Model inputs'!U30) -> 50 | H32: ='Model inputs'!G32*(1+'Model inputs'!U30) -> 50 | I32: ='Model inputs'!H32*(1+'Model inputs'!U30) -> 50 | J32: ='Model inputs'!I32*(1+'Model inputs'!U30) -> 50 | K32: ='Model inputs'!J32*(1+'Model inputs'!U30) -> 50 | L32: ='Model inputs'!K32*(1+'Model inputs'!U30) -> 50 | M32: ='Model inputs'!L32*(1+'Model inputs'!U30) -> 50 | N32: ='Model inputs'!M32*(1+'Model inputs'!U30) -> 50 | O32: ='Model inputs'!N32*(1+'Model inputs'!U30) -> 50 | P32: ='Model inputs'!O32*(1+'Model inputs'!U30) -> 50 | Q32: ='Model inputs'!P32*(1+'Model inputs'!U30) -> 50 | R32: ='Model inputs'!Q32*(1+'Model inputs'!U30) -> 50 | S32: ='Model inputs'!R32*(1+'Model inputs'!U30) -> 50 | T32: ='Model inputs'!S32*(1+'Model inputs'!U30) -> 50
A33: Paying teams · Growth | B33: 0 | C33: =IF('Model inputs'!U41="","",'Model inputs'!U41) -> 50 | D33: ='Model inputs'!C33*(1+'Model inputs'!U31) -> 55 | E33: ='Model inputs'!D33*(1+'Model inputs'!U31) -> 60.5 | F33: ='Model inputs'!E33*(1+'Model inputs'!U31) -> 66.55 | G33: ='Model inputs'!F33*(1+'Model inputs'!U31) -> 73.205 | H33: ='Model inputs'!G33*(1+'Model inputs'!U31) -> 80.5255 | I33: ='Model inputs'!H33*(1+'Model inputs'!U31) -> 88.57805 | J33: ='Model inputs'!I33*(1+'Model inputs'!U31) -> 97.435855 | K33: ='Model inputs'!J33*(1+'Model inputs'!U31) -> 107.17944 | L33: ='Model inputs'!K33*(1+'Model inputs'!U31) -> 117.89738 | M33: ='Model inputs'!L33*(1+'Model inputs'!U31) -> 129.68712 | N33: ='Model inputs'!M33*(1+'Model inputs'!U31) -> 142.65584 | O33: ='Model inputs'!N33*(1+'Model inputs'!U31) -> 156.92142 | P33: ='Model inputs'!O33*(1+'Model inputs'!U31) -> 172.61356 | Q33: ='Model inputs'!P33*(1+'Model inputs'!U31) -> 189.87492 | R33: ='Model inputs'!Q33*(1+'Model inputs'!U31) -> 208.86241 | S33: ='Model inputs'!R33*(1+'Model inputs'!U31) -> 229.74865 | T33: ='Model inputs'!S33*(1+'Model inputs'!U31) -> 252.72351
A34: Repair cost per round · 18-month forecast | U34: ='Model inputs'!U47+'Model inputs'!U63*((1-'Model inputs'!U62)*'Model inputs'!U57+'Model inputs'!U62*'Model inputs'!U61) -> 1.5
A35: Revenue per team · Base | U35: ='Model inputs'!U59+'Model inputs'!U50*'Model inputs'!U48 -> 49
A36: Revenue per team · Growth | U36: ='Model inputs'!U60+'Model inputs'!U51*'Model inputs'!U49 -> 49
A37: Rounds per team · 18-month forecast | U37: ='Model inputs'!U64+'Model inputs'!U50 -> 20
A38: Starting cash · Base | U38: =10000 -> 10000
A39: Starting cash · Growth | U39: ='Model inputs'!U38 -> 10000
A40: Starting teams · Base | U40: =50 -> 50
A41: Starting teams · Growth | U41: ='Model inputs'!U40 -> 50
A42: Cost of revenue | B42: 0 | C42: ='Model inputs'!C44+'Model inputs'!C43 -> 1700 | D42: ='Model inputs'!D44+'Model inputs'!D43 -> 1700 | E42: ='Model inputs'!E44+'Model inputs'!E43 -> 1700 | F42: ='Model inputs'!F44+'Model inputs'!F43 -> 1700 | G42: ='Model inputs'!G44+'Model inputs'!G43 -> 1700 | H42: ='Model inputs'!H44+'Model inputs'!H43 -> 1700 | I42: ='Model inputs'!I44+'Model inputs'!I43 -> 1700 | J42: ='Model inputs'!J44+'Model inputs'!J43 -> 1700 | ... T42: ='Model inputs'!T44+'Model inputs'!T43 -> 1700
A43: Infrastructure expense | B43: 0 | C43: =IF('Model inputs'!U8="","",'Model inputs'!U8) -> 200 | D43: =IF('Model inputs'!U8="","",'Model inputs'!U8) -> 200 | E43: =IF('Model inputs'!U8="","",'Model inputs'!U8) -> 200 | F43: =IF('Model inputs'!U8="","",'Model inputs'!U8) -> 200 | G43: =IF('Model inputs'!U8="","",'Model inputs'!U8) -> 200 | H43: =IF('Model inputs'!U8="","",'Model inputs'!U8) -> 200 | I43: =IF('Model inputs'!U8="","",'Model inputs'!U8) -> 200 | J43: =IF('Model inputs'!U8="","",'Model inputs'!U8) -> 200 | K43: =IF('Model inputs'!U8="","",'Model inputs'!U8) -> 200 | L43: =IF('Model inputs'!U8="","",'Model inputs'!U8) -> 200 | M43: =IF('Model inputs'!U8="","",'Model inputs'!U8) -> 200 | N43: =IF('Model inputs'!U8="","",'Model inputs'!U8) -> 200 | O43: =IF('Model inputs'!U8="","",'Model inputs'!U8) -> 200 | P43: =IF('Model inputs'!U8="","",'Model inputs'!U8) -> 200 | Q43: =IF('Model inputs'!U8="","",'Model inputs'!U8) -> 200 | R43: =IF('Model inputs'!U8="","",'Model inputs'!U8) -> 200 | S43: =IF('Model inputs'!U8="","",'Model inputs'!U8) -> 200 | T43: =IF('Model inputs'!U8="","",'Model inputs'!U8) -> 200
A44: Monthly model fees | B44: 0 | C44: ='Model inputs'!C45*'Model inputs'!U34 -> 1500 | D44: ='Model inputs'!D45*'Model inputs'!U34 -> 1500 | E44: ='Model inputs'!E45*'Model inputs'!U34 -> 1500 | F44: ='Model inputs'!F45*'Model inputs'!U34 -> 1500 | G44: ='Model inputs'!G45*'Model inputs'!U34 -> 1500 | H44: ='Model inputs'!H45*'Model inputs'!U34 -> 1500 | I44: ='Model inputs'!I45*'Model inputs'!U34 -> 1500 | J44: ='Model inputs'!J45*'Model inputs'!U34 -> 1500 | K44: ='Model inputs'!K45*'Model inputs'!U34 -> 1500 | L44: ='Model inputs'!L45*'Model inputs'!U34 -> 1500 | M44: ='Model inputs'!M45*'Model inputs'!U34 -> 1500 | N44: ='Model inputs'!N45*'Model inputs'!U34 -> 1500 | O44: ='Model inputs'!O45*'Model inputs'!U34 -> 1500 | P44: ='Model inputs'!P45*'Model inputs'!U34 -> 1500 | Q44: ='Model inputs'!Q45*'Model inputs'!U34 -> 1500 | R44: ='Model inputs'!R45*'Model inputs'!U34 -> 1500 | S44: ='Model inputs'!S45*'Model inputs'!U34 -> 1500 | T44: ='Model inputs'!T45*'Model inputs'!U34 -> 1500
A45: Repair rounds delivered | B45: 0 | C45: ='Model inputs'!C32*'Model inputs'!U37 -> 1000 | D45: ='Model inputs'!D32*'Model inputs'!U37 -> 1000 | E45: ='Model inputs'!E32*'Model inputs'!U37 -> 1000 | F45: ='Model inputs'!F32*'Model inputs'!U37 -> 1000 | G45: ='Model inputs'!G32*'Model inputs'!U37 -> 1000 | H45: ='Model inputs'!H32*'Model inputs'!U37 -> 1000 | I45: ='Model inputs'!I32*'Model inputs'!U37 -> 1000 | J45: ='Model inputs'!J32*'Model inputs'!U37 -> 1000 | K45: ='Model inputs'!K32*'Model inputs'!U37 -> 1000 | L45: ='Model inputs'!L32*'Model inputs'!U37 -> 1000 | M45: ='Model inputs'!M32*'Model inputs'!U37 -> 1000 | N45: ='Model inputs'!N32*'Model inputs'!U37 -> 1000 | O45: ='Model inputs'!O32*'Model inputs'!U37 -> 1000 | P45: ='Model inputs'!P32*'Model inputs'!U37 -> 1000 | Q45: ='Model inputs'!Q32*'Model inputs'!U37 -> 1000 | R45: ='Model inputs'!R32*'Model inputs'!U37 -> 1000 | S45: ='Model inputs'!S32*'Model inputs'!U37 -> 1000 | T45: ='Model inputs'!T32*'Model inputs'!U37 -> 1000
A46: Cost of revenue | B46: 0 | C46: ='Model inputs'!C79+'Model inputs'!C73 -> 1700 | D46: ='Model inputs'!D79+'Model inputs'!D73 -> 1850 | E46: ='Model inputs'!E79+'Model inputs'!E73 -> 2015 | F46: ='Model inputs'!F79+'Model inputs'!F73 -> 2196.5 | G46: ='Model inputs'!G79+'Model inputs'!G73 -> 2396.15 | H46: ='Model inputs'!H79+'Model inputs'!H73 -> 2615.765 | I46: ='Model inputs'!I79+'Model inputs'!I73 -> 2857.3415 | J46: ='Model inputs'!J79+'Model inputs'!J73 -> 3123.0757 | ... T46: ='Model inputs'!T79+'Model inputs'!T73 -> 7781.7054
A47: Diagnosis cost per round · Repair cost per round · 18-month forecast | U47: ='Model inputs'!U65-'Model inputs'!U63*'Model inputs'!U57 -> 0.38
A48: Extra round price · Revenue per team · Base · Base | U48: =2 -> 2
A49: Extra round price · Revenue per team · Growth · Growth | U49: ='Model inputs'!U48 -> 2
A50: Extra rounds per team · Revenue per team · Base · Base | U50: =0 -> 0
A51: Extra rounds per team · Revenue per team · Growth · Growth | U51: ='Model inputs'!U50 -> 0
A52: Founder payroll | B52: =IF('Model inputs'!B19="","",'Model inputs'!B19) -> 0 | C52: =IF('Model inputs'!C19="","",'Model inputs'!C19) -> 0 | D52: =IF('Model inputs'!D19="","",'Model inputs'!D19) -> 0 | E52: =IF('Model inputs'!E19="","",'Model inputs'!E19) -> 0 | F52: =IF('Model inputs'!F19="","",'Model inputs'!F19) -> 0 | G52: =IF('Model inputs'!G19="","",'Model inputs'!G19) -> 0 | H52: =IF('Model inputs'!H19="","",'Model inputs'!H19) -> 0 | I52: =IF('Model inputs'!I19="","",'Model inputs'!I19) -> 8000 | ... T52: =IF('Model inputs'!T19="","",'Model inputs'!T19) -> 8000
A53: Founder payroll > Placeholder founder 1 | B53: ='Model inputs'!B15 -> 0 | C53: =IF(IF(IF(ISERROR(DATE(2026,10,1)>=DATE(YEAR('Model inputs'!U67),MONTH('Model inputs'!U67),1)),DATE(2026,10,1)>=DATE(YEAR('Model inputs'!U67),MONTH('Model inputs'!U67),1),IF(DATE(YEAR('Model inputs'!U67),MONTH('Model inputs'!U67),1)="","",DATE(2026,10,1)>=DATE(YEAR('Model inputs'!U67),MONTH('Model inputs'!U67),1)))="",FALSE,IF(ISERROR(DATE(2026,10,1)>=DATE(YEAR('Model inputs'!U67),MONTH('Model inputs'!U67),1)),DATE(2026,10,1)>=DATE(YEAR('Model inputs'!U67),MONTH('Model inputs'!U67),1),IF(DATE(YEAR('Model inputs'!U67),MONTH('Model inputs'!U67),1)="","",DATE(2026,10,1)>=DATE(YEAR('Model inputs'!U67),MONTH('Model inputs'!U67),1)))),IF('Model inputs'!U75="","",'Model inputs'!U75),0) -> 0 | D53: =IF(IF(IF(ISERROR(DATE(2026,11,1)>=DATE(YEAR('Model inputs'!U67),MONTH('Model inputs'!U67),1)),DATE(2026,11,1)>=DATE(YEAR('Model inputs'!U67),MONTH('Model inputs'!U67),1),IF(DATE(YEAR('Model inputs'!U67),MONTH('Model inputs'!U67),1)="","",DATE(2026,11,1)>=DATE(YEAR('Model inputs'!U67),MONTH('Model inputs'!U67),1)))="",FALSE,IF(ISERROR(DATE(2026,11,1)>=DATE(YEAR('Model inputs'!U67),MONTH('Model inputs'!U67),1)),DATE(2026,11,1)>=DATE(YEAR('Model inputs'!U67),MONTH('Model inputs'!U67),1),IF(DATE(YEAR('Model inputs'!U67),MONTH('Model inputs'!U67),1)="","",DATE(2026,11,1)>=DATE(YEAR('Model inputs'!U67),MONTH('Model inputs'!U67),1)))),IF('Model inputs'!U75="","",'Model inputs'!U75),0) -> 0 | E53: =IF(IF(IF(ISERROR(DATE(2026,12,1)>=DATE(YEAR('Model inputs'!U67),MONTH('Model inputs'!U67),1)),DATE(2026,12,1)>=DATE(YEAR('Model inputs'!U67),MONTH('Model inputs'!U67),1),IF(DATE(YEAR('Model inputs'!U67),MONTH('Model inputs'!U67),1)="","",DATE(2026,12,1)>=DATE(YEAR('Model inputs'!U67),MONTH('Model inputs'!U67),1)))="",FALSE,IF(ISERROR(DATE(2026,12,1)>=DATE(YEAR('Model inputs'!U67),MONTH('Model inputs'!U67),1)),DATE(2026,12,1)>=DATE(YEAR('Model inputs'!U67),MONTH('Model inputs'!U67),1),IF(DATE(YEAR('Model inputs'!U67),MONTH('Model inputs'!U67),1)="","",DATE(2026,12,1)>=DATE(YEAR('Model inputs'!U67),MONTH('Model inputs'!U67),1)))),IF('Model inputs'!U75="","",'Model inputs'!U75),0) -> 0 | F53: =IF(IF(IF(ISERROR(DATE(2027,1,1)>=DATE(YEAR('Model inputs'!U67),MONTH('Model inputs'!U67),1)),DATE(2027,1,1)>=DATE(YEAR('Model inputs'!U67),MONTH('Model inputs'!U67),1),IF(DATE(YEAR('Model inputs'!U67),MONTH('Model inputs'!U67),1)="","",DATE(2027,1,1)>=DATE(YEAR('Model inputs'!U67),MONTH('Model inputs'!U67),1)))="",FALSE,IF(ISERROR(DATE(2027,1,1)>=DATE(YEAR('Model inputs'!U67),MONTH('Model inputs'!U67),1)),DATE(2027,1,1)>=DATE(YEAR('Model inputs'!U67),MONTH('Model inputs'!U67),1),IF(DATE(YEAR('Model inputs'!U67),MONTH('Model inputs'!U67),1)="","",DATE(2027,1,1)>=DATE(YEAR('Model inputs'!U67),MONTH('Model inputs'!U67),1)))),IF('Model inputs'!U75="","",'Model inputs'!U75),0) -> 0 | G53: =IF(IF(IF(ISERROR(DATE(2027,2,1)>=DATE(YEAR('Model inputs'!U67),MONTH('Model inputs'!U67),1)),DATE(2027,2,1)>=DATE(YEAR('Model inputs'!U67),MONTH('Model inputs'!U67),1),IF(DATE(YEAR('Model inputs'!U67),MONTH('Model inputs'!U67),1)="","",DATE(2027,2,1)>=DATE(YEAR('Model inputs'!U67),MONTH('Model inputs'!U67),1)))="",FALSE,IF(ISERROR(DATE(2027,2,1)>=DATE(YEAR('Model inputs'!U67),MONTH('Model inputs'!U67),1)),DATE(2027,2,1)>=DATE(YEAR('Model inputs'!U67),MONTH('Model inputs'!U67),1),IF(DATE(YEAR('Model inputs'!U67),MONTH('Model inputs'!U67),1)="","",DATE(2027,2,1)>=DATE(YEAR('Model inputs'!U67),MONTH('Model inputs'!U67),1)))),IF('Model inputs'!U75="","",'Model inputs'!U75),0) -> 0 | H53: =IF(IF(IF(ISERROR(DATE(2027,3,1)>=DATE(YEAR('Model inputs'!U67),MONTH('Model inputs'!U67),1)),DATE(2027,3,1)>=DATE(YEAR('Model inputs'!U67),MONTH('Model inputs'!U67),1),IF(DATE(YEAR('Model inputs'!U67),MONTH('Model inputs'!U67),1)="","",DATE(2027,3,1)>=DATE(YEAR('Model inputs'!U67),MONTH('Model inputs'!U67),1)))="",FALSE,IF(ISERROR(DATE(2027,3,1)>=DATE(YEAR('Model inputs'!U67),MONTH('Model inputs'!U67),1)),DATE(2027,3,1)>=DATE(YEAR('Model inputs'!U67),MONTH('Model inputs'!U67),1),IF(DATE(YEAR('Model inputs'!U67),MONTH('Model inputs'!U67),1)="","",DATE(2027,3,1)>=DATE(YEAR('Model inputs'!U67),MONTH('Model inputs'!U67),1)))),IF('Model inputs'!U75="","",'Model inputs'!U75),0) -> 0 | I53: =IF(IF(IF(ISERROR(DATE(2027,4,1)>=DATE(YEAR('Model inputs'!U67),MONTH('Model inputs'!U67),1)),DATE(2027,4,1)>=DATE(YEAR('Model inputs'!U67),MONTH('Model inputs'!U67),1),IF(DATE(YEAR('Model inputs'!U67),MONTH('Model inputs'!U67),1)="","",DATE(2027,4,1)>=DATE(YEAR('Model inputs'!U67),MONTH('Model inputs'!U67),1)))="",FALSE,IF(ISERROR(DATE(2027,4,1)>=DATE(YEAR('Model inputs'!U67),MONTH('Model inputs'!U67),1)),DATE(2027,4,1)>=DATE(YEAR('Model inputs'!U67),MONTH('Model inputs'!U67),1),IF(DATE(YEAR('Model inputs'!U67),MONTH('Model inputs'!U67),1)="","",DATE(2027,4,1)>=DATE(YEAR('Model inputs'!U67),MONTH('Model inputs'!U67),1)))),IF('Model inputs'!U75="","",'Model inputs'!U75),0) -> 2000 | J53: =IF(IF(IF(ISERROR(DATE(2027,5,1)>=DATE(YEAR('Model inputs'!U67),MONTH('Model inputs'!U67),1)),DATE(2027,5,1)>=DATE(YEAR('Model inputs'!U67),MONTH('Model inputs'!U67),1),IF(DATE(YEAR('Model inputs'!U67),MONTH('Model inputs'!U67),1)="","",DATE(2027,5,1)>=DATE(YEAR('Model inputs'!U67),MONTH('Model inputs'!U67),1)))="",FALSE,IF(ISERROR(DATE(2027,5,1)>=DATE(YEAR('Model inputs'!U67),MONTH('Model inputs'!U67),1)),DATE(2027,5,1)>=DATE(YEAR('Model inputs'!U67),MONTH('Model inputs'!U67),1),IF(DATE(YEAR('Model inputs'!U67),MONTH('Model inputs'!U67),1)="","",DATE(2027,5,1)>=DATE(YEAR('Model inputs'!U67),MONTH('Model inputs'!U67),1)))),IF('Model inputs'!U75="","",'Model inputs'!U75),0) -> 2000 | K53: =IF(IF(IF(ISERROR(DATE(2027,6,1)>=DATE(YEAR('Model inputs'!U67),MONTH('Model inputs'!U67),1)),DATE(2027,6,1)>=DATE(YEAR('Model inputs'!U67),MONTH('Model inputs'!U67),1),IF(DATE(YEAR('Model inputs'!U67),MONTH('Model inputs'!U67),1)="","",DATE(2027,6,1)>=DATE(YEAR('Model inputs'!U67),MONTH('Model inputs'!U67),1)))="",FALSE,IF(ISERROR(DATE(2027,6,1)>=DATE(YEAR('Model inputs'!U67),MONTH('Model inputs'!U67),1)),DATE(2027,6,1)>=DATE(YEAR('Model inputs'!U67),MONTH('Model inputs'!U67),1),IF(DATE(YEAR('Model inputs'!U67),MONTH('Model inputs'!U67),1)="","",DATE(2027,6,1)>=DATE(YEAR('Model inputs'!U67),MONTH('Model inputs'!U67),1)))),IF('Model inputs'!U75="","",'Model inputs'!U75),0) -> 2000 | L53: =IF(IF(IF(ISERROR(DATE(2027,7,1)>=DATE(YEAR('Model inputs'!U67),MONTH('Model inputs'!U67),1)),DATE(2027,7,1)>=DATE(YEAR('Model inputs'!U67),MONTH('Model inputs'!U67),1),IF(DATE(YEAR('Model inputs'!U67),MONTH('Model inputs'!U67),1)="","",DATE(2027,7,1)>=DATE(YEAR('Model inputs'!U67),MONTH('Model inputs'!U67),1)))="",FALSE,IF(ISERROR(DATE(2027,7,1)>=DATE(YEAR('Model inputs'!U67),MONTH('Model inputs'!U67),1)),DATE(2027,7,1)>=DATE(YEAR('Model inputs'!U67),MONTH('Model inputs'!U67),1),IF(DATE(YEAR('Model inputs'!U67),MONTH('Model inputs'!U67),1)="","",DATE(2027,7,1)>=DATE(YEAR('Model inputs'!U67),MONTH('Model inputs'!U67),1)))),IF('Model inputs'!U75="","",'Model inputs'!U75),0) -> 2000 | M53: =IF(IF(IF(ISERROR(DATE(2027,8,1)>=DATE(YEAR('Model inputs'!U67),MONTH('Model inputs'!U67),1)),DATE(2027,8,1)>=DATE(YEAR('Model inputs'!U67),MONTH('Model inputs'!U67),1),IF(DATE(YEAR('Model inputs'!U67),MONTH('Model inputs'!U67),1)="","",DATE(2027,8,1)>=DATE(YEAR('Model inputs'!U67),MONTH('Model inputs'!U67),1)))="",FALSE,IF(ISERROR(DATE(2027,8,1)>=DATE(YEAR('Model inputs'!U67),MONTH('Model inputs'!U67),1)),DATE(2027,8,1)>=DATE(YEAR('Model inputs'!U67),MONTH('Model inputs'!U67),1),IF(DATE(YEAR('Model inputs'!U67),MONTH('Model inputs'!U67),1)="","",DATE(2027,8,1)>=DATE(YEAR('Model inputs'!U67),MONTH('Model inputs'!U67),1)))),IF('Model inputs'!U75="","",'Model inputs'!U75),0) -> 2000 | N53: =IF(IF(IF(ISERROR(DATE(2027,9,1)>=DATE(YEAR('Model inputs'!U67),MONTH('Model inputs'!U67),1)),DATE(2027,9,1)>=DATE(YEAR('Model inputs'!U67),MONTH('Model inputs'!U67),1),IF(DATE(YEAR('Model inputs'!U67),MONTH('Model inputs'!U67),1)="","",DATE(2027,9,1)>=DATE(YEAR('Model inputs'!U67),MONTH('Model inputs'!U67),1)))="",FALSE,IF(ISERROR(DATE(2027,9,1)>=DATE(YEAR('Model inputs'!U67),MONTH('Model inputs'!U67),1)),DATE(2027,9,1)>=DATE(YEAR('Model inputs'!U67),MONTH('Model inputs'!U67),1),IF(DATE(YEAR('Model inputs'!U67),MONTH('Model inputs'!U67),1)="","",DATE(2027,9,1)>=DATE(YEAR('Model inputs'!U67),MONTH('Model inputs'!U67),1)))),IF('Model inputs'!U75="","",'Model inputs'!U75),0) -> 2000 | O53: =IF(IF(IF(ISERROR(DATE(2027,10,1)>=DATE(YEAR('Model inputs'!U67),MONTH('Model inputs'!U67),1)),DATE(2027,10,1)>=DATE(YEAR('Model inputs'!U67),MONTH('Model inputs'!U67),1),IF(DATE(YEAR('Model inputs'!U67),MONTH('Model inputs'!U67),1)="","",DATE(2027,10,1)>=DATE(YEAR('Model inputs'!U67),MONTH('Model inputs'!U67),1)))="",FALSE,IF(ISERROR(DATE(2027,10,1)>=DATE(YEAR('Model inputs'!U67),MONTH('Model inputs'!U67),1)),DATE(2027,10,1)>=DATE(YEAR('Model inputs'!U67),MONTH('Model inputs'!U67),1),IF(DATE(YEAR('Model inputs'!U67),MONTH('Model inputs'!U67),1)="","",DATE(2027,10,1)>=DATE(YEAR('Model inputs'!U67),MONTH('Model inputs'!U67),1)))),IF('Model inputs'!U75="","",'Model inputs'!U75),0) -> 2000 | P53: =IF(IF(IF(ISERROR(DATE(2027,11,1)>=DATE(YEAR('Model inputs'!U67),MONTH('Model inputs'!U67),1)),DATE(2027,11,1)>=DATE(YEAR('Model inputs'!U67),MONTH('Model inputs'!U67),1),IF(DATE(YEAR('Model inputs'!U67),MONTH('Model inputs'!U67),1)="","",DATE(2027,11,1)>=DATE(YEAR('Model inputs'!U67),MONTH('Model inputs'!U67),1)))="",FALSE,IF(ISERROR(DATE(2027,11,1)>=DATE(YEAR('Model inputs'!U67),MONTH('Model inputs'!U67),1)),DATE(2027,11,1)>=DATE(YEAR('Model inputs'!U67),MONTH('Model inputs'!U67),1),IF(DATE(YEAR('Model inputs'!U67),MONTH('Model inputs'!U67),1)="","",DATE(2027,11,1)>=DATE(YEAR('Model inputs'!U67),MONTH('Model inputs'!U67),1)))),IF('Model inputs'!U75="","",'Model inputs'!U75),0) -> 2000 | Q53: =IF(IF(IF(ISERROR(DATE(2027,12,1)>=DATE(YEAR('Model inputs'!U67),MONTH('Model inputs'!U67),1)),DATE(2027,12,1)>=DATE(YEAR('Model inputs'!U67),MONTH('Model inputs'!U67),1),IF(DATE(YEAR('Model inputs'!U67),MONTH('Model inputs'!U67),1)="","",DATE(2027,12,1)>=DATE(YEAR('Model inputs'!U67),MONTH('Model inputs'!U67),1)))="",FALSE,IF(ISERROR(DATE(2027,12,1)>=DATE(YEAR('Model inputs'!U67),MONTH('Model inputs'!U67),1)),DATE(2027,12,1)>=DATE(YEAR('Model inputs'!U67),MONTH('Model inputs'!U67),1),IF(DATE(YEAR('Model inputs'!U67),MONTH('Model inputs'!U67),1)="","",DATE(2027,12,1)>=DATE(YEAR('Model inputs'!U67),MONTH('Model inputs'!U67),1)))),IF('Model inputs'!U75="","",'Model inputs'!U75),0) -> 2000 | R53: =IF(IF(IF(ISERROR(DATE(2028,1,1)>=DATE(YEAR('Model inputs'!U67),MONTH('Model inputs'!U67),1)),DATE(2028,1,1)>=DATE(YEAR('Model inputs'!U67),MONTH('Model inputs'!U67),1),IF(DATE(YEAR('Model inputs'!U67),MONTH('Model inputs'!U67),1)="","",DATE(2028,1,1)>=DATE(YEAR('Model inputs'!U67),MONTH('Model inputs'!U67),1)))="",FALSE,IF(ISERROR(DATE(2028,1,1)>=DATE(YEAR('Model inputs'!U67),MONTH('Model inputs'!U67),1)),DATE(2028,1,1)>=DATE(YEAR('Model inputs'!U67),MONTH('Model inputs'!U67),1),IF(DATE(YEAR('Model inputs'!U67),MONTH('Model inputs'!U67),1)="","",DATE(2028,1,1)>=DATE(YEAR('Model inputs'!U67),MONTH('Model inputs'!U67),1)))),IF('Model inputs'!U75="","",'Model inputs'!U75),0) -> 2000 | S53: =IF(IF(IF(ISERROR(DATE(2028,2,1)>=DATE(YEAR('Model inputs'!U67),MONTH('Model inputs'!U67),1)),DATE(2028,2,1)>=DATE(YEAR('Model inputs'!U67),MONTH('Model inputs'!U67),1),IF(DATE(YEAR('Model inputs'!U67),MONTH('Model inputs'!U67),1)="","",DATE(2028,2,1)>=DATE(YEAR('Model inputs'!U67),MONTH('Model inputs'!U67),1)))="",FALSE,IF(ISERROR(DATE(2028,2,1)>=DATE(YEAR('Model inputs'!U67),MONTH('Model inputs'!U67),1)),DATE(2028,2,1)>=DATE(YEAR('Model inputs'!U67),MONTH('Model inputs'!U67),1),IF(DATE(YEAR('Model inputs'!U67),MONTH('Model inputs'!U67),1)="","",DATE(2028,2,1)>=DATE(YEAR('Model inputs'!U67),MONTH('Model inputs'!U67),1)))),IF('Model inputs'!U75="","",'Model inputs'!U75),0) -> 2000 | T53: =IF(IF(IF(ISERROR(DATE(2028,3,1)>=DATE(YEAR('Model inputs'!U67),MONTH('Model inputs'!U67),1)),DATE(2028,3,1)>=DATE(YEAR('Model inputs'!U67),MONTH('Model inputs'!U67),1),IF(DATE(YEAR('Model inputs'!U67),MONTH('Model inputs'!U67),1)="","",DATE(2028,3,1)>=DATE(YEAR('Model inputs'!U67),MONTH('Model inputs'!U67),1)))="",FALSE,IF(ISERROR(DATE(2028,3,1)>=DATE(YEAR('Model inputs'!U67),MONTH('Model inputs'!U67),1)),DATE(2028,3,1)>=DATE(YEAR('Model inputs'!U67),MONTH('Model inputs'!U67),1),IF(DATE(YEAR('Model inputs'!U67),MONTH('Model inputs'!U67),1)="","",DATE(2028,3,1)>=DATE(YEAR('Model inputs'!U67),MONTH('Model inputs'!U67),1)))),IF('Model inputs'!U75="","",'Model inputs'!U75),0) -> 2000
A54: Founder payroll > Placeholder founder 2 | B54: ='Model inputs'!B16 -> 0 | C54: =IF(IF(IF(ISERROR(DATE(2026,10,1)>=DATE(YEAR('Model inputs'!U68),MONTH('Model inputs'!U68),1)),DATE(2026,10,1)>=DATE(YEAR('Model inputs'!U68),MONTH('Model inputs'!U68),1),IF(DATE(YEAR('Model inputs'!U68),MONTH('Model inputs'!U68),1)="","",DATE(2026,10,1)>=DATE(YEAR('Model inputs'!U68),MONTH('Model inputs'!U68),1)))="",FALSE,IF(ISERROR(DATE(2026,10,1)>=DATE(YEAR('Model inputs'!U68),MONTH('Model inputs'!U68),1)),DATE(2026,10,1)>=DATE(YEAR('Model inputs'!U68),MONTH('Model inputs'!U68),1),IF(DATE(YEAR('Model inputs'!U68),MONTH('Model inputs'!U68),1)="","",DATE(2026,10,1)>=DATE(YEAR('Model inputs'!U68),MONTH('Model inputs'!U68),1)))),IF('Model inputs'!U76="","",'Model inputs'!U76),0) -> 0 | D54: =IF(IF(IF(ISERROR(DATE(2026,11,1)>=DATE(YEAR('Model inputs'!U68),MONTH('Model inputs'!U68),1)),DATE(2026,11,1)>=DATE(YEAR('Model inputs'!U68),MONTH('Model inputs'!U68),1),IF(DATE(YEAR('Model inputs'!U68),MONTH('Model inputs'!U68),1)="","",DATE(2026,11,1)>=DATE(YEAR('Model inputs'!U68),MONTH('Model inputs'!U68),1)))="",FALSE,IF(ISERROR(DATE(2026,11,1)>=DATE(YEAR('Model inputs'!U68),MONTH('Model inputs'!U68),1)),DATE(2026,11,1)>=DATE(YEAR('Model inputs'!U68),MONTH('Model inputs'!U68),1),IF(DATE(YEAR('Model inputs'!U68),MONTH('Model inputs'!U68),1)="","",DATE(2026,11,1)>=DATE(YEAR('Model inputs'!U68),MONTH('Model inputs'!U68),1)))),IF('Model inputs'!U76="","",'Model inputs'!U76),0) -> 0 | E54: =IF(IF(IF(ISERROR(DATE(2026,12,1)>=DATE(YEAR('Model inputs'!U68),MONTH('Model inputs'!U68),1)),DATE(2026,12,1)>=DATE(YEAR('Model inputs'!U68),MONTH('Model inputs'!U68),1),IF(DATE(YEAR('Model inputs'!U68),MONTH('Model inputs'!U68),1)="","",DATE(2026,12,1)>=DATE(YEAR('Model inputs'!U68),MONTH('Model inputs'!U68),1)))="",FALSE,IF(ISERROR(DATE(2026,12,1)>=DATE(YEAR('Model inputs'!U68),MONTH('Model inputs'!U68),1)),DATE(2026,12,1)>=DATE(YEAR('Model inputs'!U68),MONTH('Model inputs'!U68),1),IF(DATE(YEAR('Model inputs'!U68),MONTH('Model inputs'!U68),1)="","",DATE(2026,12,1)>=DATE(YEAR('Model inputs'!U68),MONTH('Model inputs'!U68),1)))),IF('Model inputs'!U76="","",'Model inputs'!U76),0) -> 0 | F54: =IF(IF(IF(ISERROR(DATE(2027,1,1)>=DATE(YEAR('Model inputs'!U68),MONTH('Model inputs'!U68),1)),DATE(2027,1,1)>=DATE(YEAR('Model inputs'!U68),MONTH('Model inputs'!U68),1),IF(DATE(YEAR('Model inputs'!U68),MONTH('Model inputs'!U68),1)="","",DATE(2027,1,1)>=DATE(YEAR('Model inputs'!U68),MONTH('Model inputs'!U68),1)))="",FALSE,IF(ISERROR(DATE(2027,1,1)>=DATE(YEAR('Model inputs'!U68),MONTH('Model inputs'!U68),1)),DATE(2027,1,1)>=DATE(YEAR('Model inputs'!U68),MONTH('Model inputs'!U68),1),IF(DATE(YEAR('Model inputs'!U68),MONTH('Model inputs'!U68),1)="","",DATE(2027,1,1)>=DATE(YEAR('Model inputs'!U68),MONTH('Model inputs'!U68),1)))),IF('Model inputs'!U76="","",'Model inputs'!U76),0) -> 0 | G54: =IF(IF(IF(ISERROR(DATE(2027,2,1)>=DATE(YEAR('Model inputs'!U68),MONTH('Model inputs'!U68),1)),DATE(2027,2,1)>=DATE(YEAR('Model inputs'!U68),MONTH('Model inputs'!U68),1),IF(DATE(YEAR('Model inputs'!U68),MONTH('Model inputs'!U68),1)="","",DATE(2027,2,1)>=DATE(YEAR('Model inputs'!U68),MONTH('Model inputs'!U68),1)))="",FALSE,IF(ISERROR(DATE(2027,2,1)>=DATE(YEAR('Model inputs'!U68),MONTH('Model inputs'!U68),1)),DATE(2027,2,1)>=DATE(YEAR('Model inputs'!U68),MONTH('Model inputs'!U68),1),IF(DATE(YEAR('Model inputs'!U68),MONTH('Model inputs'!U68),1)="","",DATE(2027,2,1)>=DATE(YEAR('Model inputs'!U68),MONTH('Model inputs'!U68),1)))),IF('Model inputs'!U76="","",'Model inputs'!U76),0) -> 0 | H54: =IF(IF(IF(ISERROR(DATE(2027,3,1)>=DATE(YEAR('Model inputs'!U68),MONTH('Model inputs'!U68),1)),DATE(2027,3,1)>=DATE(YEAR('Model inputs'!U68),MONTH('Model inputs'!U68),1),IF(DATE(YEAR('Model inputs'!U68),MONTH('Model inputs'!U68),1)="","",DATE(2027,3,1)>=DATE(YEAR('Model inputs'!U68),MONTH('Model inputs'!U68),1)))="",FALSE,IF(ISERROR(DATE(2027,3,1)>=DATE(YEAR('Model inputs'!U68),MONTH('Model inputs'!U68),1)),DATE(2027,3,1)>=DATE(YEAR('Model inputs'!U68),MONTH('Model inputs'!U68),1),IF(DATE(YEAR('Model inputs'!U68),MONTH('Model inputs'!U68),1)="","",DATE(2027,3,1)>=DATE(YEAR('Model inputs'!U68),MONTH('Model inputs'!U68),1)))),IF('Model inputs'!U76="","",'Model inputs'!U76),0) -> 0 | I54: =IF(IF(IF(ISERROR(DATE(2027,4,1)>=DATE(YEAR('Model inputs'!U68),MONTH('Model inputs'!U68),1)),DATE(2027,4,1)>=DATE(YEAR('Model inputs'!U68),MONTH('Model inputs'!U68),1),IF(DATE(YEAR('Model inputs'!U68),MONTH('Model inputs'!U68),1)="","",DATE(2027,4,1)>=DATE(YEAR('Model inputs'!U68),MONTH('Model inputs'!U68),1)))="",FALSE,IF(ISERROR(DATE(2027,4,1)>=DATE(YEAR('Model inputs'!U68),MONTH('Model inputs'!U68),1)),DATE(2027,4,1)>=DATE(YEAR('Model inputs'!U68),MONTH('Model inputs'!U68),1),IF(DATE(YEAR('Model inputs'!U68),MONTH('Model inputs'!U68),1)="","",DATE(2027,4,1)>=DATE(YEAR('Model inputs'!U68),MONTH('Model inputs'!U68),1)))),IF('Model inputs'!U76="","",'Model inputs'!U76),0) -> 2000 | J54: =IF(IF(IF(ISERROR(DATE(2027,5,1)>=DATE(YEAR('Model inputs'!U68),MONTH('Model inputs'!U68),1)),DATE(2027,5,1)>=DATE(YEAR('Model inputs'!U68),MONTH('Model inputs'!U68),1),IF(DATE(YEAR('Model inputs'!U68),MONTH('Model inputs'!U68),1)="","",DATE(2027,5,1)>=DATE(YEAR('Model inputs'!U68),MONTH('Model inputs'!U68),1)))="",FALSE,IF(ISERROR(DATE(2027,5,1)>=DATE(YEAR('Model inputs'!U68),MONTH('Model inputs'!U68),1)),DATE(2027,5,1)>=DATE(YEAR('Model inputs'!U68),MONTH('Model inputs'!U68),1),IF(DATE(YEAR('Model inputs'!U68),MONTH('Model inputs'!U68),1)="","",DATE(2027,5,1)>=DATE(YEAR('Model inputs'!U68),MONTH('Model inputs'!U68),1)))),IF('Model inputs'!U76="","",'Model inputs'!U76),0) -> 2000 | K54: =IF(IF(IF(ISERROR(DATE(2027,6,1)>=DATE(YEAR('Model inputs'!U68),MONTH('Model inputs'!U68),1)),DATE(2027,6,1)>=DATE(YEAR('Model inputs'!U68),MONTH('Model inputs'!U68),1),IF(DATE(YEAR('Model inputs'!U68),MONTH('Model inputs'!U68),1)="","",DATE(2027,6,1)>=DATE(YEAR('Model inputs'!U68),MONTH('Model inputs'!U68),1)))="",FALSE,IF(ISERROR(DATE(2027,6,1)>=DATE(YEAR('Model inputs'!U68),MONTH('Model inputs'!U68),1)),DATE(2027,6,1)>=DATE(YEAR('Model inputs'!U68),MONTH('Model inputs'!U68),1),IF(DATE(YEAR('Model inputs'!U68),MONTH('Model inputs'!U68),1)="","",DATE(2027,6,1)>=DATE(YEAR('Model inputs'!U68),MONTH('Model inputs'!U68),1)))),IF('Model inputs'!U76="","",'Model inputs'!U76),0) -> 2000 | L54: =IF(IF(IF(ISERROR(DATE(2027,7,1)>=DATE(YEAR('Model inputs'!U68),MONTH('Model inputs'!U68),1)),DATE(2027,7,1)>=DATE(YEAR('Model inputs'!U68),MONTH('Model inputs'!U68),1),IF(DATE(YEAR('Model inputs'!U68),MONTH('Model inputs'!U68),1)="","",DATE(2027,7,1)>=DATE(YEAR('Model inputs'!U68),MONTH('Model inputs'!U68),1)))="",FALSE,IF(ISERROR(DATE(2027,7,1)>=DATE(YEAR('Model inputs'!U68),MONTH('Model inputs'!U68),1)),DATE(2027,7,1)>=DATE(YEAR('Model inputs'!U68),MONTH('Model inputs'!U68),1),IF(DATE(YEAR('Model inputs'!U68),MONTH('Model inputs'!U68),1)="","",DATE(2027,7,1)>=DATE(YEAR('Model inputs'!U68),MONTH('Model inputs'!U68),1)))),IF('Model inputs'!U76="","",'Model inputs'!U76),0) -> 2000 | M54: =IF(IF(IF(ISERROR(DATE(2027,8,1)>=DATE(YEAR('Model inputs'!U68),MONTH('Model inputs'!U68),1)),DATE(2027,8,1)>=DATE(YEAR('Model inputs'!U68),MONTH('Model inputs'!U68),1),IF(DATE(YEAR('Model inputs'!U68),MONTH('Model inputs'!U68),1)="","",DATE(2027,8,1)>=DATE(YEAR('Model inputs'!U68),MONTH('Model inputs'!U68),1)))="",FALSE,IF(ISERROR(DATE(2027,8,1)>=DATE(YEAR('Model inputs'!U68),MONTH('Model inputs'!U68),1)),DATE(2027,8,1)>=DATE(YEAR('Model inputs'!U68),MONTH('Model inputs'!U68),1),IF(DATE(YEAR('Model inputs'!U68),MONTH('Model inputs'!U68),1)="","",DATE(2027,8,1)>=DATE(YEAR('Model inputs'!U68),MONTH('Model inputs'!U68),1)))),IF('Model inputs'!U76="","",'Model inputs'!U76),0) -> 2000 | N54: =IF(IF(IF(ISERROR(DATE(2027,9,1)>=DATE(YEAR('Model inputs'!U68),MONTH('Model inputs'!U68),1)),DATE(2027,9,1)>=DATE(YEAR('Model inputs'!U68),MONTH('Model inputs'!U68),1),IF(DATE(YEAR('Model inputs'!U68),MONTH('Model inputs'!U68),1)="","",DATE(2027,9,1)>=DATE(YEAR('Model inputs'!U68),MONTH('Model inputs'!U68),1)))="",FALSE,IF(ISERROR(DATE(2027,9,1)>=DATE(YEAR('Model inputs'!U68),MONTH('Model inputs'!U68),1)),DATE(2027,9,1)>=DATE(YEAR('Model inputs'!U68),MONTH('Model inputs'!U68),1),IF(DATE(YEAR('Model inputs'!U68),MONTH('Model inputs'!U68),1)="","",DATE(2027,9,1)>=DATE(YEAR('Model inputs'!U68),MONTH('Model inputs'!U68),1)))),IF('Model inputs'!U76="","",'Model inputs'!U76),0) -> 2000 | O54: =IF(IF(IF(ISERROR(DATE(2027,10,1)>=DATE(YEAR('Model inputs'!U68),MONTH('Model inputs'!U68),1)),DATE(2027,10,1)>=DATE(YEAR('Model inputs'!U68),MONTH('Model inputs'!U68),1),IF(DATE(YEAR('Model inputs'!U68),MONTH('Model inputs'!U68),1)="","",DATE(2027,10,1)>=DATE(YEAR('Model inputs'!U68),MONTH('Model inputs'!U68),1)))="",FALSE,IF(ISERROR(DATE(2027,10,1)>=DATE(YEAR('Model inputs'!U68),MONTH('Model inputs'!U68),1)),DATE(2027,10,1)>=DATE(YEAR('Model inputs'!U68),MONTH('Model inputs'!U68),1),IF(DATE(YEAR('Model inputs'!U68),MONTH('Model inputs'!U68),1)="","",DATE(2027,10,1)>=DATE(YEAR('Model inputs'!U68),MONTH('Model inputs'!U68),1)))),IF('Model inputs'!U76="","",'Model inputs'!U76),0) -> 2000 | P54: =IF(IF(IF(ISERROR(DATE(2027,11,1)>=DATE(YEAR('Model inputs'!U68),MONTH('Model inputs'!U68),1)),DATE(2027,11,1)>=DATE(YEAR('Model inputs'!U68),MONTH('Model inputs'!U68),1),IF(DATE(YEAR('Model inputs'!U68),MONTH('Model inputs'!U68),1)="","",DATE(2027,11,1)>=DATE(YEAR('Model inputs'!U68),MONTH('Model inputs'!U68),1)))="",FALSE,IF(ISERROR(DATE(2027,11,1)>=DATE(YEAR('Model inputs'!U68),MONTH('Model inputs'!U68),1)),DATE(2027,11,1)>=DATE(YEAR('Model inputs'!U68),MONTH('Model inputs'!U68),1),IF(DATE(YEAR('Model inputs'!U68),MONTH('Model inputs'!U68),1)="","",DATE(2027,11,1)>=DATE(YEAR('Model inputs'!U68),MONTH('Model inputs'!U68),1)))),IF('Model inputs'!U76="","",'Model inputs'!U76),0) -> 2000 | Q54: =IF(IF(IF(ISERROR(DATE(2027,12,1)>=DATE(YEAR('Model inputs'!U68),MONTH('Model inputs'!U68),1)),DATE(2027,12,1)>=DATE(YEAR('Model inputs'!U68),MONTH('Model inputs'!U68),1),IF(DATE(YEAR('Model inputs'!U68),MONTH('Model inputs'!U68),1)="","",DATE(2027,12,1)>=DATE(YEAR('Model inputs'!U68),MONTH('Model inputs'!U68),1)))="",FALSE,IF(ISERROR(DATE(2027,12,1)>=DATE(YEAR('Model inputs'!U68),MONTH('Model inputs'!U68),1)),DATE(2027,12,1)>=DATE(YEAR('Model inputs'!U68),MONTH('Model inputs'!U68),1),IF(DATE(YEAR('Model inputs'!U68),MONTH('Model inputs'!U68),1)="","",DATE(2027,12,1)>=DATE(YEAR('Model inputs'!U68),MONTH('Model inputs'!U68),1)))),IF('Model inputs'!U76="","",'Model inputs'!U76),0) -> 2000 | R54: =IF(IF(IF(ISERROR(DATE(2028,1,1)>=DATE(YEAR('Model inputs'!U68),MONTH('Model inputs'!U68),1)),DATE(2028,1,1)>=DATE(YEAR('Model inputs'!U68),MONTH('Model inputs'!U68),1),IF(DATE(YEAR('Model inputs'!U68),MONTH('Model inputs'!U68),1)="","",DATE(2028,1,1)>=DATE(YEAR('Model inputs'!U68),MONTH('Model inputs'!U68),1)))="",FALSE,IF(ISERROR(DATE(2028,1,1)>=DATE(YEAR('Model inputs'!U68),MONTH('Model inputs'!U68),1)),DATE(2028,1,1)>=DATE(YEAR('Model inputs'!U68),MONTH('Model inputs'!U68),1),IF(DATE(YEAR('Model inputs'!U68),MONTH('Model inputs'!U68),1)="","",DATE(2028,1,1)>=DATE(YEAR('Model inputs'!U68),MONTH('Model inputs'!U68),1)))),IF('Model inputs'!U76="","",'Model inputs'!U76),0) -> 2000 | S54: =IF(IF(IF(ISERROR(DATE(2028,2,1)>=DATE(YEAR('Model inputs'!U68),MONTH('Model inputs'!U68),1)),DATE(2028,2,1)>=DATE(YEAR('Model inputs'!U68),MONTH('Model inputs'!U68),1),IF(DATE(YEAR('Model inputs'!U68),MONTH('Model inputs'!U68),1)="","",DATE(2028,2,1)>=DATE(YEAR('Model inputs'!U68),MONTH('Model inputs'!U68),1)))="",FALSE,IF(ISERROR(DATE(2028,2,1)>=DATE(YEAR('Model inputs'!U68),MONTH('Model inputs'!U68),1)),DATE(2028,2,1)>=DATE(YEAR('Model inputs'!U68),MONTH('Model inputs'!U68),1),IF(DATE(YEAR('Model inputs'!U68),MONTH('Model inputs'!U68),1)="","",DATE(2028,2,1)>=DATE(YEAR('Model inputs'!U68),MONTH('Model inputs'!U68),1)))),IF('Model inputs'!U76="","",'Model inputs'!U76),0) -> 2000 | T54: =IF(IF(IF(ISERROR(DATE(2028,3,1)>=DATE(YEAR('Model inputs'!U68),MONTH('Model inputs'!U68),1)),DATE(2028,3,1)>=DATE(YEAR('Model inputs'!U68),MONTH('Model inputs'!U68),1),IF(DATE(YEAR('Model inputs'!U68),MONTH('Model inputs'!U68),1)="","",DATE(2028,3,1)>=DATE(YEAR('Model inputs'!U68),MONTH('Model inputs'!U68),1)))="",FALSE,IF(ISERROR(DATE(2028,3,1)>=DATE(YEAR('Model inputs'!U68),MONTH('Model inputs'!U68),1)),DATE(2028,3,1)>=DATE(YEAR('Model inputs'!U68),MONTH('Model inputs'!U68),1),IF(DATE(YEAR('Model inputs'!U68),MONTH('Model inputs'!U68),1)="","",DATE(2028,3,1)>=DATE(YEAR('Model inputs'!U68),MONTH('Model inputs'!U68),1)))),IF('Model inputs'!U76="","",'Model inputs'!U76),0) -> 2000
